Workbook

Sheet Pedidos CardMarket
A1: Order Number | B1: Seller / Buyer | C1: Items | D1: Total Price | E1: Deliver Date | F1: Comentarios | G1: Tipo Operación | H1: TCG
A2: 1285152349 | B2: Distritozero-Bilbao | C2: 4 | D2: 4.41 | E2: 29.06.2026 | F2: Estado: Pagado; Vendedor: Distritozero-Bilbao; Envío repartido: 1.45 EUR | G2: Compra | H2: Magic The Gathering
A3: 1284988797 | B3: Mariluz92 | C3: 1 | D3: 1.7 | E3: 28.06.2026 | F3: Estado: Pagado; Vendedor: Mariluz92; Envío repartido: 1.45 EUR | G3: Compra | H3: Riftbound
A4: 1284988792 | B4: Oscar161 | C4: 1 | D4: 1.65 | E4: 28.06.2026 | F4: Estado: Pagado; Vendedor: Oscar161; Envío repartido: 1.45 EUR | G4: Compra | H4: Riftbound
A5: 1284986651 | B5: CartinhaBrilhante | C5: 16 | D5: 56.49 | E5: 28.06.2026 | F5: Estado: Pagado; Vendedor: CartinhaBrilhante; Envío repartido: 7.06 EUR | G5: Compra | H5: Riftbound
A6: 1284986254 | B6: PulpulFolker | C6: 11 | D6: 47.36 | E6: 28.06.2026 | F6: Estado: Pagado; Vendedor: PulpulFolker; Envío repartido: 7.06 EUR | G6: Compra | H6: Riftbound
A7: 1284983295 | B7: Cyrusi | C7: 2 | D7: 49.48 | E7: 28.06.2026 | F7: Estado: Pagado; Vendedor: Cyrusi; Envío repartido: 7.06 EUR | G7: Compra | H7: Riftbound
A8: 1284982979 | B8: Azgrand | C8: 1 | D8: 16.45 | E8: 28.06.2026 | F8: Estado: Pagado; Vendedor: Azgrand; Envío repartido: 1.45 EUR | G8: Compra | H8: Riftbound
A9: 1284982829 | B9: Canichev | C9: 2 | D9: 3.24 | E9: 28.06.2026 | F9: Estado: Pagado; Vendedor: Canichev; Envío repartido: 1.45 EUR | G9: Compra | H9: Riftbound
A10: 1284982814 | B10: Gorgonas87 | C10: 2 | D10: 2 | E10: 28.06.2026 | F10: Estado: Pagado; Vendedor: Gorgonas87; Envío repartido: 1.45 EUR | G10: Compra | H10: Riftbound
A11: 1284982624 | B11: ManaCore | C11: 2 | D11: 2.89 | E11: 28.06.2026 | F11: Estado: Pagado; Vendedor: ManaCore; Envío repartido: 1.45 EUR | G11: Compra | H11: Riftbound
A12: 1284982290 | B12: Silvela | C12: 5 | D12: 9.45 | E12: 28.06.2026 | F12: Estado: Pagado; Vendedor: Silvela; Envío repartido: 1.45 EUR | G12: Compra | H12: Riftbound
A13: 1284981397 | B13: Moria05 | C13: 8 | D13: 5.24 | E13: 28.06.2026 | F13: Estado: Pagado; Vendedor: Moria05; Envío repartido: 1.45 EUR | G13: Compra | H13: Riftbound
... A267: 1249026814 | B267: Aitorplanchas | C267: 4 | D267: 5.25 | E267: 02.01.2026 | F267: Estado: Recibido; Comprador: Aitorplanchas; Envío repartido: 1.45 EUR | G267: Venta | H267: Magic The Gathering
A268: WA-20260101-03 | B268: Willybizarre | C268: 1 | D268: 330 | E268: 01.01.2026 | F268: Estado: Importado desde Pedidos WhatsApp; origen manual; lineas: 1 | G268: Compra | H268: Magic The Gathering
A269: WA-20260101-02 | B269: Liddia7 | C269: 7 | D269: 31.5 | E269: 01.01.2026 | F269: Estado: Importado desde Pedidos WhatsApp; origen manual; lineas: 2 | G269: Compra | H269: Magic The Gathering
A270: WA-20260101-01 | B270: Bronhy | C270: 2 | D270: 700 | E270: 01.01.2026 | F270: Estado: Importado desde Pedidos WhatsApp; origen manual; lineas: 1 | G270: Compra | H270: Magic The Gathering
A271: 1248886513 | B271: Voldraek | C271: 12 | D271: 8.45 | E271: 01.01.2026 | F271: Estado: Recibido; Comprador: Voldraek; Envío repartido: 2.45 EUR | G271: Venta | H271: Magic The Gathering
A272: 1248630308 | B272: ChaugnarFaugn | C272: 2 | D272: 8.23 | E272: 30.12.2025 | F272: Estado: Recibido; Comprador: ChaugnarFaugn; Envío repartido: 1.33 EUR | G272: Venta | H272: Magic The Gathering
A273: 1248408245 | B273: Arkanum | C273: 2 | D273: 12.23 | E273: 29.12.2025 | F273: Estado: Recibido; Comprador: Arkanum; Envío repartido: 1.33 EUR | G273: Venta | H273: Magic The Gathering
A274: 1248289480 | B274: adriangd | C274: 5 | D274: 2.83 | E274: 28.12.2025 | F274: Estado: Recibido; Comprador: adriangd; Envío repartido: 1.33 EUR | G274: Venta | H274: Magic The Gathering
A275: 1248193531 | B275: salucks | C275: 2 | D275: 4.35 | E275: 28.12.2025 | F275: Estado: Recibido; Comprador: salucks; Envío repartido: 2.45 EUR | G275: Venta | H275: Magic The Gathering
A276: 1248066770 | B276: Javieeh | C276: 2 | D276: 9.78 | E276: 27.12.2025 | F276: Estado: Recibido; Comprador: Javieeh; Envío repartido: 1.33 EUR | G276: Venta | H276: Magic The Gathering
A277: 1247810200 | B277: enrico3547 | C277: 4 | D277: 55.4 | E277: 25.12.2025 | F277: Estado: Recibido; Comprador: enrico3547; Envío repartido: 7.60 EUR | G277: Venta | H277: Magic The Gathering
A278: 1247673365 | B278: Vitosellmagic | C278: 3 | D278: 25.18 | E278: 24.12.2025 | F278: Estado: Enviado; Vendedor: Vitosellmagic; Envío repartido: 1.33 EUR | G278: Compra | H278: Magic The Gathering
A279: 1247489911 | B279: Zeross | C279: 1 | D279: 4.4 | E279: 23.12.2025 | F279: Estado: Recibido; Comprador: Zeross; Envío repartido: 2.45 EUR | G279: Venta | H279: Magic The Gathering
A280: 1247478896 | B280: Mikota | C280: 1 | D280: 5.28 | E280: 23.12.2025 | F280: Estado: Recibido; Comprador: Mikota; Envío repartido: 1.33 EUR | G280: Venta | H280: Magic The Gathering
A281: 1247458671 | B281: Espartano88 | C281: 4 | D281: 12.53 | E281: 23.12.2025 | F281: Estado: Cancelado; Comprador: Espartano88; Envío repartido: 1.33 EUR | G281: Cancelado | H281: Magic The Gathering
A282: 1247427520 | B282: Larguiruncio | C282: 1 | D282: 1.58 | E282: 22.12.2025 | F282: Estado: Recibido; Comprador: Larguiruncio; Envío repartido: 1.33 EUR | G282: Venta | H282: Magic The Gathering
... A290: 1247229759 | B290: daktylus75 | C290: 4 | D290: 13.25 | E290: 21.12.2025 | F290: Estado: Recibido; Comprador: daktylus75; Envío repartido: 2.45 EUR | G290: Venta | H290: Magic The Gathering
A291: WA-20251220-01 | B291: 34628270693 | C291: 1 | D291: 310 | E291: 20.12.2025 | F291: Estado: Importado desde Pedidos WhatsApp; origen manual; lineas: 1 | G291: Compra | H291: Magic The Gathering
A292: 1247020450 | B292: Cuatrolo | C292: 1 | D292: 3.28 | E292: 19.12.2025 | F292: Estado: Recibido; Comprador: Cuatrolo; Envío repartido: 1.33 EUR | G292: Venta | H292: Magic The Gathering
A293: 1246809442 | B293: Racato | C293: 4 | D293: 87.4 | E293: 18.12.2025 | F293: Estado: Recibido; Comprador: Racato; Envío repartido: 7.60 EUR | G293: Venta | H293: Magic The Gathering
A294: 1246782050 | B294: Devian-Magic-Cards | C294: 5 | D294: 47.62 | E294: 18.12.2025 | F294: Estado: Enviado; Vendedor: Devian-Magic-Cards; Envío repartido: 5.93 EUR | G294: Compra | H294: Magic The Gathering
A295: 1246778711 | B295: botusfetus | C295: 4 | D295: 5.13 | E295: 18.12.2025 | F295: Estado: Recibido; Comprador: botusfetus; Envío repartido: 1.33 EUR | G295: Venta | H295: Magic The Gathering
A296: 1246502519 | B296: Aleixescurabello | C296: 1 | D296: 1.83 | E296: 16.12.2025 | F296: Estado: Recibido; Comprador: Aleixescurabello; Envío repartido: 1.33 EUR | G296: Venta | H296: Magic The Gathering
A297: 1246390151 | B297: Seath93 | C297: 1 | D297: 335.5 | E297: 15.12.2025 | F297: Estado: Enviado; Vendedor: Seath93; Envío repartido: 34.00 EUR | G297: Compra | H297: Magic The Gathering
A298: 1246389998 | B298: Rodrigbli | C298: 1 | D298: 1.53 | E298: 15.12.2025 | F298: Estado: Enviado; Vendedor: Rodrigbli; Envío repartido: 1.33 EUR | G298: Compra | H298: Magic The Gathering
A299: 1246130252 | B299: Devian-Magic-Cards | C299: 5 | D299: 47.62 | E299: 14.12.2025 | F299: Estado: Cancelado; Vendedor: Devian-Magic-Cards; Envío repartido: 5.93 EUR | G299: Cancelado | H299: Magic The Gathering
A300: 1246129625 | B300: Distritozero-San | C300: 3 | D300: 21 | E300: 14.12.2025 | F300: Estado: Cancelado en CardMarket; recogido en mano; Vendedor: Distritozero-San; Envío eliminado por recogida en mano: 5.50 EUR | G300: Cancelado | H300: Magic The Gathering
A301: 1246129492 | B301: Levodin | C301: 4 | D301: 24.29 | E301: 14.12.2025 | F301: Estado: Enviado; Vendedor: Levodin; Envío repartido: 1.33 EUR | G301: Compra | H301: Magic The Gathering
A302: 1245818358 | B302: Terricolous | C302: 4 | D302: 4.45 | E302: 12.12.2025 | F302: Estado: Recibido; Comprador: Terricolous; Envío repartido: 2.45 EUR | G302: Venta | H302: Magic The Gathering
A303: 1245614245 | B303: AdryKeo | C303: 1 | D303: 3.28 | E303: 10.12.2025 | F303: Estado: Recibido; Comprador: AdryKeo; Envío repartido: 1.33 EUR | G303: Venta | H303: Magic The Gathering
... A312: 1244635042 | B312: Mogoga | C312: 3 | D312: 4.18 | E312: 04.12.2025 | F312: Estado: Cancelado; Comprador: Mogoga; Envío repartido: 1.33 EUR | G312: Cancelado | H312: Magic The Gathering
A313: WA-20251203-03 | B313: Aner | C313: 1 | D313: 600 | E313: 03.12.2025 | F313: Estado: Importado desde Pedidos WhatsApp; origen manual; lineas: 1 | G313: Compra | H313: Magic The Gathering
A314: WA-20251203-02 | B314: 34688908486 | C314: 4 | D314: 11 | E314: 03.12.2025 | F314: Estado: Importado desde Pedidos WhatsApp; origen manual; lineas: 1 | G314: Venta | H314: Magic The Gathering
A315: WA-20251203-01 | B315: 34644320420 | C315: 4 | D315: 45 | E315: 03.12.2025 | F315: Estado: Importado desde Pedidos WhatsApp; origen manual; lineas: 1 | G315: Venta | H315: Magic The Gathering
A316: 1244475690 | B316: fconejero99 | C316: 1 | D316: 4.83 | E316: 03.12.2025 | F316: Estado: Recibido; Comprador: fconejero99; Envío repartido: 1.33 EUR | G316: Venta | H316: Magic The Gathering
A317: 1244398238 | B317: oirakam | C317: 1 | D317: 3.28 | E317: 03.12.2025 | F317: Estado: Recibido; Comprador: oirakam; Envío repartido: 1.33 EUR | G317: Venta | H317: Magic The Gathering
A318: 1244251179 | B318: TK-13 | C318: 1 | D318: 8.4 | E318: 02.12.2025 | F318: Estado: Recibido; Comprador: TK-13; Envío repartido: 2.45 EUR | G318: Venta | H318: Magic The Gathering
A319: 1244130136 | B319: Percy666 | C319: 1 | D319: 4.4 | E319: 02.12.2025 | F319: Estado: Recibido; Comprador: Percy666; Envío repartido: 2.45 EUR | G319: Venta | H319: Magic The Gathering
A320: WA-20251201-01 | B320: 34640601276 | C320: 1 | D320: 25 | E320: 01.12.2025 | F320: Estado: Importado desde Pedidos WhatsApp; origen manual; lineas: 1 | G320: Venta | H320: Magic The Gathering
A321: 1244111848 | B321: robleno | C321: 9 | D321: 3.58 | E321: 01.12.2025 | F321: Estado: Recibido; Comprador: robleno; Envío repartido: 1.33 EUR | G321: Venta | H321: Magic The Gathering
A322: 1243929990 | B322: Mariscot | C322: 1 | D322: 2.28 | E322: 30.11.2025 | F322: Estado: Recibido; Comprador: Mariscot; Envío repartido: 1.33 EUR | G322: Venta | H322: Magic The Gathering
A323: 1243812749 | B323: Gingi | C323: 1 | D323: 2.83 | E323: 30.11.2025 | F323: Estado: Recibido; Comprador: Gingi; Envío repartido: 1.33 EUR | G323: Venta | H323: Magic The Gathering
A324: 1243793386 | B324: Rul83 | C324: 4 | D324: 3.33 | E324: 30.11.2025 | F324: Estado: Recibido; Comprador: Rul83; Envío repartido: 1.33 EUR | G324: Venta | H324: Magic The Gathering
A325: 1243741253 | B325: Eriic05 | C325: 2 | D325: 5.23 | E325: 29.11.2025 | F325: Estado: Recibido; Comprador: Eriic05; Envío repartido: 1.33 EUR | G325: Venta | H325: Magic The Gathering
A326: 1243620987 | B326: Warscapez | C326: 4 | D326: 5.13 | E326: 29.11.2025 | F326: Estado: Recibido; Comprador: Warscapez; Envío repartido: 1.33 EUR | G326: Venta | H326: Magic The Gathering
A327: 1243580885 | B327: obsl1980 | C327: 4 | D327: 316.99 | E327: 28.11.2025 | F327: Estado: Enviado; Vendedor: obsl1980; Envío repartido: 15.49 EUR | G327: Compra | H327: Magic The Gathering
A328: 1243443704 | B328: Borium | C328: 1 | D328: 3.28 | E328: 28.11.2025 | F328: Estado: Cancelado; Comprador: Borium; Envío repartido: 1.33 EUR | G328: Cancelado | H328: Magic The Gathering
A329: 1243238844 | B329: Fenrir97 | C329: 1 | D329: 3.28 | E329: 26.11.2025 | F329: Estado: Recibido; Comprador: Fenrir97; Envío repartido: 1.33 EUR | G329: Venta | H329: Magic The Gathering
A330: 1243145592 | B330: Ferberino | C330: 1 | D330: 3.28 | E330: 26.11.2025 | F330: Estado: Recibido; Comprador: Ferberino; Envío repartido: 1.33 EUR | G330: Venta | H330: Magic The Gathering
A331: 1243134485 | B331: danicsb | C331: 2 | D331: 11.23 | E331: 26.11.2025 | F331: Estado: Recibido; Comprador: danicsb; Envío repartido: 1.33 EUR | G331: Venta | H331: Magic The Gathering
A332: 1243072138 | B332: Ganfar | C332: 4 | D332: 6.25 | E332: 25.11.2025 | F332: Estado: Recibido; Comprador: Ganfar; Envío repartido: 2.45 EUR | G332: Venta | H332: Magic The Gathering
... A516: 1220180784 | B516: YildumMTG | C516: 2 | D516: 9.31 | E516: 10.07.2025 | F516: Estado: Enviado; Vendedor: YildumMTG; Envío repartido: 1.33 EUR | G516: Compra | H516: Magic The Gathering
A517: WA-20250708-02 | B517: David Rivero | C517: 1 | D517: 85 | E517: 08.07.2025 | F517: Estado: Importado desde Pedidos WhatsApp; origen manual; lineas: 1 | G517: Compra | H517: Magic The Gathering
A518: WA-20250708-01 | B518: 34653388331 | C518: 16 | D518: 127.5 | E518: 08.07.2025 | F518: Estado: Importado desde Pedidos WhatsApp; origen manual; lineas: 7 | G518: Venta | H518: Magic The Gathering
A519: 1219880469 | B519: XAntonioX24 | C519: 2 | D519: 39.83 | E519: 08.07.2025 | F519: Estado: Recibido; Comprador: XAntonioX24; Envío repartido: 5.93 EUR | G519: Venta | H519: Magic The Gathering
A520: 1219822855 | B520: Fantastica | C520: 1 | D520: 8.32 | E520: 08.07.2025 | F520: Estado: Recibido; Comprador: Fantastica; Envío repartido: 1.33 EUR | G520: Venta | H520: Magic The Gathering
A521: 1219818110 | B521: Fantastica | C521: 2 | D521: 15.31 | E521: 08.07.2025 | F521: Estado: Recibido; Comprador: Fantastica; Envío repartido: 1.33 EUR | G521: Venta | H521: Magic The Gathering
A522: 1219230739 | B522: valdrich8 | C522: 1 | D522: 3.48 | E522: 04.07.2025 | F522: Estado: Enviado; Vendedor: valdrich8; Envío repartido: 1.33 EUR | G522: Compra | H522: Magic The Gathering
A523: 1219230717 | B523: Mazvigosl | C523: 3 | D523: 13.18 | E523: 04.07.2025 | F523: Estado: Enviado; Vendedor: Mazvigosl; Envío repartido: 1.33 EUR | G523: Compra | H523: Magic The Gathering
A524: 1219222787 | B524: Itaca | C524: 6 | D524: 22.03 | E524: 04.07.2025 | F524: Estado: Enviado; Vendedor: Itaca; Envío repartido: 1.33 EUR | G524: Compra | H524: Magic The Gathering
A525: 1219056744 | B525: ppinach | C525: 1 | D525: 8.28 | E525: 03.07.2025 | F525: Estado: Recibido; Comprador: ppinach; Envío repartido: 1.33 EUR | G525: Venta | H525: Magic The Gathering
A526: 1219054032 | B526: Pakkalicio | C526: 4 | D526: 31.86 | E526: 03.07.2025 | F526: Estado: Enviado; Vendedor: Pakkalicio; Envío repartido: 5.93 EUR | G526: Compra | H526: Magic The Gathering
A527: 1219053120 | B527: mundicomics | C527: 4 | D527: 32.06 | E527: 03.07.2025 | F527: Estado: Enviado; Vendedor: mundicomics; Envío repartido: 5.93 EUR | G527: Compra | H527: Magic The Gathering
A528: 1219048667 | B528: TEMPEST-STORE | C528: 2 | D528: 18.31 | E528: 03.07.2025 | F528: Estado: Enviado; Vendedor: TEMPEST-STORE; Envío repartido: 1.33 EUR | G528: Compra | H528: Magic The Gathering
A529: 1219047398 | B529: marconi | C529: 1 | D529: 16.33 | E529: 03.07.2025 | F529: Estado: Enviado; Vendedor: marconi; Envío repartido: 1.33 EUR | G529: Compra | H529: Magic The Gathering
A530: 1219047393 | B530: yeicocalderon | C530: 1 | D530: 15.26 | E530: 03.07.2025 | F530: Estado: Enviado; Vendedor: yeicocalderon; Envío repartido: 1.33 EUR | G530: Compra | H530: Magic The Gathering
... A551: 1215739166 | B551: Metropolis-Center | C551: 16 | D551: 51.86 | E551: 12.06.2025 | F551: Estado: Enviado; Vendedor: Metropolis-Center; Envío repartido: 5.99 EUR | G551: Compra | H551: Magic The Gathering
A552: WA-20250611-02 | B552: 34683281207 | C552: 1 | D552: 15 | E552: 11.06.2025 | F552: Estado: Importado desde Pedidos WhatsApp; origen manual; lineas: 1 | G552: Venta | H552: Magic The Gathering
A553: WA-20250611-01 | B553: 34676414055 | C553: 8 | D553: 10 | E553: 11.06.2025 | F553: Estado: Importado desde Pedidos WhatsApp; origen manual; lineas: 2 | G553: Venta | H553: Magic The Gathering
A554: 1215625358 | B554: digito1981 | C554: 1 | D554: 76.61 | E554: 11.06.2025 | F554: Estado: Enviado; Vendedor: digito1981; Envío repartido: 5.93 EUR | G554: Compra | H554: Magic The Gathering
A555: 1215625346 | B555: Eudinho | C555: 1 | D555: 71.58 | E555: 11.06.2025 | F555: Estado: Enviado; Vendedor: Eudinho; Envío repartido: 5.93 EUR | G555: Compra | H555: Magic The Gathering
A556: 1215579303 | B556: CalongeComics | C556: 4 | D556: 4.33 | E556: 11.06.2025 | F556: Estado: Enviado; Vendedor: CalongeComics; Envío repartido: 1.33 EUR | G556: Compra | H556: Magic The Gathering
A557: 1215578294 | B557: JupiterMadridNorte | C557: 20 | D557: 9.38 | E557: 11.06.2025 | F557: Estado: Enviado; Vendedor: JupiterMadridNorte; Envío repartido: 2.10 EUR | G557: Compra | H557: Magic The Gathering
A558: 1215387351 | B558: Martwalks | C558: 1 | D558: 17.28 | E558: 09.06.2025 | F558: Estado: Recibido; Comprador: Martwalks; Envío repartido: 1.33 EUR | G558: Venta | H558: Magic The Gathering
A559: 1215184874 | B559: Shark-Games | C559: 2 | D559: 2.33 | E559: 09.06.2025 | F559: Estado: Enviado; Vendedor: Shark-Games; Envío repartido: 1.33 EUR | G559: Compra | H559: Magic The Gathering
A560: 1215183701 | B560: TEMPEST-STORE | C560: 5 | D560: 42.06 | E560: 09.06.2025 | F560: Estado: Enviado; Vendedor: TEMPEST-STORE; Envío repartido: 5.93 EUR | G560: Compra | H560: Magic The Gathering
A561: 1215026902 | B561: valdrich8 | C561: 1 | D561: 76.63 | E561: 07.06.2025 | F561: Estado: Enviado; Vendedor: valdrich8; Envío repartido: 5.93 EUR | G561: Compra | H561: Magic The Gathering
A562: 1214932427 | B562: AlexStrachan | C562: 1 | D562: 76.63 | E562: 07.06.2025 | F562: Estado: Enviado; Vendedor: AlexStrachan; Envío repartido: 5.93 EUR | G562: Compra | H562: Magic The Gathering
A563: 1214667069 | B563: ElGansitoCaiman | C563: 8 | D563: 19.09 | E563: 05.06.2025 | F563: Estado: Enviado; Vendedor: ElGansitoCaiman; Envío repartido: 1.33 EUR | G563: Compra | H563: Magic The Gathering
A564: 1214237000 | B564: TiendaMulligan | C564: 2 | D564: 19.99 | E564: 02.06.2025 | F564: Estado: Enviado; Vendedor: TiendaMulligan; Envío repartido: 1.33 EUR | G564: Compra | H564: Magic The Gathering
A565: 1214178445 | B565: TEMPEST-STORE | C565: 7 | D565: 74.42 | E565: 02.06.2025 | F565: Estado: Enviado; Vendedor: TEMPEST-STORE; Envío repartido: 5.93 EUR | G565: Compra | H565: Magic The Gathering
... A607: 1209236015 | B607: Edi-88 | C607: 4 | D607: 22.25 | E607: 01.05.2025 | F607: Estado: Recibido; Comprador: Edi-88; Envío repartido: 2.45 EUR | G607: Venta | H607: Magic The Gathering
A608: WA-20250430-01 | B608: Japón | C608: 2 | D608: 130 | E608: 30.04.2025 | F608: Estado: Importado desde Pedidos WhatsApp; origen manual; lineas: 2 | G608: Compra | H608: Magic The Gathering
A609: 1209191236 | B609: pacofaco | C609: 4 | D609: 5.13 | E609: 30.04.2025 | F609: Estado: Recibido; Comprador: pacofaco; Envío repartido: 1.33 EUR | G609: Venta | H609: Magic The Gathering
A610: 1208867327 | B610: tobinono | C610: 4 | D610: 119.4 | E610: 28.04.2025 | F610: Estado: Recibido; Comprador: tobinono; Envío repartido: 7.60 EUR | G610: Venta | H610: Magic The Gathering
A611: 1208850807 | B611: DUAL-GAMES | C611: 2 | D611: 4.03 | E611: 28.04.2025 | F611: Estado: Enviado; Vendedor: DUAL-GAMES; Envío repartido: 1.33 EUR | G611: Compra | H611: Magic The Gathering
A612: 1208850772 | B612: Aramian | C612: 1 | D612: 2.18 | E612: 28.04.2025 | F612: Estado: Enviado; Vendedor: Aramian; Envío repartido: 1.33 EUR | G612: Compra | H612: Magic The Gathering
...

Sheet Colección
A1: Order Number | B1: Mes | C1: Año | D1: Date | E1: Seller / Buyer | F1: Card Name | G1: Edition | H1: Playset | I1: Language | J1: Unit Price | K1: Quantity | L1: Total | M1: Tipo Operación | N1: Precio de venta | O1: TCG
A2: 1164742270 | B2: Julio | C2: 2024 | D2: 45490.423 | E2: Knowny | F2: Phlage, Titan of Fire's Fury | G2: Modern Horizons 3 | H2: No | I2: Inglés | J2: 51.773333 | K2: 3 | L2: =J2*K2 -> 155.32 | M2: Venta | N2: 155.32 | O2: Magic The Gathering
A3: WA-20241001-01 | B3: Octubre | C3: 2024 | D3: 45566 | E3: 34633956985 | F3: Ocelot Pride | G3: Modern Horizons 3 | H3: Si | I3: Inglés | J3: 35.8175 | K3: 4 | L3: =J3*K3 -> 143.27 | M3: Venta | N3: 143.27 | O3: Magic The Gathering
A4: 1120143415 | B4: Julio | C4: 2023 | D4: 45134.502 | E4: NeverlandMTG | F4: Grief [Playset] | G4: Modern Horizons 2 | H4: No | I4: Inglés | J4: 130.28 | K4: 1 | L4: =J4*K4 -> 130.28 | M4: Venta | N4: 130.28 | O4: Magic The Gathering
A5: 1181893231 | B5: Noviembre | C5: 2024 | D5: 45626.486 | E5: Torkok | F5: Tamiyo, Inquisitive Student // Tamiyo, Seasoned Scholar | G5: Modern Horizons 2: Extras | H5: Si | I5: Inglés | J5: 31.767415 | K5: 4 | L5: =J5*K5 -> 127.06966 | M5: Venta | N5: 127.06966 | O5: Magic The Gathering
A6: 1208867327 | B6: Abril | C6: 2025 | D6: 45775.863 | E6: tobinono | F6: Parallax Wave | G6: Nemesis | H6: Si | I6: Japonés | J6: 29.85 | K6: 4 | L6: =J6*K6 -> 119.4 | M6: Venta | N6: 119.4 | O6: Magic The Gathering
A7: 1164075103 | B7: Julio | C7: 2024 | D7: 45475.811 | E7: rafa-1993-magic | F7: Atraxa, Grand Unifier [Playset] | G7: Phyrexia: All Will Be One | H7: No | I7: Inglés | J7: 105.39928 | K7: 1 | L7: =J7*K7 -> 105.39928 | M7: Venta | N7: 105.39928 | O7: Magic The Gathering
A8: 1164617239 | B8: Julio | C8: 2024 | D8: 45486.496 | E8: Oyea2000Hacha | F8: Phlage, Titan of Fire's Fury | G8: Modern Horizons 3 | H8: No | I8: Inglés | J8: 52.152551 | K8: 2 | L8: =J8*K8 -> 104.3051 | M8: Venta | N8: 104.3051 | O8: Magic The Gathering
A9: CVSALE-1121120101-01 | B9: Julio | C9: 2023 | D9: 45133.373 | E9: Venta asociada sin pedido identificado | F9: Ragavan, Nimble Pilferer | G9: Modern Horizons 2 | H9: Si | I9: Inglés | J9: 95.39 | K9: 1 | L9: =J9*K9 -> 95.39 | M9: Venta | N9: 95.39 | O9: Magic The Gathering
A10: 1179893768 | B10: Octubre | C10: 2024 | D10: 45596.443 | E10: Veilanof | F10: Ajani, Nacatl Pariah // Ajani, Nacatl Avenger | G10: Modern Horizons 3: Extras | H10: Si | I10: Inglés | J10: 22.3175 | K10: 4 | L10: =J10*K10 -> 89.27 | M10: Venta | N10: 89.27 | O10: Magic The Gathering
A11: 1284601698 | B11: Junio | C11: 2026 | D11: 46199.732 | E11: ElCige | F11: Snapcaster Mage | G11: Innistrad Remastered: Extras | H11: Si | I11: Japonés | J11: 21.96 | K11: 4 | L11: =J11*K11 -> 87.84 | M11: Venta | N11: 87.84 | O11: Magic The Gathering
A12: 1246809442 | B12: Diciembre | C12: 2025 | D12: 46020.428 | E12: Racato | F12: Riverpyre Verge | G12: Aetherdrift: Extras | H12: Si | I12: Inglés | J12: 21.85 | K12: 4 | L12: =J12*K12 -> 87.4 | M12: Venta | N12: 87.4 | O12: Magic The Gathering
A13: 1163758975 | B13: Julio | C13: 2024 | D13: 45476.34 | E13: davolcu | F13: Agatha's Soul Cauldron | G13: Wilds of Eldraine | H13: No | I13: Inglés | J13: 42.685 | K13: 2 | L13: =J13*K13 -> 85.37 | M13: Venta | N13: 85.37 | O13: Magic The Gathering
A14: 1164216706 | B14: Julio | C14: 2024 | D14: 45476.773 | E14: TheGoe | F14: Misty Rainforest [Playset] | G14: Modern Horizons 2 | H14: No | I14: Inglés | J14: 82.25 | K14: 1 | L14: =J14*K14 -> 82.25 | M14: Venta | N14: 82.25 | O14: Magic The Gathering
A15: 1146287863 | B15: Febrero | C15: 2024 | D15: 45345.518 | E15: kuerpo | F15: Sheoldred, the Apocalypse | G15: Dominaria United | H15: No | I15: Español | J15: 80.42 | K15: 1 | L15: =J15*K15 -> 80.42 | M15: Venta | N15: 80.42 | O15: Magic The Gathering
A16: 1178792325 | B16: Octubre | C16: 2024 | D16: 45582.813 | E16: SrBau | F16: Psychic Frog | G16: Modern Horizons 3 | H16: Si | I16: Inglés | J16: 17.3175 | K16: 4 | L16: =J16*K16 -> 69.27 | M16: Venta | N16: 69.27 | O16: Magic The Gathering
A17: WA-20250708-01 | B17: Julio | C17: 2025 | D17: 45846 | E17: 34653388331 | F17: Ravenous Baloth | G17: Onslaught | H17: No | I17: Japonés | J17: 17 | K17: 4 | L17: =J17*K17 -> 68 | M17: Venta | N17: 68 | O17: Magic The Gathering
A18: 1236601962 | B18: Octubre | C18: 2025 | D18: 45959.634 | E18: Kacon | F18: Starting Town | G18: Magic: The Gathering - FINAL FANTASY | H18: Si | I18: Inglés | J18: 16.8 | K18: 4 | L18: =J18*K18 -> 67.2 | M18: Venta | N18: 67.2 | O18: Magic The Gathering
A19: 1198292265 | B19: Febrero | C19: 2025 | D19: 45715.351 | E19: safetronik1985 | F19: Overlord of the Hauntwoods | G19: Duskmourn: House of Horror | H19: Si | I19: Inglés | J19: 16.3825 | K19: 4 | L19: =J19*K19 -> 65.53 | M19: Venta | N19: 65.53 | O19: Magic The Gathering
A20: 1163978024 | B20: Julio | C20: 2024 | D20: 45475.309 | E20: Macufa | F20: Arid Mesa [Playset] | G20: Modern Horizons 2 | H20: No | I20: Inglés | J20: 65.42 | K20: 1 | L20: =J20*K20 -> 65.42 | M20: Venta | N20: 65.42 | O20: Magic The Gathering
A21: 1162835755 | B21: Julio | C21: 2024 | D21: 45489.051 | E21: Noeperez | F21: Flooded Strand | G21: Khans of Tarkir | H21: Si | I21: Español | J21: 16.3175 | K21: 4 | L21: =J21*K21 -> 65.27 | M21: Venta | N21: 65.27 | O21: Magic The Gathering
A22: 1240414115 | B22: Noviembre | C22: 2025 | D22: 45974.51 | E22: Lorme87 | F22: Ulamog, the Defiler | G22: Modern Horizons 3 | H22: No | I22: Japonés | J22: 20.926667 | K22: 3 | L22: =J22*K22 -> 62.78 | M22: Venta | N22: 62.78 | O22: Magic The Gathering
A23: 1255482037 | B23: Febrero | C23: 2026 | D23: 46062.577 | E23: Kenoven | F23: Monument to Endurance | G23: Aetherdrift: Extras | H23: Si | I23: Inglés | J23: 15.5575 | K23: 4 | L23: =J23*K23 -> 62.23 | M23: Venta | N23: 62.23 | O23: Magic The Gathering
A24: 1231603567 | B24: Septiembre | C24: 2025 | D24: 45925.419 | E24: dacamcue | F24: Sheoldred, the Apocalypse | G24: Dominaria United | H24: No | I24: Español | J24: 60.88 | K24: 1 | L24: =J24*K24 -> 60.88 | M24: Venta | N24: 60.88 | O24: Magic The Gathering
A25: 1164973766 | B25: Julio | C25: 2024 | D25: 45482.461 | E25: danicsb | F25: Verdant Catacombs [Playset] | G25: Zendikar | H25: No | I25: Español | J25: 55.42 | K25: 1 | L25: =J25*K25 -> 55.42 | M25: Venta | N25: 55.42 | O25: Magic The Gathering
A26: 1163688955 | B26: Julio | C26: 2024 | D26: 45475.777 | E26: Metropolis-Center | F26: Shuko [Playset] | G26: Betrayers of Kamigawa | H26: No | I26: Español | J26: 55.42 | K26: 1 | L26: =J26*K26 -> 55.42 | M26: Venta | N26: 55.42 | O26: Magic The Gathering
A27: 1247810200 | B27: Enero | C27: 2026 | D27: 46028.597 | E27: enrico3547 | F27: Stormchaser's Talent | G27: Bloomburrow | H27: Si | I27: Inglés | J27: 13.85 | K27: 4 | L27: =J27*K27 -> 55.4 | M27: Venta | N27: 55.4 | O27: Magic The Gathering
A28: CVSALE-1142556696-01 | B28: Enero | C28: 2024 | D28: 45311.474 | E28: Venta asociada sin pedido identificado | F28: Scalding Tarn | G28: Modern Horizons 2 | H28: No | I28: Inglés | J28: 27.21 | K28: 2 | L28: =J28*K28 -> 54.42 | M28: Venta | N28: 54.42 | O28: Magic The Gathering
A29: 1166492703 | B29: Julio | C29: 2024 | D29: 45494.41 | E29: hotcoffeegg | F29: Steam Vents [Playset] | G29: Ravnica Remastered | H29: No | I29: Inglés | J29: 54.127775 | K29: 1 | L29: =J29*K29 -> 54.127775 | M29: Venta | N29: 54.127775 | O29: Magic The Gathering
A30: 1188500052 | B30: Enero | C30: 2025 | D30: 45664.515 | E30: Vintar | F30: The Meathook Massacre (V.2) | G30: Innistrad: Midnight Hunt: Promos | H30: No | I30: Inglés | J30: 26.524307 | K30: 2 | L30: =J30*K30 -> 53.048615 | M30: Venta | N30: 53.048615 | O30: Magic The Gathering
A31: 1164108421 | B31: Julio | C31: 2024 | D31: 45475.957 | E31: WORKSHOP12 | F31: Marsh Flats [Playset] | G31: Modern Horizons 2 | H31: No | I31: Inglés | J31: 52.829099 | K31: 1 | L31: =J31*K31 -> 52.829099 | M31: Venta | N31: 52.829099 | O31: Magic The Gathering
A32: 1176843547 | B32: Octubre | C32: 2024 | D32: 45576.409 | E32: J4ceBeleren | F32: Orcish Bowmasters | G32: The Lord of the Rings: Tales of Middle-earth | H32: No | I32: Inglés | J32: 52.25 | K32: 1 | L32: =J32*K32 -> 52.25 | M32: Venta | N32: 52.25 | O32: Magic The Gathering
A33: 1119858259 | B33: Julio | C33: 2023 | D33: 45129.326 | E33: GnarChikito | F33: Orcish Bowmasters | G33: The Lord of the Rings: Tales of Middle-earth | H33: No | I33: Inglés | J33: 49.15427 | K33: 1 | L33: =J33*K33 -> 49.15427 | M33: Venta | N33: 49.15427 | O33: Magic The Gathering
A34: CVSALE-1145214768-01 | B34: Febrero | C34: 2024 | D34: 45332.82 | E34: Venta asociada sin pedido identificado | F34: Breeding Pool | G34: Gatecrash | H34: No | I34: Inglés | J34: 47.62 | K34: 1 | L34: =J34*K34 -> 47.62 | M34: Venta | N34: 47.62 | O34: Magic The Gathering
A35: 1164108421 | B35: Julio | C35: 2024 | D35: 45475.957 | E35: WORKSHOP12 | F35: Goryo's Vengeance [Playset] | G35: Betrayers of Kamigawa | H35: No | I35: Español | J35: 47.540901 | K35: 1 | L35: =J35*K35 -> 47.540901 | M35: Venta | N35: 47.540901 | O35: Magic The Gathering
A36: 1166492703 | B36: Julio | C36: 2024 | D36: 45499.705 | E36: hotcoffeegg | F36: Ledger Shredder | G36: Streets of New Capenna: Extras | H36: No | I36: Inglés | J36: 15.808095 | K36: 3 | L36: =J36*K36 -> 47.424286 | M36: Venta | N36: 47.424286 | O36: Magic The Gathering
A37: 1165660431 | B37: Julio | C37: 2024 | D37: 45492.343 | E37: Jesval | F37: Phlage, Titan of Fire's Fury | G37: Modern Horizons 3 | H37: No | I37: Inglés | J37: 47.42 | K37: 1 | L37: =J37*K37 -> 47.42 | M37: Venta | N37: 47.42 | O37: Magic The Gathering
A38: 1119858259 | B38: Julio | C38: 2023 | D38: 45129.326 | E38: GnarChikito | F38: Orcish Bowmasters | G38: The Lord of the Rings: Tales of Middle-earth | H38: No | I38: Inglés | J38: 47.040108 | K38: 1 | L38: =J38*K38 -> 47.040108 | M38: Venta | N38: 47.040108 | O38: Magic The Gathering
A39: CVSALE-1130277526-01 | B39: Octubre | C39: 2023 | D39: 45208.902 | E39: Venta asociada sin pedido identificado | F39: Sacred Foundry | G39: Ravnica: City of Guilds | H39: No | I39: Inglés | J39: 22.92 | K39: 2 | L39: =J39*K39 -> 45.84 | M39: Venta | N39: 45.84 | O39: Magic The Gathering
A40: 1157257374 | B40: Mayo | C40: 2024 | D40: 45425.982 | E40: Kalashju | F40: Leyline of the Guildpact [Playset] | G40: Murders at Karlov Manor | H40: No | I40: Inglés | J40: 45.42 | K40: 1 | L40: =J40*K40 -> 45.42 | M40: Venta | N40: 45.42 | O40: Magic The Gathering
A41: WA-20251203-01 | B41: Diciembre | C41: 2025 | D41: 45994 | E41: 34644320420 | F41: Cosmogrand Zenith | G41: Edge of Eternities | H41: Si | I41: Inglés | J41: 11.25 | K41: 4 | L41: =J41*K41 -> 45 | M41: Venta | N41: 45 | O41: Magic The Gathering
A42: 1234897710 | B42: Octubre | C42: 2025 | D42: 45937.769 | E42: SchwarzesFleisch | F42: Deranged Hermit | G42: Urza's Legacy | H42: No | I42: Japonés | J42: 43.55 | K42: 1 | L42: =J42*K42 -> 43.55 | M42: Venta | N42: 43.55 | O42: Magic The Gathering
A43: 1245439549 | B43: Diciembre | C43: 2025 | D43: 46012.648 | E43: Enderu01 | F43: Lumra, Bellow of the Woods (V.1) | G43: Bloomburrow: Extras | H43: No | I43: Inglés | J43: 42.55 | K43: 1 | L43: =J43*K43 -> 42.55 | M43: Venta | N43: 42.55 | O43: Magic The Gathering
A44: 1194307080 | B44: Febrero | C44: 2025 | D44: 45699.485 | E44: DarkJaBBa | F44: Agatha's Soul Cauldron | G44: Wilds of Eldraine | H44: No | I44: Inglés | J44: 42.55 | K44: 1 | L44: =J44*K44 -> 42.55 | M44: Venta | N44: 42.55 | O44: Magic The Gathering
A45: 1131574286 | B45: Octubre | C45: 2023 | D45: 45229.634 | E45: dmnferreira | F45: Agatha's Soul Cauldron | G45: Wilds of Eldraine | H45: No | I45: Inglés | J45: 42.2 | K45: 1 | L45: =J45*K45 -> 42.2 | M45: Venta | N45: 42.2 | O45: Magic The Gathering
A46: 1200447336 | B46: Marzo | C46: 2025 | D46: 45725.004 | E46: FrankerG | F46: Dauthi Voidwalker | G46: Modern Horizons 2 | H46: Si | I46: Inglés | J46: 10.4325 | K46: 4 | L46: =J46*K46 -> 41.73 | M46: Venta | N46: 41.73 | O46: Magic The Gathering
A47: 1193092740 | B47: Enero | C47: 2025 | D47: 45681.491 | E47: MrDylan83 | F47: Thoughtseize | G47: Theros | H47: Si | I47: Inglés | J47: 10.4325 | K47: 4 | L47: =J47*K47 -> 41.73 | M47: Venta | N47: 41.73 | O47: Magic The Gathering
A48: CVSALE-1097748382-01 | B48: Diciembre | C48: 2022 | D48: 44911.369 | E48: Venta asociada sin pedido identificado | F48: Polluted Delta | G48: Khans of Tarkir | H48: No | I48: Español | J48: 20.17 | K48: 2 | L48: =J48*K48 -> 40.34 | M48: Venta | N48: 40.34 | O48: Magic The Gathering
A49: 1219880469 | B49: Julio | C49: 2025 | D49: 45853.658 | E49: XAntonioX24 | F49: Beza, the Bounding Spring | G49: Bloomburrow: Extras | H49: No | I49: Inglés | J49: 19.915 | K49: 2 | L49: =J49*K49 -> 39.83 | M49: Venta | N49: 39.83 | O49: Magic The Gathering
A50: 1178657400 | B50: Octubre | C50: 2024 | D50: 45595.673 | E50: NickDeme | F50: Flare of Denial | G50: Modern Horizons 3 | H50: Si | I50: Inglés | J50: 9.775 | K50: 4 | L50: =J50*K50 -> 39.1 | M50: Venta | N50: 39.1 | O50: Magic The Gathering
A51: CVSALE-1139327696-01 | B51: Diciembre | C51: 2023 | D51: 45284.475 | E51: Venta asociada sin pedido identificado | F51: Gix, Yawgmoth Praetor | G51: The Brothers' War | H51: No | I51: Inglés | J51: 19.335 | K51: 2 | L51: =J51*K51 -> 38.67 | M51: Venta | N51: 38.67 | O51: Magic The Gathering
A52: 1175688448 | B52: Septiembre | C52: 2024 | D52: 45561.783 | E52: Adammalti | F52: Consign to Memory [Playset] | G52: Modern Horizons 3 | H52: No | I52: Inglés | J52: 37.5 | K52: 1 | L52: =J52*K52 -> 37.5 | M52: Venta | N52: 37.5 | O52: Magic The Gathering
A53: 1185364801 | B53: Diciembre | C53: 2024 | D53: 45631.519 | E53: teff13 | F53: Fountainport | G53: Bloomburrow | H53: Si | I53: Inglés | J53: 9.3175 | K53: 4 | L53: =J53*K53 -> 37.27 | M53: Venta | N53: 37.27 | O53: Magic The Gathering
A54: 1160995310 | B54: Junio | C54: 2024 | D54: 45463.485 | E54: Maphys | F54: Bloodstained Mire | G54: Khans of Tarkir | H54: No | I54: Español | J54: 17.685 | K54: 2 | L54: =J54*K54 -> 35.37 | M54: Venta | N54: 35.37 | O54: Magic The Gathering
A55: 1185865223 | B55: Diciembre | C55: 2024 | D55: 45643.582 | E55: MTB123 | F55: Enduring Innocence | G55: Duskmourn: House of Horror | H55: Si | I55: Inglés | J55: 8.775 | K55: 4 | L55: =J55*K55 -> 35.1 | M55: Venta | N55: 35.1 | O55: Magic The Gathering
A56: 1111582930 | B56: Mayo | C56: 2023 | D56: 45050.343 | E56: JordiLara82 | F56: Fable of the Mirror-Breaker // Reflection of Kiki-Jiki | G56: Kamigawa: Neon Dynasty: Extras | H56: No | I56: Inglés | J56: 34.27 | K56: 1 | L56: =J56*K56 -> 34.27 | M56: Venta | N56: 34.27 | O56: Magic The Gathering
A57: 1191996305 | B57: Enero | C57: 2025 | D57: 45674.567 | E57: leocanalejo | F57: Recruiter of the Guard | G57: Modern Horizons 3 | H57: Si | I57: Inglés | J57: 8.4325 | K57: 4 | L57: =J57*K57 -> 33.73 | M57: Venta | N57: 33.73 | O57: Magic The Gathering
A58: 1166294148 | B58: Agosto | C58: 2024 | D58: 45506.305 | E58: Santilands | F58: Overgrown Tomb | G58: Return to Ravnica | H58: Si | I58: Chino-S | J58: 8.3346845 | K58: 4 | L58: =J58*K58 -> 33.338738 | M58: Venta | N58: 33.338738 | O58: Magic The Gathering
A59: 1118014908 | B59: Julio | C59: 2023 | D59: 45112.526 | E59: roggearne | F59: Cyclonic Rift | G59: Return to Ravnica | H59: No | I59: Inglés | J59: 32.75 | K59: 1 | L59: =J59*K59 -> 32.75 | M59: Venta | N59: 32.75 | O59: Magic The Gathering
A60: 1166294148 | B60: Julio | C60: 2024 | D60: 45492.784 | E60: Santilands | F60: Hallowed Fountain [Playset] | G60: Dissension | H60: No | I60: Español | J60: 31.976302 | K60: 1 | L60: =J60*K60 -> 31.976302 | M60: Venta | N60: 31.976302 | O60: Magic The Gathering
A61: 1166294148 | B61: Agosto | C61: 2024 | D61: 45506.305 | E61: Santilands | F61: Temple Garden [Playset] | G61: Return to Ravnica | H61: No | I61: Español | J61: 31.202975 | K61: 1 | L61: =J61*K61 -> 31.202975 | M61: Venta | N61: 31.202975 | O61: Magic The Gathering
A62: CVSALE-1125857031-02 | B62: Septiembre | C62: 2023 | D62: 45173.764 | E62: Venta asociada sin pedido identificado | F62: Blood Crypt | G62: Return to Ravnica | H62: No | I62: Inglés | J62: 14.538074 | K62: 2 | L62: =J62*K62 -> 29.076147 | M62: Venta | N62: 29.076147 | O62: Magic The Gathering
A63: CVSALE-1139234090-01 | B63: Diciembre | C63: 2023 | D63: 45283.795 | E63: Venta asociada sin pedido identificado | F63: Shattered Sanctum | G63: Innistrad: Crimson Vow | H63: Si | I63: Español | J63: 6.8425 | K63: 4 | L63: =J63*K63 -> 27.37 | M63: Venta | N63: 27.37 | O63: Magic The Gathering
A64: CVSALE-1127400018-01 | B64: Septiembre | C64: 2023 | D64: 45185.359 | E64: Venta asociada sin pedido identificado | F64: The Ozolith | G64: Ikoria: Lair of Behemoths | H64: No | I64: Japonés | J64: 13.17 | K64: 2 | L64: =J64*K64 -> 26.34 | M64: Venta | N64: 26.34 | O64: Magic The Gathering
A65: 1197512959 | B65: Febrero | C65: 2025 | D65: 45713.969 | E65: EndlessFate | F65: Zur, Eternal Schemer (V.1) | G65: Dominaria United: Extras | H65: No | I65: Inglés | J65: 8.7666667 | K65: 3 | L65: =J65*K65 -> 26.3 | M65: Venta | N65: 26.3 | O65: Magic The Gathering
A66: CVSALE-1183898242-01 | B66: Noviembre | C66: 2024 | D66: 45619.499 | E66: Venta asociada sin pedido identificado | F66: Overlord of the Mistmoors | G66: Duskmourn: House of Horror | H66: No | I66: Inglés | J66: 8.64 | K66: 3 | L66: =J66*K66 -> 25.92 | M66: Venta | N66: 25.92 | O66: Magic The Gathering
A67: 1237409267 | B67: Noviembre | C67: 2025 | D67: 45985.664 | E67: luigireyes892 | F67: Birthing Ritual | G67: Modern Horizons 3 | H67: Si | I67: Inglés | J67: 6.2825 | K67: 4 | L67: =J67*K67 -> 25.13 | M67: Venta | N67: 25.13 | O67: Magic The Gathering
A68: 1240546158 | B68: Noviembre | C68: 2025 | D68: 45975.562 | E68: awgodi | F68: Enduring Curiosity | G68: Duskmourn: House of Horror | H68: Si | I68: Japonés | J68: 6.2825 | K68: 4 | L68: =J68*K68 -> 25.13 | M68: Venta | N68: 25.13 | O68: Magic The Gathering
A69: 1163566856 | B69: Julio | C69: 2024 | D69: 45485.555 | E69: SaviourZero | F69: Wedding Announcement // Wedding Festivity | G69: Innistrad: Crimson Vow: Promos | H69: Si | I69: Inglés | J69: 6.255 | K69: 4 | L69: =J69*K69 -> 25.02 | M69: Venta | N69: 25.02 | O69: Magic The Gathering
A70: WA-20251201-01 | B70: Diciembre | C70: 2025 | D70: 45992 | E70: 34640601276 | F70: Goblin Sharpshooter | G70: Onslaught | H70: No | I70: Japonés | J70: 25 | K70: 1 | L70: =J70*K70 -> 25 | M70: Venta | N70: 25 | O70: Magic The Gathering
A71: 1178747825 | B71: Octubre | C71: 2024 | D71: 45587.484 | E71: Mazvigosl | F71: Suncleanser | G71: Core 2019 | H71: Si | I71: Inglés | J71: 6.2427016 | K71: 4 | L71: =J71*K71 -> 24.970806 | M71: Venta | N71: 24.970806 | O71: Magic The Gathering
A72: 1237155870 | B72: Octubre | C72: 2025 | D72: 45961.408 | E72: MVozila | F72: Gloomlake Verge | G72: Duskmourn: House of Horror: Extras | H72: No | I72: Inglés | J72: 12.175 | K72: 2 | L72: =J72*K72 -> 24.35 | M72: Venta | N72: 24.35 | O72: Magic The Gathering
A73: CVSALE-1097325133-01 | B73: Diciembre | C73: 2022 | D73: 44906.571 | E73: Venta asociada sin pedido identificado | F73: Wooded Foothills | G73: Khans of Tarkir | H73: No | I73: Español | J73: 12.17 | K73: 2 | L73: =J73*K73 -> 24.34 | M73: Venta | N73: 24.34 | O73: Magic The Gathering
A74: 1234987459 | B74: Octubre | C74: 2025 | D74: 45954.27 | E74: Ancor96 | F74: Amulet of Vigor | G74: Worldwake | H74: No | I74: Inglés | J74: 24.28 | K74: 1 | L74: =J74*K74 -> 24.28 | M74: Venta | N74: 24.28 | O74: Magic The Gathering
A75: 1171530906 | B75: Agosto | C75: 2024 | D75: 45532.032 | E75: xiterpepeferrone | F75: Roaming Throne (V.2) | G75: The Lost Caverns of Ixalan: Promos | H75: No | I75: Inglés | J75: 24.25 | K75: 1 | L75: =J75*K75 -> 24.25 | M75: Venta | N75: 24.25 | O75: Magic The Gathering
A76: 1159437793 | B76: Junio | C76: 2024 | D76: 45448.604 | E76: moloney | F76: Emeria's Call // Emeria, Shattered Skyclave [Playset] | G76: Zendikar Rising Expeditions | H76: No | I76: Inglés | J76: 24.25 | K76: 1 | L76: =J76*K76 -> 24.25 | M76: Venta | N76: 24.25 | O76: Magic The Gathering
A77: 1169967614 | B77: Agosto | C77: 2024 | D77: 45535.032 | E77: MagusDoVinhedo | F77: Virtue of Loyalty // Ardenvale Fealty | G77: Wilds of Eldraine: Extras | H77: No | I77: Inglés | J77: 12.1 | K77: 2 | L77: =J77*K77 -> 24.2 | M77: Venta | N77: 24.2 | O77: Magic The Gathering
A78: 1149091921 | B78: Marzo | C78: 2024 | D78: 45376.913 | E78: faof26 | F78: Raffine's Tower | G78: Streets of New Capenna | H78: No | I78: Inglés | J78: 12.1 | K78: 2 | L78: =J78*K78 -> 24.2 | M78: Venta | N78: 24.2 | O78: Magic The Gathering
A79: 1234193549 | B79: Octubre | C79: 2025 | D79: 45944.331 | E79: erreme2121 | F79: Amulet of Vigor | G79: Worldwake | H79: No | I79: Inglés | J79: 23.28 | K79: 1 | L79: =J79*K79 -> 23.28 | M79: Venta | N79: 23.28 | O79: Magic The Gathering
A80: 1232760932 | B80: Octubre | C80: 2025 | D80: 45932.675 | E80: alextormento | F80: Amulet of Vigor | G80: Worldwake | H80: No | I80: Español | J80: 23.28 | K80: 1 | L80: =J80*K80 -> 23.28 | M80: Venta | N80: 23.28 | O80: Magic The Gathering
A81: 1166866080 | B81: Julio | C81: 2024 | D81: 45496.94 | E81: saiman14 | F81: Godless Shrine | G81: Gatecrash | H81: No | I81: Italiano | J81: 7.7166667 | K81: 3 | L81: =J81*K81 -> 23.15 | M81: Venta | N81: 23.15 | O81: Magic The Gathering
A82: 1187236864 | B82: Diciembre | C82: 2024 | D82: 45653.024 | E82: maikyhateyou | F82: Teferi, Hero of Dominaria | G82: Dominaria | H82: No | I82: Inglés | J82: 11.56 | K82: 2 | L82: =J82*K82 -> 23.12 | M82: Venta | N82: 23.12 | O82: Magic The Gathering
A83: CVSALE-1097268072-01 | B83: Diciembre | C83: 2022 | D83: 44905.8 | E83: Venta asociada sin pedido identificado | F83: Malakir Rebirth // Malakir Mire | G83: Zendikar Rising | H83: Si | I83: Japonés | J83: 5.6889034 | K83: 4 | L83: =J83*K83 -> 22.755614 | M83: Venta | N83: 22.755614 | O83: Magic The Gathering
A84: 1238778886 | B84: Noviembre | C84: 2025 | D84: 45975.669 | E84: Kurgankurgan | F84: Azure Beastbinder | G84: Bloomburrow: Extras | H84: No | I84: Inglés | J84: 11.175 | K84: 2 | L84: =J84*K84 -> 22.35 | M84: Venta | N84: 22.35 | O84: Magic The Gathering
A85: 1190024451 | B85: Enero | C85: 2025 | D85: 45662.388 | E85: Nighthaze7170 | F85: Caretaker's Talent | G85: Bloomburrow | H85: No | I85: Inglés | J85: 11.175 | K85: 2 | L85: =J85*K85 -> 22.35 | M85: Venta | N85: 22.35 | O85: Magic The Gathering
A86: 1241565486 | B86: Noviembre | C86: 2025 | D86: 45985.642 | E86: Kevin9990 | F86: Smuggler's Surprise | G86: Outlaws of Thunder Junction | H86: Si | I86: Inglés | J86: 5.5625 | K86: 4 | L86: =J86*K86 -> 22.25 | M86: Venta | N86: 22.25 | O86: Magic The Gathering
A87: 1209236015 | B87: Mayo | C87: 2025 | D87: 45778.076 | E87: Edi-88 | F87: Dryad of the Ilysian Grove | G87: Theros Beyond Death | H87: Si | I87: Inglés | J87: 5.5625 | K87: 4 | L87: =J87*K87 -> 22.25 | M87: Venta | N87: 22.25 | O87: Magic The Gathering
A88: CVSALE-1107026406-01 | B88: Marzo | C88: 2023 | D88: 45000.078 | E88: Venta asociada sin pedido identificado | F88: Teferi, Time Raveler | G88: War of the Spark | H88: No | I88: Japonés | J88: 11.07 | K88: 2 | L88: =J88*K88 -> 22.14 | M88: Venta | N88: 22.14 | O88: Magic The Gathering
A89: 1124619405 | B89: Septiembre | C89: 2023 | D89: 45175.779 | E89: BigFabio91 | F89: Palantír of Orthanc | G89: The Lord of the Rings: Tales of Middle-earth | H89: No | I89: Inglés | J89: 22.05 | K89: 1 | L89: =J89*K89 -> 22.05 | M89: Venta | N89: 22.05 | O89: Magic The Gathering
A90: 1164617239 | B90: Julio | C90: 2024 | D90: 45486.496 | E90: Oyea2000Hacha | F90: Nethergoyf | G90: Modern Horizons 3 | H90: No | I90: Inglés | J90: 21.873793 | K90: 1 | L90: =J90*K90 -> 21.873793 | M90: Venta | N90: 21.873793 | O90: Magic The Gathering
A91: 1257556326 | B91: Febrero | C91: 2026 | D91: 46068.357 | E91: Warscapez | F91: Caves of Koilos | G91: Apocalypse | H91: No | I91: Chino-S | J91: 10.675 | K91: 2 | L91: =J91*K91 -> 21.35 | M91: Venta | N91: 21.35 | O91: Magic The Gathering
A92: 1185794477 | B92: Diciembre | C92: 2024 | D92: 45632.42 | E92: Jagago | F92: Chalice of the Void | G92: Mirrodin | H92: No | I92: Inglés | J92: 21.17 | K92: 1 | L92: =J92*K92 -> 21.17 | M92: Venta | N92: 21.17 | O92: Magic The Gathering
A93: 1157350742 | B93: Mayo | C93: 2024 | D93: 45433.562 | E93: FigureSevilla | F93: Valki, God of Lies // Tibalt, Cosmic Impostor | G93: Kaldheim | H93: No | I93: Inglés | J93: 10.56 | K93: 2 | L93: =J93*K93 -> 21.12 | M93: Venta | N93: 21.12 | O93: Magic The Gathering
A94: 1188485592 | B94: Enero | C94: 2025 | D94: 45669.964 | E94: SrGekota | F94: Flame of Anor | G94: The Lord of the Rings: Tales of Middle-earth | H94: Si | I94: Inglés | J94: 5.255 | K94: 4 | L94: =J94*K94 -> 21.02 | M94: Venta | N94: 21.02 | O94: Magic The Gathering
A95: 1240764273 | B95: Noviembre | C95: 2025 | D95: 45973.018 | E95: Warscapez | F95: Cunning Wish | G95: Judgment | H95: Si | I95: Inglés | J95: 5.2325 | K95: 4 | L95: =J95*K95 -> 20.93 | M95: Venta | N95: 20.93 | O95: Magic The Gathering
A96: CVSALE-1121120052-01 | B96: Julio | C96: 2023 | D96: 45133.373 | E96: Venta asociada sin pedido identificado | F96: Seasoned Pyromancer | G96: Modern Horizons | H96: Si | I96: Inglés | J96: 5.135 | K96: 4 | L96: =J96*K96 -> 20.54 | M96: Venta | N96: 20.54 | O96: Magic The Gathering
A97: WA-20250708-01 | B97: Julio | C97: 2025 | D97: 45846 | E97: 34653388331 | F97: Cursed Totem | G97: Mirage | H97: No | I97: Japonés | J97: 20 | K97: 1 | L97: =J97*K97 -> 20 | M97: Venta | N97: 20 | O97: Magic The Gathering
A98: 1158670738 | B98: Junio | C98: 2024 | D98: 45447.532 | E98: Shifteris | F98: Scion of Draco | G98: The List | H98: No | I98: Inglés | J98: 6.525 | K98: 3 | L98: =J98*K98 -> 19.575 | M98: Venta | N98: 19.575 | O98: Magic The Gathering
A99: 1239427732 | B99: Noviembre | C99: 2025 | D99: 45974.664 | E99: Vladitsv | F99: Haliya, Guided by Light | G99: Edge of Eternities: Extras | H99: Si | I99: Inglés | J99: 4.8325 | K99: 4 | L99: =J99*K99 -> 19.33 | M99: Venta | N99: 19.33 | O99: Magic The Gathering
A100: 1240558130 | B100: Noviembre | C100: 2025 | D100: 45978.648 | E100: CaballeroLuna | F100: Phyrexian Tower | G100: Modern Horizons 3 | H100: No | I100: Inglés | J100: 19.28 | K100: 1 | L100: =J100*K100 -> 19.28 | M100: Venta | N100: 19.28 | O100: Magic The Gathering
...

Sheet Tablas
A1: Tipo Operación | B1: Compra | D1: Etiquetas de fila | E1: Suma de Total | G1: Tipo Operación | H1: Compra | L1: Tipo Operación | M1: Compra | O1: Tipo Operación | P1: Compra
D2: Compra | E2: 39622.374
A3: Etiquetas de fila | B3: Suma de Total | D3: Venta | E3: 7217.9134 | G3: Etiquetas de fila | H3: Suma de Total | I3: Suma de Quantity | L3: Etiquetas de fila | M3: Suma de Total | O3: Etiquetas de fila | P3: Suma de Total
A4: 2022 | B4: 3852.76 | D4: (en blanco) | G4: Modern Horizons 2: Extras | H4: 2246.7577 | I4: 145 | L4: City of Traitors | M4: 1293.97 | O4: Magic The Gathering | P4: 35620.341
A5: 2023 | B5: 6353.4336 | D5: Total general | E5: 46840.288 | G5: Unleashed | H5: 1759.3655 | I5: 163 | L5: Serra's Sanctum | M5: 1030 | O5: One Piece | P5: 334.62386
A6: 2024 | B6: 10771.94 | G6: Modern Horizons 3 | H6: 1489.2334 | I6: 265 | L6: Collector Booster Box The Hobbit | M6: 899.9 | O6: Riftbound | P6: 3667.41
A7: 2025 | B7: 10887.041 | G7: Exodus | H7: 1327.3305 | I7: 9 | L7: Underground Sea | M7: 600 | O7: Total general | P7: 39622.374
A8: 2026 | B8: 7757.2 | G8: Modern Horizons 3: Extras | H8: 1316.4214 | I8: 123 | L8: Unleashed Booster Box Case (6x) | M8: 590
A9: Total general | B9: 39622.374 | G9: The Lord of the Rings: Tales of Middle-earth | H9: 1260.9508 | I9: 266 | L9: Scrubland | M9: 425
G10: Urza's Saga | H10: 1128.7762 | I10: 71 | L10: Flooded Strand | M10: 393.35598
G11: Revised | H11: 1025 | I11: 3 | L11: Vivi Ornitier (V.1) | M11: 324.79
G12: Onslaught | H12: 1002.0291 | I12: 39 | L12: Wooded Foothills | M12: 323.41573
G13: Modern Horizons 2 | H13: 994.97726 | I13: 173 | L13: Chrome Mox | M13: 315.49
G14: The Hobbit | H14: 899.9 | I14: 2 | L14: Mox Opal | M14: 296.72727
G15: Fourth Edition: Black Bordered | H15: 737.84364 | I15: 103 | L15: Orcish Bowmasters | M15: 272.65
G16: Spiritforged | H16: 683.23768 | I16: 135 | L16: Bloodstained Mire | M16: 268.37573
G17: Origins | H17: 643.5869 | I17: 121 | L17: Agatha's Soul Cauldron | M17: 266.25
G18: Time Spiral Remastered: Extras | H18: 571.77355 | I18: 113 | L18: Arcane Box Set | M18: 237.57917
G19: Origins: Promos | H19: 554.98917 | I19: 6 | L19: Worlds Bundle 2025 | M19: 236
G20: Double Masters 2022: Extras | H20: 459.8881 | I20: 66 | L20: Ocelot Pride (V.1) | M20: 232.96279
G21: Modern Horizons | H21: 457.08676 | I21: 97 | L21: Fury [Playset] | M21: 223.7
... G34: Total general | H34: 22939.997 | I34: 2332 | L34: Scalding Tarn (V.1) | M34: 174.1082
L35: Misty Rainforest (V.1) | M35: 171.25565
L36: Nethergoyf | M36: 167.6
L37: Teferi, Time Raveler | M37: 162.89944
L38: Prismatic Vista (V.1) | M38: 160.55
L39: Wrenn and Six (V.1) | M39: 154.05
L40: Amulet of Vigor | M40: 152.69
L41: Baited Hook | M41: 150.63475
L42: Stifle | M42: 150
L43: Psychic Frog (V.1) | M43: 149.30258
L44: Subtlety | M44: 147.06026
L45: Sephiroth, Fabled SOLDIER // Sephiroth, One-Winged Angel (V.1) | M45: 146.84
L46: Windswept Heath [Playset] | M46: 145.47
... L54: Total general | M54: 13619.969

Sheet Graficos Legacy
A1: Dashboard actualizado con Compra y Venta separadas
A3: Gasto total mensual | J3: Resumen por TCG
A4: Mes | B4: Suma de Total | E4: Lineas coleccion | F4: =COUNTA(Colección!$A$2:$A$10001) -> 3857 | J4: TCG | K4: Quantity compra | L4: Total compra | M4: Precio venta
A5: =YEAR(DATE(2026,6,1))&"-"&RIGHT("0"&MONTH(DATE(2026,6,1)),2)&" "&CHOOSE(MONTH(DATE(2026,6,1)),"enero","febrero","marzo","abril","mayo","junio","julio","agosto","septiembre","octubre","noviembre","diciembre") -> 2026-06 junio | B5: =SUMIFS(Colección!$L$2:$L$10001,Colección!$M$2:$M$10001,"Compra",Colección!$D$2:$D$10001,">="&DATE(2026,6,1),Colección!$D$2:$D$10001,"<"&DATE(2026,7,1)) -> 3510.83 | E5: Lineas Compra | F5: =COUNTIF(Colección!$M$2:$M$10001,"Compra") -> 3287 | J5: ="Magic The Gathering" -> Magic The Gathering | K5: =IF($J5="","",SUMIFS(Colección!$K$2:$K$10001,Colección!$O$2:$O$10001,$J5,Colección!$M$2:$M$10001,"Compra")) -> 6337 | L5: =IF($J5="","",SUMIFS(Colección!$L$2:$L$10001,Colección!$O$2:$O$10001,$J5,Colección!$M$2:$M$10001,"Compra")) -> 35680.341 | M5: =IF($J5="","",SUMIFS(Colección!$N$2:$N$10001,Colección!$O$2:$O$10001,$J5,Colección!$M$2:$M$10001,"Venta")) -> 7222.779
A6: =YEAR(DATE(2026,5,1))&"-"&RIGHT("0"&MONTH(DATE(2026,5,1)),2)&" "&CHOOSE(MONTH(DATE(2026,5,1)),"enero","febrero","marzo","abril","mayo","junio","julio","agosto","septiembre","octubre","noviembre","diciembre") -> 2026-05 mayo | B6: =SUMIFS(Colección!$L$2:$L$10001,Colección!$M$2:$M$10001,"Compra",Colección!$D$2:$D$10001,">="&DATE(2026,5,1),Colección!$D$2:$D$10001,"<"&DATE(2026,6,1)) -> 1230.3 | E6: Lineas Venta | F6: =COUNTIF(Colección!$M$2:$M$10001,"Venta") -> 570 | J6: ="Riftbound" -> Riftbound | K6: =IF($J6="","",SUMIFS(Colección!$K$2:$K$10001,Colección!$O$2:$O$10001,$J6,Colección!$M$2:$M$10001,"Compra")) -> 429 | L6: =IF($J6="","",SUMIFS(Colección!$L$2:$L$10001,Colección!$O$2:$O$10001,$J6,Colección!$M$2:$M$10001,"Compra")) -> 3667.41 | M6: =IF($J6="","",SUMIFS(Colección!$N$2:$N$10001,Colección!$O$2:$O$10001,$J6,Colección!$M$2:$M$10001,"Venta")) -> 0
A7: =YEAR(DATE(2026,4,1))&"-"&RIGHT("0"&MONTH(DATE(2026,4,1)),2)&" "&CHOOSE(MONTH(DATE(2026,4,1)),"enero","febrero","marzo","abril","mayo","junio","julio","agosto","septiembre","octubre","noviembre","diciembre") -> 2026-04 abril | B7: =SUMIFS(Colección!$L$2:$L$10001,Colección!$M$2:$M$10001,"Compra",Colección!$D$2:$D$10001,">="&DATE(2026,4,1),Colección!$D$2:$D$10001,"<"&DATE(2026,5,1)) -> 27.76 | E7: Gasto compra total | F7: =SUMIFS(Colección!$L$2:$L$10001,Colección!$M$2:$M$10001,"Compra") -> 39682.374 | J7: ="One Piece" -> One Piece | K7: =IF($J7="","",SUMIFS(Colección!$K$2:$K$10001,Colección!$O$2:$O$10001,$J7,Colección!$M$2:$M$10001,"Compra")) -> 373 | L7: =IF($J7="","",SUMIFS(Colección!$L$2:$L$10001,Colección!$O$2:$O$10001,$J7,Colección!$M$2:$M$10001,"Compra")) -> 334.62386 | M7: =IF($J7="","",SUMIFS(Colección!$N$2:$N$10001,Colección!$O$2:$O$10001,$J7,Colección!$M$2:$M$10001,"Venta")) -> 19.47
A8: =YEAR(DATE(2026,3,1))&"-"&RIGHT("0"&MONTH(DATE(2026,3,1)),2)&" "&CHOOSE(MONTH(DATE(2026,3,1)),"enero","febrero","marzo","abril","mayo","junio","julio","agosto","septiembre","octubre","noviembre","diciembre") -> 2026-03 marzo | B8: =SUMIFS(Colección!$L$2:$L$10001,Colección!$M$2:$M$10001,"Compra",Colección!$D$2:$D$10001,">="&DATE(2026,3,1),Colección!$D$2:$D$10001,"<"&DATE(2026,4,1)) -> 241.54 | E8: Importe venta total | F8: =SUMIFS(Colección!$N$2:$N$10001,Colección!$M$2:$M$10001,"Venta") -> 7242.249
A9: =YEAR(DATE(2026,2,1))&"-"&RIGHT("0"&MONTH(DATE(2026,2,1)),2)&" "&CHOOSE(MONTH(DATE(2026,2,1)),"enero","febrero","marzo","abril","mayo","junio","julio","agosto","septiembre","octubre","noviembre","diciembre") -> 2026-02 febrero | B9: =SUMIFS(Colección!$L$2:$L$10001,Colección!$M$2:$M$10001,"Compra",Colección!$D$2:$D$10001,">="&DATE(2026,2,1),Colección!$D$2:$D$10001,"<"&DATE(2026,3,1)) -> 358.21 | E9: Lineas Cancelado | F9: =COUNTIF(Colección!$M$2:$M$10001,"Cancelado") -> 0
A10: =YEAR(DATE(2026,1,1))&"-"&RIGHT("0"&MONTH(DATE(2026,1,1)),2)&" "&CHOOSE(MONTH(DATE(2026,1,1)),"enero","febrero","marzo","abril","mayo","junio","julio","agosto","septiembre","octubre","noviembre","diciembre") -> 2026-01 enero | B10: =SUMIFS(Colección!$L$2:$L$10001,Colección!$M$2:$M$10001,"Compra",Colección!$D$2:$D$10001,">="&DATE(2026,1,1),Colección!$D$2:$D$10001,"<"&DATE(2026,2,1)) -> 2448.56
A11: =YEAR(DATE(2025,12,1))&"-"&RIGHT("0"&MONTH(DATE(2025,12,1)),2)&" "&CHOOSE(MONTH(DATE(2025,12,1)),"enero","febrero","marzo","abril","mayo","junio","julio","agosto","septiembre","octubre","noviembre","diciembre") -> 2025-12 diciembre | B11: =SUMIFS(Colección!$L$2:$L$10001,Colección!$M$2:$M$10001,"Compra",Colección!$D$2:$D$10001,">="&DATE(2025,12,1),Colección!$D$2:$D$10001,"<"&DATE(2025,13,1)) -> 1465.13
A12: =YEAR(DATE(2025,11,1))&"-"&RIGHT("0"&MONTH(DATE(2025,11,1)),2)&" "&CHOOSE(MONTH(DATE(2025,11,1)),"enero","febrero","marzo","abril","mayo","junio","julio","agosto","septiembre","octubre","noviembre","diciembre") -> 2025-11 noviembre | B12: =SUMIFS(Colección!$L$2:$L$10001,Colección!$M$2:$M$10001,"Compra",Colección!$D$2:$D$10001,">="&DATE(2025,11,1),Colección!$D$2:$D$10001,"<"&DATE(2025,12,1)) -> 554.11
A13: =YEAR(DATE(2025,10,1))&"-"&RIGHT("0"&MONTH(DATE(2025,10,1)),2)&" "&CHOOSE(MONTH(DATE(2025,10,1)),"enero","febrero","marzo","abril","mayo","junio","julio","agosto","septiembre","octubre","noviembre","diciembre") -> 2025-10 octubre | B13: =SUMIFS(Colección!$L$2:$L$10001,Colección!$M$2:$M$10001,"Compra",Colección!$D$2:$D$10001,">="&DATE(2025,10,1),Colección!$D$2:$D$10001,"<"&DATE(2025,11,1)) -> 456.03
A14: =YEAR(DATE(2025,9,1))&"-"&RIGHT("0"&MONTH(DATE(2025,9,1)),2)&" "&CHOOSE(MONTH(DATE(2025,9,1)),"enero","febrero","marzo","abril","mayo","junio","julio","agosto","septiembre","octubre","noviembre","diciembre") -> 2025-09 septiembre | B14: =SUMIFS(Colección!$L$2:$L$10001,Colección!$M$2:$M$10001,"Compra",Colección!$D$2:$D$10001,">="&DATE(2025,9,1),Colección!$D$2:$D$10001,"<"&DATE(2025,10,1)) -> 195.62
A15: =YEAR(DATE(2025,8,1))&"-"&RIGHT("0"&MONTH(DATE(2025,8,1)),2)&" "&CHOOSE(MONTH(DATE(2025,8,1)),"enero","febrero","marzo","abril","mayo","junio","julio","agosto","septiembre","octubre","noviembre","diciembre") -> 2025-08 agosto | B15: =SUMIFS(Colección!$L$2:$L$10001,Colección!$M$2:$M$10001,"Compra",Colección!$D$2:$D$10001,">="&DATE(2025,8,1),Colección!$D$2:$D$10001,"<"&DATE(2025,9,1)) -> 243.64
A16: =YEAR(DATE(2025,7,1))&"-"&RIGHT("0"&MONTH(DATE(2025,7,1)),2)&" "&CHOOSE(MONTH(DATE(2025,7,1)),"enero","febrero","marzo","abril","mayo","junio","julio","agosto","septiembre","octubre","noviembre","diciembre") -> 2025-07 julio | B16: =SUMIFS(Colección!$L$2:$L$10001,Colección!$M$2:$M$10001,"Compra",Colección!$D$2:$D$10001,">="&DATE(2025,7,1),Colección!$D$2:$D$10001,"<"&DATE(2025,8,1)) -> 739.23
A17: =YEAR(DATE(2025,6,1))&"-"&RIGHT("0"&MONTH(DATE(2025,6,1)),2)&" "&CHOOSE(MONTH(DATE(2025,6,1)),"enero","febrero","marzo","abril","mayo","junio","julio","agosto","septiembre","octubre","noviembre","diciembre") -> 2025-06 junio | B17: =SUMIFS(Colección!$L$2:$L$10001,Colección!$M$2:$M$10001,"Compra",Colección!$D$2:$D$10001,">="&DATE(2025,6,1),Colección!$D$2:$D$10001,"<"&DATE(2025,7,1)) -> 701.66 | J17: Resumen Compra/Venta
A18: =YEAR(DATE(2025,5,1))&"-"&RIGHT("0"&MONTH(DATE(2025,5,1)),2)&" "&CHOOSE(MONTH(DATE(2025,5,1)),"enero","febrero","marzo","abril","mayo","junio","julio","agosto","septiembre","octubre","noviembre","diciembre") -> 2025-05 mayo | B18: =SUMIFS(Colección!$L$2:$L$10001,Colección!$M$2:$M$10001,"Compra",Colección!$D$2:$D$10001,">="&DATE(2025,5,1),Colección!$D$2:$D$10001,"<"&DATE(2025,6,1)) -> 490.35 | J18: Tipo Operacion | K18: Suma Quantity | L18: Total compra | M18: Precio venta
A19: =YEAR(DATE(2025,4,1))&"-"&RIGHT("0"&MONTH(DATE(2025,4,1)),2)&" "&CHOOSE(MONTH(DATE(2025,4,1)),"enero","febrero","marzo","abril","mayo","junio","julio","agosto","septiembre","octubre","noviembre","diciembre") -> 2025-04 abril | B19: =SUMIFS(Colección!$L$2:$L$10001,Colección!$M$2:$M$10001,"Compra",Colección!$D$2:$D$10001,">="&DATE(2025,4,1),Colección!$D$2:$D$10001,"<"&DATE(2025,5,1)) -> 2333.71 | J19: ="Compra" -> Compra | K19: =SUMIFS(Colección!$K$2:$K$10001,Colección!$M$2:$M$10001,$J19) -> 7139 | L19: =IF($J19="Compra",SUMIFS(Colección!$L$2:$L$10001,Colección!$M$2:$M$10001,$J19),0) -> 39682.374 | M19: =IF($J19="Venta",SUMIFS(Colección!$N$2:$N$10001,Colección!$M$2:$M$10001,$J19),0) -> 0
A20: =YEAR(DATE(2025,3,1))&"-"&RIGHT("0"&MONTH(DATE(2025,3,1)),2)&" "&CHOOSE(MONTH(DATE(2025,3,1)),"enero","febrero","marzo","abril","mayo","junio","julio","agosto","septiembre","octubre","noviembre","diciembre") -> 2025-03 marzo | B20: =SUMIFS(Colección!$L$2:$L$10001,Colección!$M$2:$M$10001,"Compra",Colección!$D$2:$D$10001,">="&DATE(2025,3,1),Colección!$D$2:$D$10001,"<"&DATE(2025,4,1)) -> 2207.0009 | J20: ="Venta" -> Venta | K20: =SUMIFS(Colección!$K$2:$K$10001,Colección!$M$2:$M$10001,$J20) -> 1073 | L20: =IF($J20="Compra",SUMIFS(Colección!$L$2:$L$10001,Colección!$M$2:$M$10001,$J20),0) -> 0 | M20: =IF($J20="Venta",SUMIFS(Colección!$N$2:$N$10001,Colección!$M$2:$M$10001,$J20),0) -> 7242.249
A21: =YEAR(DATE(2025,2,1))&"-"&RIGHT("0"&MONTH(DATE(2025,2,1)),2)&" "&CHOOSE(MONTH(DATE(2025,2,1)),"enero","febrero","marzo","abril","mayo","junio","julio","agosto","septiembre","octubre","noviembre","diciembre") -> 2025-02 febrero | B21: =SUMIFS(Colección!$L$2:$L$10001,Colección!$M$2:$M$10001,"Compra",Colección!$D$2:$D$10001,">="&DATE(2025,2,1),Colección!$D$2:$D$10001,"<"&DATE(2025,3,1)) -> 937.97 | J21: ="Cancelado" -> Cancelado | K21: =SUMIFS(Colección!$K$2:$K$10001,Colección!$M$2:$M$10001,$J21) -> 0 | L21: =IF($J21="Compra",SUMIFS(Colección!$L$2:$L$10001,Colección!$M$2:$M$10001,$J21),0) -> 0 | M21: =IF($J21="Venta",SUMIFS(Colección!$N$2:$N$10001,Colección!$M$2:$M$10001,$J21),0) -> 0
A22: =YEAR(DATE(2025,1,1))&"-"&RIGHT("0"&MONTH(DATE(2025,1,1)),2)&" "&CHOOSE(MONTH(DATE(2025,1,1)),"enero","febrero","marzo","abril","mayo","junio","julio","agosto","septiembre","octubre","noviembre","diciembre") -> 2025-01 enero | B22: =SUMIFS(Colección!$L$2:$L$10001,Colección!$M$2:$M$10001,"Compra",Colección!$D$2:$D$10001,">="&DATE(2025,1,1),Colección!$D$2:$D$10001,"<"&DATE(2025,2,1)) -> 562.59
A23: =YEAR(DATE(2024,12,1))&"-"&RIGHT("0"&MONTH(DATE(2024,12,1)),2)&" "&CHOOSE(MONTH(DATE(2024,12,1)),"enero","febrero","marzo","abril","mayo","junio","julio","agosto","septiembre","octubre","noviembre","diciembre") -> 2024-12 diciembre | B23: =SUMIFS(Colección!$L$2:$L$10001,Colección!$M$2:$M$10001,"Compra",Colección!$D$2:$D$10001,">="&DATE(2024,12,1),Colección!$D$2:$D$10001,"<"&DATE(2024,13,1)) -> 897.14
A24: =YEAR(DATE(2024,11,1))&"-"&RIGHT("0"&MONTH(DATE(2024,11,1)),2)&" "&CHOOSE(MONTH(DATE(2024,11,1)),"enero","febrero","marzo","abril","mayo","junio","julio","agosto","septiembre","octubre","noviembre","diciembre") -> 2024-11 noviembre | B24: =SUMIFS(Colección!$L$2:$L$10001,Colección!$M$2:$M$10001,"Compra",Colección!$D$2:$D$10001,">="&DATE(2024,11,1),Colección!$D$2:$D$10001,"<"&DATE(2024,12,1)) -> 583.05
A25: =YEAR(DATE(2024,10,1))&"-"&RIGHT("0"&MONTH(DATE(2024,10,1)),2)&" "&CHOOSE(MONTH(DATE(2024,10,1)),"enero","febrero","marzo","abril","mayo","junio","julio","agosto","septiembre","octubre","noviembre","diciembre") -> 2024-10 octubre | B25: =SUMIFS(Colección!$L$2:$L$10001,Colección!$M$2:$M$10001,"Compra",Colección!$D$2:$D$10001,">="&DATE(2024,10,1),Colección!$D$2:$D$10001,"<"&DATE(2024,11,1)) -> 800.76
A26: =YEAR(DATE(2024,9,1))&"-"&RIGHT("0"&MONTH(DATE(2024,9,1)),2)&" "&CHOOSE(MONTH(DATE(2024,9,1)),"enero","febrero","marzo","abril","mayo","junio","julio","agosto","septiembre","octubre","noviembre","diciembre") -> 2024-09 septiembre | B26: =SUMIFS(Colección!$L$2:$L$10001,Colección!$M$2:$M$10001,"Compra",Colección!$D$2:$D$10001,">="&DATE(2024,9,1),Colección!$D$2:$D$10001,"<"&DATE(2024,10,1)) -> 450.39
A27: =YEAR(DATE(2024,8,1))&"-"&RIGHT("0"&MONTH(DATE(2024,8,1)),2)&" "&CHOOSE(MONTH(DATE(2024,8,1)),"enero","febrero","marzo","abril","mayo","junio","julio","agosto","septiembre","octubre","noviembre","diciembre") -> 2024-08 agosto | B27: =SUMIFS(Colección!$L$2:$L$10001,Colección!$M$2:$M$10001,"Compra",Colección!$D$2:$D$10001,">="&DATE(2024,8,1),Colección!$D$2:$D$10001,"<"&DATE(2024,9,1)) -> 664.07
A28: =YEAR(DATE(2024,7,1))&"-"&RIGHT("0"&MONTH(DATE(2024,7,1)),2)&" "&CHOOSE(MONTH(DATE(2024,7,1)),"enero","febrero","marzo","abril","mayo","junio","julio","agosto","septiembre","octubre","noviembre","diciembre") -> 2024-07 julio | B28: =SUMIFS(Colección!$L$2:$L$10001,Colección!$M$2:$M$10001,"Compra",Colección!$D$2:$D$10001,">="&DATE(2024,7,1),Colección!$D$2:$D$10001,"<"&DATE(2024,8,1)) -> 1260.31
A29: =YEAR(DATE(2024,6,1))&"-"&RIGHT("0"&MONTH(DATE(2024,6,1)),2)&" "&CHOOSE(MONTH(DATE(2024,6,1)),"enero","febrero","marzo","abril","mayo","junio","julio","agosto","septiembre","octubre","noviembre","diciembre") -> 2024-06 junio | B29: =SUMIFS(Colección!$L$2:$L$10001,Colección!$M$2:$M$10001,"Compra",Colección!$D$2:$D$10001,">="&DATE(2024,6,1),Colección!$D$2:$D$10001,"<"&DATE(2024,7,1)) -> 2096.53
A30: =YEAR(DATE(2024,5,1))&"-"&RIGHT("0"&MONTH(DATE(2024,5,1)),2)&" "&CHOOSE(MONTH(DATE(2024,5,1)),"enero","febrero","marzo","abril","mayo","junio","julio","agosto","septiembre","octubre","noviembre","diciembre") -> 2024-05 mayo | B30: =SUMIFS(Colección!$L$2:$L$10001,Colección!$M$2:$M$10001,"Compra",Colección!$D$2:$D$10001,">="&DATE(2024,5,1),Colección!$D$2:$D$10001,"<"&DATE(2024,6,1)) -> 1971.47
A31: =YEAR(DATE(2024,4,1))&"-"&RIGHT("0"&MONTH(DATE(2024,4,1)),2)&" "&CHOOSE(MONTH(DATE(2024,4,1)),"enero","febrero","marzo","abril","mayo","junio","julio","agosto","septiembre","octubre","noviembre","diciembre") -> 2024-04 abril | B31: =SUMIFS(Colección!$L$2:$L$10001,Colección!$M$2:$M$10001,"Compra",Colección!$D$2:$D$10001,">="&DATE(2024,4,1),Colección!$D$2:$D$10001,"<"&DATE(2024,5,1)) -> 497.54
A32: =YEAR(DATE(2024,3,1))&"-"&RIGHT("0"&MONTH(DATE(2024,3,1)),2)&" "&CHOOSE(MONTH(DATE(2024,3,1)),"enero","febrero","marzo","abril","mayo","junio","julio","agosto","septiembre","octubre","noviembre","diciembre") -> 2024-03 marzo | B32: =SUMIFS(Colección!$L$2:$L$10001,Colección!$M$2:$M$10001,"Compra",Colección!$D$2:$D$10001,">="&DATE(2024,3,1),Colección!$D$2:$D$10001,"<"&DATE(2024,4,1)) -> 519.02
A33: =YEAR(DATE(2024,2,1))&"-"&RIGHT("0"&MONTH(DATE(2024,2,1)),2)&" "&CHOOSE(MONTH(DATE(2024,2,1)),"enero","febrero","marzo","abril","mayo","junio","julio","agosto","septiembre","octubre","noviembre","diciembre") -> 2024-02 febrero | B33: =SUMIFS(Colección!$L$2:$L$10001,Colección!$M$2:$M$10001,"Compra",Colección!$D$2:$D$10001,">="&DATE(2024,2,1),Colección!$D$2:$D$10001,"<"&DATE(2024,3,1)) -> 435.24 | J33: Top ediciones por gasto
A34: =YEAR(DATE(2024,1,1))&"-"&RIGHT("0"&MONTH(DATE(2024,1,1)),2)&" "&CHOOSE(MONTH(DATE(2024,1,1)),"enero","febrero","marzo","abril","mayo","junio","julio","agosto","septiembre","octubre","noviembre","diciembre") -> 2024-01 enero | B34: =SUMIFS(Colección!$L$2:$L$10001,Colección!$M$2:$M$10001,"Compra",Colección!$D$2:$D$10001,">="&DATE(2024,1,1),Colección!$D$2:$D$10001,"<"&DATE(2024,2,1)) -> 596.42 | J34: Edition | K34: Suma de Total | L34: Suma de Quantity
A35: =YEAR(DATE(2023,12,1))&"-"&RIGHT("0"&MONTH(DATE(2023,12,1)),2)&" "&CHOOSE(MONTH(DATE(2023,12,1)),"enero","febrero","marzo","abril","mayo","junio","julio","agosto","septiembre","octubre","noviembre","diciembre") -> 2023-12 diciembre | B35: =SUMIFS(Colección!$L$2:$L$10001,Colección!$M$2:$M$10001,"Compra",Colección!$D$2:$D$10001,">="&DATE(2023,12,1),Colección!$D$2:$D$10001,"<"&DATE(2023,13,1)) -> 1079.91 | J35: =IFERROR(INDEX('Aux Graficos'!$A$2:$A$321,MATCH(1,'Aux Graficos'!$D$2:$D$321,0)),"") -> Modern Horizons 2: Extras | K35: =IF($J35="","",SUMIFS(Colección!$L$2:$L$10001,Colección!$G$2:$G$10001,$J35,Colección!$M$2:$M$10001,"Compra")) -> 2246.7577 | L35: =IF($J35="","",SUMIFS(Colección!$K$2:$K$10001,Colección!$G$2:$G$10001,$J35,Colección!$M$2:$M$10001,"Compra")) -> 145
A36: =YEAR(DATE(2023,11,1))&"-"&RIGHT("0"&MONTH(DATE(2023,11,1)),2)&" "&CHOOSE(MONTH(DATE(2023,11,1)),"enero","febrero","marzo","abril","mayo","junio","julio","agosto","septiembre","octubre","noviembre","diciembre") -> 2023-11 noviembre | B36: =SUMIFS(Colección!$L$2:$L$10001,Colección!$M$2:$M$10001,"Compra",Colección!$D$2:$D$10001,">="&DATE(2023,11,1),Colección!$D$2:$D$10001,"<"&DATE(2023,12,1)) -> 361.7 | J36: =IFERROR(INDEX('Aux Graficos'!$A$2:$A$321,MATCH(2,'Aux Graficos'!$D$2:$D$321,0)),"") -> Unleashed | K36: =IF($J36="","",SUMIFS(Colección!$L$2:$L$10001,Colección!$G$2:$G$10001,$J36,Colección!$M$2:$M$10001,"Compra")) -> 1759.3655 | L36: =IF($J36="","",SUMIFS(Colección!$K$2:$K$10001,Colección!$G$2:$G$10001,$J36,Colección!$M$2:$M$10001,"Compra")) -> 163
A37: =YEAR(DATE(2023,10,1))&"-"&RIGHT("0"&MONTH(DATE(2023,10,1)),2)&" "&CHOOSE(MONTH(DATE(2023,10,1)),"enero","febrero","marzo","abril","mayo","junio","julio","agosto","septiembre","octubre","noviembre","diciembre") -> 2023-10 octubre | B37: =SUMIFS(Colección!$L$2:$L$10001,Colección!$M$2:$M$10001,"Compra",Colección!$D$2:$D$10001,">="&DATE(2023,10,1),Colección!$D$2:$D$10001,"<"&DATE(2023,11,1)) -> 487.02 | J37: =IFERROR(INDEX('Aux Graficos'!$A$2:$A$321,MATCH(3,'Aux Graficos'!$D$2:$D$321,0)),"") -> Modern Horizons 3 | K37: =IF($J37="","",SUMIFS(Colección!$L$2:$L$10001,Colección!$G$2:$G$10001,$J37,Colección!$M$2:$M$10001,"Compra")) -> 1489.2334 | L37: =IF($J37="","",SUMIFS(Colección!$K$2:$K$10001,Colección!$G$2:$G$10001,$J37,Colección!$M$2:$M$10001,"Compra")) -> 265
A38: =YEAR(DATE(2023,9,1))&"-"&RIGHT("0"&MONTH(DATE(2023,9,1)),2)&" "&CHOOSE(MONTH(DATE(2023,9,1)),"enero","febrero","marzo","abril","mayo","junio","julio","agosto","septiembre","octubre","noviembre","diciembre") -> 2023-09 septiembre | B38: =SUMIFS(Colección!$L$2:$L$10001,Colección!$M$2:$M$10001,"Compra",Colección!$D$2:$D$10001,">="&DATE(2023,9,1),Colección!$D$2:$D$10001,"<"&DATE(2023,10,1)) -> 424.94 | J38: =IFERROR(INDEX('Aux Graficos'!$A$2:$A$321,MATCH(4,'Aux Graficos'!$D$2:$D$321,0)),"") -> Exodus | K38: =IF($J38="","",SUMIFS(Colección!$L$2:$L$10001,Colección!$G$2:$G$10001,$J38,Colección!$M$2:$M$10001,"Compra")) -> 1327.3305 | L38: =IF($J38="","",SUMIFS(Colección!$K$2:$K$10001,Colección!$G$2:$G$10001,$J38,Colección!$M$2:$M$10001,"Compra")) -> 9
A39: =YEAR(DATE(2023,8,1))&"-"&RIGHT("0"&MONTH(DATE(2023,8,1)),2)&" "&CHOOSE(MONTH(DATE(2023,8,1)),"enero","febrero","marzo","abril","mayo","junio","julio","agosto","septiembre","octubre","noviembre","diciembre") -> 2023-08 agosto | B39: =SUMIFS(Colección!$L$2:$L$10001,Colección!$M$2:$M$10001,"Compra",Colección!$D$2:$D$10001,">="&DATE(2023,8,1),Colección!$D$2:$D$10001,"<"&DATE(2023,9,1)) -> 134.95 | J39: =IFERROR(INDEX('Aux Graficos'!$A$2:$A$321,MATCH(5,'Aux Graficos'!$D$2:$D$321,0)),"") -> Modern Horizons 3: Extras | K39: =IF($J39="","",SUMIFS(Colección!$L$2:$L$10001,Colección!$G$2:$G$10001,$J39,Colección!$M$2:$M$10001,"Compra")) -> 1316.4214 | L39: =IF($J39="","",SUMIFS(Colección!$K$2:$K$10001,Colección!$G$2:$G$10001,$J39,Colección!$M$2:$M$10001,"Compra")) -> 123
A40: =YEAR(DATE(2023,7,1))&"-"&RIGHT("0"&MONTH(DATE(2023,7,1)),2)&" "&CHOOSE(MONTH(DATE(2023,7,1)),"enero","febrero","marzo","abril","mayo","junio","julio","agosto","septiembre","octubre","noviembre","diciembre") -> 2023-07 julio | B40: =SUMIFS(Colección!$L$2:$L$10001,Colección!$M$2:$M$10001,"Compra",Colección!$D$2:$D$10001,">="&DATE(2023,7,1),Colección!$D$2:$D$10001,"<"&DATE(2023,8,1)) -> 1108.3936 | J40: =IFERROR(INDEX('Aux Graficos'!$A$2:$A$321,MATCH(6,'Aux Graficos'!$D$2:$D$321,0)),"") -> The Lord of the Rings: Tales of Middle-earth | K40: =IF($J40="","",SUMIFS(Colección!$L$2:$L$10001,Colección!$G$2:$G$10001,$J40,Colección!$M$2:$M$10001,"Compra")) -> 1260.9508 | L40: =IF($J40="","",SUMIFS(Colección!$K$2:$K$10001,Colección!$G$2:$G$10001,$J40,Colección!$M$2:$M$10001,"Compra")) -> 266
A41: =YEAR(DATE(2023,6,1))&"-"&RIGHT("0"&MONTH(DATE(2023,6,1)),2)&" "&CHOOSE(MONTH(DATE(2023,6,1)),"enero","febrero","marzo","abril","mayo","junio","julio","agosto","septiembre","octubre","noviembre","diciembre") -> 2023-06 junio | B41: =SUMIFS(Colección!$L$2:$L$10001,Colección!$M$2:$M$10001,"Compra",Colección!$D$2:$D$10001,">="&DATE(2023,6,1),Colección!$D$2:$D$10001,"<"&DATE(2023,7,1)) -> 334.72 | J41: =IFERROR(INDEX('Aux Graficos'!$A$2:$A$321,MATCH(7,'Aux Graficos'!$D$2:$D$321,0)),"") -> Urza's Saga | K41: =IF($J41="","",SUMIFS(Colección!$L$2:$L$10001,Colección!$G$2:$G$10001,$J41,Colección!$M$2:$M$10001,"Compra")) -> 1128.7762 | L41: =IF($J41="","",SUMIFS(Colección!$K$2:$K$10001,Colección!$G$2:$G$10001,$J41,Colección!$M$2:$M$10001,"Compra")) -> 71
A42: =YEAR(DATE(2023,5,1))&"-"&RIGHT("0"&MONTH(DATE(2023,5,1)),2)&" "&CHOOSE(MONTH(DATE(2023,5,1)),"enero","febrero","marzo","abril","mayo","junio","julio","agosto","septiembre","octubre","noviembre","diciembre") -> 2023-05 mayo | B42: =SUMIFS(Colección!$L$2:$L$10001,Colección!$M$2:$M$10001,"Compra",Colección!$D$2:$D$10001,">="&DATE(2023,5,1),Colección!$D$2:$D$10001,"<"&DATE(2023,6,1)) -> 616.66 | J42: =IFERROR(INDEX('Aux Graficos'!$A$2:$A$321,MATCH(8,'Aux Graficos'!$D$2:$D$321,0)),"") -> Revised | K42: =IF($J42="","",SUMIFS(Colección!$L$2:$L$10001,Colección!$G$2:$G$10001,$J42,Colección!$M$2:$M$10001,"Compra")) -> 1025 | L42: =IF($J42="","",SUMIFS(Colección!$K$2:$K$10001,Colección!$G$2:$G$10001,$J42,Colección!$M$2:$M$10001,"Compra")) -> 3
A43: =YEAR(DATE(2023,4,1))&"-"&RIGHT("0"&MONTH(DATE(2023,4,1)),2)&" "&CHOOSE(MONTH(DATE(2023,4,1)),"enero","febrero","marzo","abril","mayo","junio","julio","agosto","septiembre","octubre","noviembre","diciembre") -> 2023-04 abril | B43: =SUMIFS(Colección!$L$2:$L$10001,Colección!$M$2:$M$10001,"Compra",Colección!$D$2:$D$10001,">="&DATE(2023,4,1),Colección!$D$2:$D$10001,"<"&DATE(2023,5,1)) -> 212.49 | J43: =IFERROR(INDEX('Aux Graficos'!$A$2:$A$321,MATCH(9,'Aux Graficos'!$D$2:$D$321,0)),"") -> Onslaught | K43: =IF($J43="","",SUMIFS(Colección!$L$2:$L$10001,Colección!$G$2:$G$10001,$J43,Colección!$M$2:$M$10001,"Compra")) -> 1002.0291 | L43: =IF($J43="","",SUMIFS(Colección!$K$2:$K$10001,Colección!$G$2:$G$10001,$J43,Colección!$M$2:$M$10001,"Compra")) -> 39
A44: =YEAR(DATE(2023,3,1))&"-"&RIGHT("0"&MONTH(DATE(2023,3,1)),2)&" "&CHOOSE(MONTH(DATE(2023,3,1)),"enero","febrero","marzo","abril","mayo","junio","julio","agosto","septiembre","octubre","noviembre","diciembre") -> 2023-03 marzo | B44: =SUMIFS(Colección!$L$2:$L$10001,Colección!$M$2:$M$10001,"Compra",Colección!$D$2:$D$10001,">="&DATE(2023,3,1),Colección!$D$2:$D$10001,"<"&DATE(2023,4,1)) -> 429.28 | J44: =IFERROR(INDEX('Aux Graficos'!$A$2:$A$321,MATCH(10,'Aux Graficos'!$D$2:$D$321,0)),"") -> Modern Horizons 2 | K44: =IF($J44="","",SUMIFS(Colección!$L$2:$L$10001,Colección!$G$2:$G$10001,$J44,Colección!$M$2:$M$10001,"Compra")) -> 994.97726 | L44: =IF($J44="","",SUMIFS(Colección!$K$2:$K$10001,Colección!$G$2:$G$10001,$J44,Colección!$M$2:$M$10001,"Compra")) -> 173
A45: =YEAR(DATE(2023,2,1))&"-"&RIGHT("0"&MONTH(DATE(2023,2,1)),2)&" "&CHOOSE(MONTH(DATE(2023,2,1)),"enero","febrero","marzo","abril","mayo","junio","julio","agosto","septiembre","octubre","noviembre","diciembre") -> 2023-02 febrero | B45: =SUMIFS(Colección!$L$2:$L$10001,Colección!$M$2:$M$10001,"Compra",Colección!$D$2:$D$10001,">="&DATE(2023,2,1),Colección!$D$2:$D$10001,"<"&DATE(2023,3,1)) -> 296.16 | J45: =IFERROR(INDEX('Aux Graficos'!$A$2:$A$321,MATCH(11,'Aux Graficos'!$D$2:$D$321,0)),"") -> Fourth Edition: Black Bordered | K45: =IF($J45="","",SUMIFS(Colección!$L$2:$L$10001,Colección!$G$2:$G$10001,$J45,Colección!$M$2:$M$10001,"Compra")) -> 737.84364 | L45: =IF($J45="","",SUMIFS(Colección!$K$2:$K$10001,Colección!$G$2:$G$10001,$J45,Colección!$M$2:$M$10001,"Compra")) -> 103
A46: =YEAR(DATE(2023,1,1))&"-"&RIGHT("0"&MONTH(DATE(2023,1,1)),2)&" "&CHOOSE(MONTH(DATE(2023,1,1)),"enero","febrero","marzo","abril","mayo","junio","julio","agosto","septiembre","octubre","noviembre","diciembre") -> 2023-01 enero | B46: =SUMIFS(Colección!$L$2:$L$10001,Colección!$M$2:$M$10001,"Compra",Colección!$D$2:$D$10001,">="&DATE(2023,1,1),Colección!$D$2:$D$10001,"<"&DATE(2023,2,1)) -> 867.21 | J46: =IFERROR(INDEX('Aux Graficos'!$A$2:$A$321,MATCH(12,'Aux Graficos'!$D$2:$D$321,0)),"") -> Spiritforged | K46: =IF($J46="","",SUMIFS(Colección!$L$2:$L$10001,Colección!$G$2:$G$10001,$J46,Colección!$M$2:$M$10001,"Compra")) -> 683.23768 | L46: =IF($J46="","",SUMIFS(Colección!$K$2:$K$10001,Colección!$G$2:$G$10001,$J46,Colección!$M$2:$M$10001,"Compra")) -> 135
A47: =YEAR(DATE(2022,12,1))&"-"&RIGHT("0"&MONTH(DATE(2022,12,1)),2)&" "&CHOOSE(MONTH(DATE(2022,12,1)),"enero","febrero","marzo","abril","mayo","junio","julio","agosto","septiembre","octubre","noviembre","diciembre") -> 2022-12 diciembre | B47: =SUMIFS(Colección!$L$2:$L$10001,Colección!$M$2:$M$10001,"Compra",Colección!$D$2:$D$10001,">="&DATE(2022,12,1),Colección!$D$2:$D$10001,"<"&DATE(2022,13,1)) -> 1214.04 | J47: =IFERROR(INDEX('Aux Graficos'!$A$2:$A$321,MATCH(13,'Aux Graficos'!$D$2:$D$321,0)),"") -> Origins | K47: =IF($J47="","",SUMIFS(Colección!$L$2:$L$10001,Colección!$G$2:$G$10001,$J47,Colección!$M$2:$M$10001,"Compra")) -> 643.5869 | L47: =IF($J47="","",SUMIFS(Colección!$K$2:$K$10001,Colección!$G$2:$G$10001,$J47,Colección!$M$2:$M$10001,"Compra")) -> 121
A48: =YEAR(DATE(2022,11,1))&"-"&RIGHT("0"&MONTH(DATE(2022,11,1)),2)&" "&CHOOSE(MONTH(DATE(2022,11,1)),"enero","febrero","marzo","abril","mayo","junio","julio","agosto","septiembre","octubre","noviembre","diciembre") -> 2022-11 noviembre | B48: =SUMIFS(Colección!$L$2:$L$10001,Colección!$M$2:$M$10001,"Compra",Colección!$D$2:$D$10001,">="&DATE(2022,11,1),Colección!$D$2:$D$10001,"<"&DATE(2022,12,1)) -> 1144.75 | J48: =IFERROR(INDEX('Aux Graficos'!$A$2:$A$321,MATCH(14,'Aux Graficos'!$D$2:$D$321,0)),"") -> Time Spiral Remastered: Extras | K48: =IF($J48="","",SUMIFS(Colección!$L$2:$L$10001,Colección!$G$2:$G$10001,$J48,Colección!$M$2:$M$10001,"Compra")) -> 571.77355 | L48: =IF($J48="","",SUMIFS(Colección!$K$2:$K$10001,Colección!$G$2:$G$10001,$J48,Colección!$M$2:$M$10001,"Compra")) -> 113
A49: =YEAR(DATE(2022,10,1))&"-"&RIGHT("0"&MONTH(DATE(2022,10,1)),2)&" "&CHOOSE(MONTH(DATE(2022,10,1)),"enero","febrero","marzo","abril","mayo","junio","julio","agosto","septiembre","octubre","noviembre","diciembre") -> 2022-10 octubre | B49: =SUMIFS(Colección!$L$2:$L$10001,Colección!$M$2:$M$10001,"Compra",Colección!$D$2:$D$10001,">="&DATE(2022,10,1),Colección!$D$2:$D$10001,"<"&DATE(2022,11,1)) -> 1119.49 | J49: =IFERROR(INDEX('Aux Graficos'!$A$2:$A$321,MATCH(15,'Aux Graficos'!$D$2:$D$321,0)),"") -> Origins: Promos | K49: =IF($J49="","",SUMIFS(Colección!$L$2:$L$10001,Colección!$G$2:$G$10001,$J49,Colección!$M$2:$M$10001,"Compra")) -> 554.98917 | L49: =IF($J49="","",SUMIFS(Colección!$K$2:$K$10001,Colección!$G$2:$G$10001,$J49,Colección!$M$2:$M$10001,"Compra")) -> 6
A50: =YEAR(DATE(2022,9,1))&"-"&RIGHT("0"&MONTH(DATE(2022,9,1)),2)&" "&CHOOSE(MONTH(DATE(2022,9,1)),"enero","febrero","marzo","abril","mayo","junio","julio","agosto","septiembre","octubre","noviembre","diciembre") -> 2022-09 septiembre | B50: =SUMIFS(Colección!$L$2:$L$10001,Colección!$M$2:$M$10001,"Compra",Colección!$D$2:$D$10001,">="&DATE(2022,9,1),Colección!$D$2:$D$10001,"<"&DATE(2022,10,1)) -> 374.48 | J50: =IFERROR(INDEX('Aux Graficos'!$A$2:$A$321,MATCH(16,'Aux Graficos'!$D$2:$D$321,0)),"") -> Magic: The Gathering - FINAL FANTASY: Extras | K50: =IF($J50="","",SUMIFS(Colección!$L$2:$L$10001,Colección!$G$2:$G$10001,$J50,Colección!$M$2:$M$10001,"Compra")) -> 542.23262 | L50: =IF($J50="","",SUMIFS(Colección!$K$2:$K$10001,Colección!$G$2:$G$10001,$J50,Colección!$M$2:$M$10001,"Compra")) -> 15
J51: =IFERROR(INDEX('Aux Graficos'!$A$2:$A$321,MATCH(17,'Aux Graficos'!$D$2:$D$321,0)),"") -> Double Masters 2022: Extras | K51: =IF($J51="","",SUMIFS(Colección!$L$2:$L$10001,Colección!$G$2:$G$10001,$J51,Colección!$M$2:$M$10001,"Compra")) -> 459.8881 | L51: =IF($J51="","",SUMIFS(Colección!$K$2:$K$10001,Colección!$G$2:$G$10001,$J51,Colección!$M$2:$M$10001,"Compra")) -> 66
J52: =IFERROR(INDEX('Aux Graficos'!$A$2:$A$321,MATCH(18,'Aux Graficos'!$D$2:$D$321,0)),"") -> Modern Horizons | K52: =IF($J52="","",SUMIFS(Colección!$L$2:$L$10001,Colección!$G$2:$G$10001,$J52,Colección!$M$2:$M$10001,"Compra")) -> 457.08676 | L52: =IF($J52="","",SUMIFS(Colección!$K$2:$K$10001,Colección!$G$2:$G$10001,$J52,Colección!$M$2:$M$10001,"Compra")) -> 97
J53: =IFERROR(INDEX('Aux Graficos'!$A$2:$A$321,MATCH(19,'Aux Graficos'!$D$2:$D$321,0)),"") -> Tempest | K53: =IF($J53="","",SUMIFS(Colección!$L$2:$L$10001,Colección!$G$2:$G$10001,$J53,Colección!$M$2:$M$10001,"Compra")) -> 436.356 | L53: =IF($J53="","",SUMIFS(Colección!$K$2:$K$10001,Colección!$G$2:$G$10001,$J53,Colección!$M$2:$M$10001,"Compra")) -> 32
A54: Cantidad total por idioma | J54: =IFERROR(INDEX('Aux Graficos'!$A$2:$A$321,MATCH(20,'Aux Graficos'!$D$2:$D$321,0)),"") -> Duskmourn: House of Horror: Extras | K54: =IF($J54="","",SUMIFS(Colección!$L$2:$L$10001,Colección!$G$2:$G$10001,$J54,Colección!$M$2:$M$10001,"Compra")) -> 409.04853 | L54: =IF($J54="","",SUMIFS(Colección!$K$2:$K$10001,Colección!$G$2:$G$10001,$J54,Colección!$M$2:$M$10001,"Compra")) -> 30
A55: Idioma | B55: Suma de Quantity | J55: =IFERROR(INDEX('Aux Graficos'!$A$2:$A$321,MATCH(21,'Aux Graficos'!$D$2:$D$321,0)),"") -> Khans of Tarkir | K55: =IF($J55="","",SUMIFS(Colección!$L$2:$L$10001,Colección!$G$2:$G$10001,$J55,Colección!$M$2:$M$10001,"Compra")) -> 384.20204 | L55: =IF($J55="","",SUMIFS(Colección!$K$2:$K$10001,Colección!$G$2:$G$10001,$J55,Colección!$M$2:$M$10001,"Compra")) -> 32
A56: =IFERROR(INDEX('Aux Graficos'!$J$2:$J$11,MATCH(1,'Aux Graficos'!$L$2:$L$11,0)),"") -> Inglés | B56: =IF($A56="","",SUMIFS(Colección!$K$2:$K$10001,Colección!$I$2:$I$10001,$A56,Colección!$M$2:$M$10001,"Compra")) -> 5499 | J56: =IFERROR(INDEX('Aux Graficos'!$A$2:$A$321,MATCH(22,'Aux Graficos'!$D$2:$D$321,0)),"") -> Aetherdrift: Extras | K56: =IF($J56="","",SUMIFS(Colección!$L$2:$L$10001,Colección!$G$2:$G$10001,$J56,Colección!$M$2:$M$10001,"Compra")) -> 363.38989 | L56: =IF($J56="","",SUMIFS(Colección!$K$2:$K$10001,Colección!$G$2:$G$10001,$J56,Colección!$M$2:$M$10001,"Compra")) -> 40
A57: =IFERROR(INDEX('Aux Graficos'!$J$2:$J$11,MATCH(2,'Aux Graficos'!$L$2:$L$11,0)),"") -> Japonés | B57: =IF($A57="","",SUMIFS(Colección!$K$2:$K$10001,Colección!$I$2:$I$10001,$A57,Colección!$M$2:$M$10001,"Compra")) -> 1098 | J57: =IFERROR(INDEX('Aux Graficos'!$A$2:$A$321,MATCH(23,'Aux Graficos'!$D$2:$D$321,0)),"") -> Scars of Mirrodin | K57: =IF($J57="","",SUMIFS(Colección!$L$2:$L$10001,Colección!$G$2:$G$10001,$J57,Colección!$M$2:$M$10001,"Compra")) -> 352.07018 | L57: =IF($J57="","",SUMIFS(Colección!$K$2:$K$10001,Colección!$G$2:$G$10001,$J57,Colección!$M$2:$M$10001,"Compra")) -> 29
A58: =IFERROR(INDEX('Aux Graficos'!$J$2:$J$11,MATCH(3,'Aux Graficos'!$L$2:$L$11,0)),"") -> Español | B58: =IF($A58="","",SUMIFS(Colección!$K$2:$K$10001,Colección!$I$2:$I$10001,$A58,Colección!$M$2:$M$10001,"Compra")) -> 451 | J58: =IFERROR(INDEX('Aux Graficos'!$A$2:$A$321,MATCH(24,'Aux Graficos'!$D$2:$D$321,0)),"") -> Worldwake | K58: =IF($J58="","",SUMIFS(Colección!$L$2:$L$10001,Colección!$G$2:$G$10001,$J58,Colección!$M$2:$M$10001,"Compra")) -> 348.50185 | L58: =IF($J58="","",SUMIFS(Colección!$K$2:$K$10001,Colección!$G$2:$G$10001,$J58,Colección!$M$2:$M$10001,"Compra")) -> 22
A59: =IFERROR(INDEX('Aux Graficos'!$J$2:$J$11,MATCH(4,'Aux Graficos'!$L$2:$L$11,0)),"") -> Chino-S | B59: =IF($A59="","",SUMIFS(Colección!$K$2:$K$10001,Colección!$I$2:$I$10001,$A59,Colección!$M$2:$M$10001,"Compra")) -> 64 | J59: =IFERROR(INDEX('Aux Graficos'!$A$2:$A$321,MATCH(25,'Aux Graficos'!$D$2:$D$321,0)),"") -> Kamigawa: Neon Dynasty: Extras | K59: =IF($J59="","",SUMIFS(Colección!$L$2:$L$10001,Colección!$G$2:$G$10001,$J59,Colección!$M$2:$M$10001,"Compra")) -> 337.55239 | L59: =IF($J59="","",SUMIFS(Colección!$K$2:$K$10001,Colección!$G$2:$G$10001,$J59,Colección!$M$2:$M$10001,"Compra")) -> 44
A60: =IFERROR(INDEX('Aux Graficos'!$J$2:$J$11,MATCH(5,'Aux Graficos'!$L$2:$L$11,0)),"") -> Italiano | B60: =IF($A60="","",SUMIFS(Colección!$K$2:$K$10001,Colección!$I$2:$I$10001,$A60,Colección!$M$2:$M$10001,"Compra")) -> 8 | J60: =IFERROR(INDEX('Aux Graficos'!$A$2:$A$321,MATCH(26,'Aux Graficos'!$D$2:$D$321,0)),"") -> Wilds of Eldraine | K60: =IF($J60="","",SUMIFS(Colección!$L$2:$L$10001,Colección!$G$2:$G$10001,$J60,Colección!$M$2:$M$10001,"Compra")) -> 334.94645 | L60: =IF($J60="","",SUMIFS(Colección!$K$2:$K$10001,Colección!$G$2:$G$10001,$J60,Colección!$M$2:$M$10001,"Compra")) -> 92
A61: =IFERROR(INDEX('Aux Graficos'!$J$2:$J$11,MATCH(6,'Aux Graficos'!$L$2:$L$11,0)),"") -> Chino-T | B61: =IF($A61="","",SUMIFS(Colección!$K$2:$K$10001,Colección!$I$2:$I$10001,$A61,Colección!$M$2:$M$10001,"Compra")) -> 6 | J61: =IFERROR(INDEX('Aux Graficos'!$A$2:$A$321,MATCH(27,'Aux Graficos'!$D$2:$D$321,0)),"") -> Secret Lair Drop Series: 30th Anniversary Countdown | K61: =IF($J61="","",SUMIFS(Colección!$L$2:$L$10001,Colección!$G$2:$G$10001,$J61,Colección!$M$2:$M$10001,"Compra")) -> 315.49 | L61: =IF($J61="","",SUMIFS(Colección!$K$2:$K$10001,Colección!$G$2:$G$10001,$J61,Colección!$M$2:$M$10001,"Compra")) -> 4
A62: =IFERROR(INDEX('Aux Graficos'!$J$2:$J$11,MATCH(7,'Aux Graficos'!$L$2:$L$11,0)),"") -> Chino | B62: =IF($A62="","",SUMIFS(Colección!$K$2:$K$10001,Colección!$I$2:$I$10001,$A62,Colección!$M$2:$M$10001,"Compra")) -> 5 | J62: =IFERROR(INDEX('Aux Graficos'!$A$2:$A$321,MATCH(28,'Aux Graficos'!$D$2:$D$321,0)),"") -> Ravnica Remastered: Extras | K62: =IF($J62="","",SUMIFS(Colección!$L$2:$L$10001,Colección!$G$2:$G$10001,$J62,Colección!$M$2:$M$10001,"Compra")) -> 312.34569 | L62: =IF($J62="","",SUMIFS(Colección!$K$2:$K$10001,Colección!$G$2:$G$10001,$J62,Colección!$M$2:$M$10001,"Compra")) -> 65
A63: =IFERROR(INDEX('Aux Graficos'!$J$2:$J$11,MATCH(8,'Aux Graficos'!$L$2:$L$11,0)),"") -> Francés | B63: =IF($A63="","",SUMIFS(Colección!$K$2:$K$10001,Colección!$I$2:$I$10001,$A63,Colección!$M$2:$M$10001,"Compra")) -> 4 | J63: =IFERROR(INDEX('Aux Graficos'!$A$2:$A$321,MATCH(29,'Aux Graficos'!$D$2:$D$321,0)),"") -> Duskmourn: House of Horror | K63: =IF($J63="","",SUMIFS(Colección!$L$2:$L$10001,Colección!$G$2:$G$10001,$J63,Colección!$M$2:$M$10001,"Compra")) -> 297.93952 | L63: =IF($J63="","",SUMIFS(Colección!$K$2:$K$10001,Colección!$G$2:$G$10001,$J63,Colección!$M$2:$M$10001,"Compra")) -> 118
A64: =IFERROR(INDEX('Aux Graficos'!$J$2:$J$11,MATCH(9,'Aux Graficos'!$L$2:$L$11,0)),"") -> Alemán | B64: =IF($A64="","",SUMIFS(Colección!$K$2:$K$10001,Colección!$I$2:$I$10001,$A64,Colección!$M$2:$M$10001,"Compra")) -> 3 | J64: =IFERROR(INDEX('Aux Graficos'!$A$2:$A$321,MATCH(30,'Aux Graficos'!$D$2:$D$321,0)),"") -> Magic: The Gathering | Avatar: The Last Airbender | K64: =IF($J64="","",SUMIFS(Colección!$L$2:$L$10001,Colección!$G$2:$G$10001,$J64,Colección!$M$2:$M$10001,"Compra")) -> 283.28334 | L64: =IF($J64="","",SUMIFS(Colección!$K$2:$K$10001,Colección!$G$2:$G$10001,$J64,Colección!$M$2:$M$10001,"Compra")) -> 60
A65: =IFERROR(INDEX('Aux Graficos'!$J$2:$J$11,MATCH(10,'Aux Graficos'!$L$2:$L$11,0)),"") -> Ruso | B65: =IF($A65="","",SUMIFS(Colección!$K$2:$K$10001,Colección!$I$2:$I$10001,$A65,Colección!$M$2:$M$10001,"Compra")) -> 1 | J65: =IFERROR(INDEX('Aux Graficos'!$A$2:$A$321,MATCH(31,'Aux Graficos'!$D$2:$D$321,0)),"") -> Dominaria United | K65: =IF($J65="","",SUMIFS(Colección!$L$2:$L$10001,Colección!$G$2:$G$10001,$J65,Colección!$M$2:$M$10001,"Compra")) -> 274.51143 | L65: =IF($J65="","",SUMIFS(Colección!$K$2:$K$10001,Colección!$G$2:$G$10001,$J65,Colección!$M$2:$M$10001,"Compra")) -> 104
J66: =IFERROR(INDEX('Aux Graficos'!$A$2:$A$321,MATCH(32,'Aux Graficos'!$D$2:$D$321,0)),"") -> Zendikar Rising | K66: =IF($J66="","",SUMIFS(Colección!$L$2:$L$10001,Colección!$G$2:$G$10001,$J66,Colección!$M$2:$M$10001,"Compra")) -> 261.76568 | L66: =IF($J66="","",SUMIFS(Colección!$K$2:$K$10001,Colección!$G$2:$G$10001,$J66,Colección!$M$2:$M$10001,"Compra")) -> 94
J67: =IFERROR(INDEX('Aux Graficos'!$A$2:$A$321,MATCH(33,'Aux Graficos'!$D$2:$D$321,0)),"") -> Scourge | K67: =IF($J67="","",SUMIFS(Colección!$L$2:$L$10001,Colección!$G$2:$G$10001,$J67,Colección!$M$2:$M$10001,"Compra")) -> 253.42288 | L67: =IF($J67="","",SUMIFS(Colección!$K$2:$K$10001,Colección!$G$2:$G$10001,$J67,Colección!$M$2:$M$10001,"Compra")) -> 25
J68: =IFERROR(INDEX('Aux Graficos'!$A$2:$A$321,MATCH(34,'Aux Graficos'!$D$2:$D$321,0)),"") -> Accesorios | K68: =IF($J68="","",SUMIFS(Colección!$L$2:$L$10001,Colección!$G$2:$G$10001,$J68,Colección!$M$2:$M$10001,"Compra")) -> 252.84478 | L68: =IF($J68="","",SUMIFS(Colección!$K$2:$K$10001,Colección!$G$2:$G$10001,$J68,Colección!$M$2:$M$10001,"Compra")) -> 51
J69: =IFERROR(INDEX('Aux Graficos'!$A$2:$A$321,MATCH(35,'Aux Graficos'!$D$2:$D$321,0)),"") -> Edge of Eternities | K69: =IF($J69="","",SUMIFS(Colección!$L$2:$L$10001,Colección!$G$2:$G$10001,$J69,Colección!$M$2:$M$10001,"Compra")) -> 252.46326 | L69: =IF($J69="","",SUMIFS(Colección!$K$2:$K$10001,Colección!$G$2:$G$10001,$J69,Colección!$M$2:$M$10001,"Compra")) -> 36
A76: Cartas con mayor gasto
A77: Card Name | B77: Total
A78: =IFERROR(INDEX('Aux Graficos'!$F$2:$F$2353,MATCH(1,'Aux Graficos'!$H$2:$H$2353,0)),"") -> City of Traitors | B78: =IF($A78="","",SUMIFS(Colección!$L$2:$L$10001,Colección!$F$2:$F$10001,$A78,Colección!$M$2:$M$10001,"Compra")) -> 1293.97
A79: =IFERROR(INDEX('Aux Graficos'!$F$2:$F$2353,MATCH(2,'Aux Graficos'!$H$2:$H$2353,0)),"") -> Serra's Sanctum | B79: =IF($A79="","",SUMIFS(Colección!$L$2:$L$10001,Colección!$F$2:$F$10001,$A79,Colección!$M$2:$M$10001,"Compra")) -> 1030
A80: =IFERROR(INDEX('Aux Graficos'!$F$2:$F$2353,MATCH(3,'Aux Graficos'!$H$2:$H$2353,0)),"") -> Underground Sea | B80: =IF($A80="","",SUMIFS(Colección!$L$2:$L$10001,Colección!$F$2:$F$10001,$A80,Colección!$M$2:$M$10001,"Compra")) -> 600
A81: =IFERROR(INDEX('Aux Graficos'!$F$2:$F$2353,MATCH(4,'Aux Graficos'!$H$2:$H$2353,0)),"") -> Scrubland | B81: =IF($A81="","",SUMIFS(Colección!$L$2:$L$10001,Colección!$F$2:$F$10001,$A81,Colección!$M$2:$M$10001,"Compra")) -> 425
A82: =IFERROR(INDEX('Aux Graficos'!$F$2:$F$2353,MATCH(5,'Aux Graficos'!$H$2:$H$2353,0)),"") -> Flooded Strand | B82: =IF($A82="","",SUMIFS(Colección!$L$2:$L$10001,Colección!$F$2:$F$10001,$A82,Colección!$M$2:$M$10001,"Compra")) -> 393.35598
A83: =IFERROR(INDEX('Aux Graficos'!$F$2:$F$2353,MATCH(6,'Aux Graficos'!$H$2:$H$2353,0)),"") -> Vivi Ornitier (V.1) | B83: =IF($A83="","",SUMIFS(Colección!$L$2:$L$10001,Colección!$F$2:$F$10001,$A83,Colección!$M$2:$M$10001,"Compra")) -> 324.79
A84: =IFERROR(INDEX('Aux Graficos'!$F$2:$F$2353,MATCH(7,'Aux Graficos'!$H$2:$H$2353,0)),"") -> Wooded Foothills | B84: =IF($A84="","",SUMIFS(Colección!$L$2:$L$10001,Colección!$F$2:$F$10001,$A84,Colección!$M$2:$M$10001,"Compra")) -> 323.41573
A85: =IFERROR(INDEX('Aux Graficos'!$F$2:$F$2353,MATCH(8,'Aux Graficos'!$H$2:$H$2353,0)),"") -> Chrome Mox | B85: =IF($A85="","",SUMIFS(Colección!$L$2:$L$10001,Colección!$F$2:$F$10001,$A85,Colección!$M$2:$M$10001,"Compra")) -> 315.49
A86: =IFERROR(INDEX('Aux Graficos'!$F$2:$F$2353,MATCH(9,'Aux Graficos'!$H$2:$H$2353,0)),"") -> Mox Opal | B86: =IF($A86="","",SUMIFS(Colección!$L$2:$L$10001,Colección!$F$2:$F$10001,$A86,Colección!$M$2:$M$10001,"Compra")) -> 296.72727
A87: =IFERROR(INDEX('Aux Graficos'!$F$2:$F$2353,MATCH(10,'Aux Graficos'!$H$2:$H$2353,0)),"") -> Orcish Bowmasters | B87: =IF($A87="","",SUMIFS(Colección!$L$2:$L$10001,Colección!$F$2:$F$10001,$A87,Colección!$M$2:$M$10001,"Compra")) -> 272.65
A88: =IFERROR(INDEX('Aux Graficos'!$F$2:$F$2353,MATCH(11,'Aux Graficos'!$H$2:$H$2353,0)),"") -> Bloodstained Mire | B88: =IF($A88="","",SUMIFS(Colección!$L$2:$L$10001,Colección!$F$2:$F$10001,$A88,Colección!$M$2:$M$10001,"Compra")) -> 268.37573
A89: =IFERROR(INDEX('Aux Graficos'!$F$2:$F$2353,MATCH(12,'Aux Graficos'!$H$2:$H$2353,0)),"") -> Agatha's Soul Cauldron | B89: =IF($A89="","",SUMIFS(Colección!$L$2:$L$10001,Colección!$F$2:$F$10001,$A89,Colección!$M$2:$M$10001,"Compra")) -> 266.25
A90: =IFERROR(INDEX('Aux Graficos'!$F$2:$F$2353,MATCH(13,'Aux Graficos'!$H$2:$H$2353,0)),"") -> Badgermole Cub | B90: =IF($A90="","",SUMIFS(Colección!$L$2:$L$10001,Colección!$F$2:$F$10001,$A90,Colección!$M$2:$M$10001,"Compra")) -> 241.81912
A91: =IFERROR(INDEX('Aux Graficos'!$F$2:$F$2353,MATCH(14,'Aux Graficos'!$H$2:$H$2353,0)),"") -> Arcane Box Set | B91: =IF($A91="","",SUMIFS(Colección!$L$2:$L$10001,Colección!$F$2:$F$10001,$A91,Colección!$M$2:$M$10001,"Compra")) -> 237.57917
A92: =IFERROR(INDEX('Aux Graficos'!$F$2:$F$2353,MATCH(15,'Aux Graficos'!$H$2:$H$2353,0)),"") -> Worlds Bundle 2025 | B92: =IF($A92="","",SUMIFS(Colección!$L$2:$L$10001,Colección!$F$2:$F$10001,$A92,Colección!$M$2:$M$10001,"Compra")) -> 236
A93: =IFERROR(INDEX('Aux Graficos'!$F$2:$F$2353,MATCH(16,'Aux Graficos'!$H$2:$H$2353,0)),"") -> Ocelot Pride (V.1) | B93: =IF($A93="","",SUMIFS(Colección!$L$2:$L$10001,Colección!$F$2:$F$10001,$A93,Colección!$M$2:$M$10001,"Compra")) -> 232.96279
A94: =IFERROR(INDEX('Aux Graficos'!$F$2:$F$2353,MATCH(17,'Aux Graficos'!$H$2:$H$2353,0)),"") -> Fury [Playset] | B94: =IF($A94="","",SUMIFS(Colección!$L$2:$L$10001,Colección!$F$2:$F$10001,$A94,Colección!$M$2:$M$10001,"Compra")) -> 223.7
A95: =IFERROR(INDEX('Aux Graficos'!$F$2:$F$2353,MATCH(18,'Aux Graficos'!$H$2:$H$2353,0)),"") -> Grief [Playset] | B95: =IF($A95="","",SUMIFS(Colección!$L$2:$L$10001,Colección!$F$2:$F$10001,$A95,Colección!$M$2:$M$10001,"Compra")) -> 213.62541
A96: =IFERROR(INDEX('Aux Graficos'!$F$2:$F$2353,MATCH(19,'Aux Graficos'!$H$2:$H$2353,0)),"") -> Force of Will | B96: =IF($A96="","",SUMIFS(Colección!$L$2:$L$10001,Colección!$F$2:$F$10001,$A96,Colección!$M$2:$M$10001,"Compra")) -> 212.91
A97: =IFERROR(INDEX('Aux Graficos'!$F$2:$F$2353,MATCH(20,'Aux Graficos'!$H$2:$H$2353,0)),"") -> Phlage, Titan of Fire's Fury (V.1) | B97: =IF($A97="","",SUMIFS(Colección!$L$2:$L$10001,Colección!$F$2:$F$10001,$A97,Colección!$M$2:$M$10001,"Compra")) -> 208.81
A98: =IFERROR(INDEX('Aux Graficos'!$F$2:$F$2353,MATCH(21,'Aux Graficos'!$H$2:$H$2353,0)),"") -> Ragavan, Nimble Pilferer [Playset] | B98: =IF($A98="","",SUMIFS(Colección!$L$2:$L$10001,Colección!$F$2:$F$10001,$A98,Colección!$M$2:$M$10001,"Compra")) -> 207.48
A99: =IFERROR(INDEX('Aux Graficos'!$F$2:$F$2353,MATCH(22,'Aux Graficos'!$H$2:$H$2353,0)),"") -> Swords to Plowshares | B99: =IF($A99="","",SUMIFS(Colección!$L$2:$L$10001,Colección!$F$2:$F$10001,$A99,Colección!$M$2:$M$10001,"Compra")) -> 205.72
A100: =IFERROR(INDEX('Aux Graficos'!$F$2:$F$2353,MATCH(23,'Aux Graficos'!$H$2:$H$2353,0)),"") -> Intuition | B100: =IF($A100="","",SUMIFS(Colección!$L$2:$L$10001,Colección!$F$2:$F$10001,$A100,Colección!$M$2:$M$10001,"Compra")) -> 200
A101: =IFERROR(INDEX('Aux Graficos'!$F$2:$F$2353,MATCH(24,'Aux Graficos'!$H$2:$H$2353,0)),"") -> Solitude [Playset] | B101: =IF($A101="","",SUMIFS(Colección!$L$2:$L$10001,Colección!$F$2:$F$10001,$A101,Colección!$M$2:$M$10001,"Compra")) -> 192.22656
A102: =IFERROR(INDEX('Aux Graficos'!$F$2:$F$2353,MATCH(25,'Aux Graficos'!$H$2:$H$2353,0)),"") -> Endurance | B102: =IF($A102="","",SUMIFS(Colección!$L$2:$L$10001,Colección!$F$2:$F$10001,$A102,Colección!$M$2:$M$10001,"Compra")) -> 187.79
A103: =IFERROR(INDEX('Aux Graficos'!$F$2:$F$2353,MATCH(26,'Aux Graficos'!$H$2:$H$2353,0)),"") -> Force of Negation (V.1) | B103: =IF($A103="","",SUMIFS(Colección!$L$2:$L$10001,Colección!$F$2:$F$10001,$A103,Colección!$M$2:$M$10001,"Compra")) -> 176.05
A104: =IFERROR(INDEX('Aux Graficos'!$F$2:$F$2353,MATCH(27,'Aux Graficos'!$H$2:$H$2353,0)),"") -> Ragavan, Nimble Pilferer | B104: =IF($A104="","",SUMIFS(Colección!$L$2:$L$10001,Colección!$F$2:$F$10001,$A104,Colección!$M$2:$M$10001,"Compra")) -> 175.04
A105: =IFERROR(INDEX('Aux Graficos'!$F$2:$F$2353,MATCH(28,'Aux Graficos'!$H$2:$H$2353,0)),"") -> Scalding Tarn (V.1) | B105: =IF($A105="","",SUMIFS(Colección!$L$2:$L$10001,Colección!$F$2:$F$10001,$A105,Colección!$M$2:$M$10001,"Compra")) -> 174.1082
A106: =IFERROR(INDEX('Aux Graficos'!$F$2:$F$2353,MATCH(29,'Aux Graficos'!$H$2:$H$2353,0)),"") -> Misty Rainforest (V.1) | B106: =IF($A106="","",SUMIFS(Colección!$L$2:$L$10001,Colección!$F$2:$F$10001,$A106,Colección!$M$2:$M$10001,"Compra")) -> 171.25565
A107: =IFERROR(INDEX('Aux Graficos'!$F$2:$F$2353,MATCH(30,'Aux Graficos'!$H$2:$H$2353,0)),"") -> Teferi, Time Raveler | B107: =IF($A107="","",SUMIFS(Colección!$L$2:$L$10001,Colección!$F$2:$F$10001,$A107,Colección!$M$2:$M$10001,"Compra")) -> 162.89944
...

Sheet Aux Graficos
A1: Edition | B1: Total compra | C1: Quantity compra | D1: Ranking | F1: Card Name | G1: Total compra | H1: Ranking | J1: Idioma | K1: Quantity compra | L1: Ranking
A2: ="2016 Version" -> 2016 Version | B2: =SUMIFS(Colección!$L$2:$L$10001,Colección!$G$2:$G$10001,$A2,Colección!$M$2:$M$10001,"Compra") -> 7.5830703 | C2: =SUMIFS(Colección!$K$2:$K$10001,Colección!$G$2:$G$10001,$A2,Colección!$M$2:$M$10001,"Compra") -> 2 | D2: =IF($B2=0,"",_xlfn.RANK.EQ($B2,$B$2:$B$321,0)+COUNTIF($B$2:B2,$B2)-1) -> 245 | F2: ="10 Ultimate Guard Dividers" -> 10 Ultimate Guard Dividers | G2: =SUMIFS(Colección!$L$2:$L$10001,Colección!$F$2:$F$10001,$F2,Colección!$M$2:$M$10001,"Compra") -> 1.9424487 | H2: =IF($G2=0,"",_xlfn.RANK.EQ($G2,$G$2:$G$2353,0)+COUNTIF($G$2:G2,$G2)-1) -> 1382 | J2: ="Alemán" -> Alemán | K2: =SUMIFS(Colección!$K$2:$K$10001,Colección!$I$2:$I$10001,$J2,Colección!$M$2:$M$10001,"Compra") -> 3 | L2: =IF($K2=0,"",_xlfn.RANK.EQ($K2,$K$2:$K$11,0)+COUNTIF($K$2:K2,$K2)-1) -> 9 | P2: =ORDENAR(UNICOS(FILTRAR(Colección[Edición];Colección[Edición]<>""))) | Q2: =ORDENAR(UNICOS(FILTRAR(Colección[Carta];Colección[Carta]<>""))) | R2: =ORDENAR(UNICOS(FILTRAR(Colección[Idioma];Colección[Idioma]<>"")))
A3: ="30th Anniversary Celebration" -> 30th Anniversary Celebration | B3: =SUMIFS(Colección!$L$2:$L$10001,Colección!$G$2:$G$10001,$A3,Colección!$M$2:$M$10001,"Compra") -> 5.5532001 | C3: =SUMIFS(Colección!$K$2:$K$10001,Colección!$G$2:$G$10001,$A3,Colección!$M$2:$M$10001,"Compra") -> 3 | D3: =IF($B3=0,"",_xlfn.RANK.EQ($B3,$B$2:$B$321,0)+COUNTIF($B$2:B3,$B3)-1) -> 262 | F3: ="100 Dragon Shield Sleeves" -> 100 Dragon Shield Sleeves | G3: =SUMIFS(Colección!$L$2:$L$10001,Colección!$F$2:$F$10001,$F3,Colección!$M$2:$M$10001,"Compra") -> 118.05668 | H3: =IF($G3=0,"",_xlfn.RANK.EQ($G3,$G$2:$G$2353,0)+COUNTIF($G$2:G3,$G3)-1) -> 59 | J3: ="Chino" -> Chino | K3: =SUMIFS(Colección!$K$2:$K$10001,Colección!$I$2:$I$10001,$J3,Colección!$M$2:$M$10001,"Compra") -> 5 | L3: =IF($K3=0,"",_xlfn.RANK.EQ($K3,$K$2:$K$11,0)+COUNTIF($K$2:K3,$K3)-1) -> 7
A4: ="Accesorios" -> Accesorios | B4: =SUMIFS(Colección!$L$2:$L$10001,Colección!$G$2:$G$10001,$A4,Colección!$M$2:$M$10001,"Compra") -> 252.84478 | C4: =SUMIFS(Colección!$K$2:$K$10001,Colección!$G$2:$G$10001,$A4,Colección!$M$2:$M$10001,"Compra") -> 51 | D4: =IF($B4=0,"",_xlfn.RANK.EQ($B4,$B$2:$B$321,0)+COUNTIF($B$2:B4,$B4)-1) -> 34 | F4: ="100 Gamegenic Just Sleeves Inner Sleeves" -> 100 Gamegenic Just Sleeves Inner Sleeves | G4: =SUMIFS(Colección!$L$2:$L$10001,Colección!$F$2:$F$10001,$F4,Colección!$M$2:$M$10001,"Compra") -> 14.31 | H4: =IF($G4=0,"",_xlfn.RANK.EQ($G4,$G$2:$G$2353,0)+COUNTIF($G$2:G4,$G4)-1) -> 521 | J4: ="Chino-S" -> Chino-S | K4: =SUMIFS(Colección!$K$2:$K$10001,Colección!$I$2:$I$10001,$J4,Colección!$M$2:$M$10001,"Compra") -> 64 | L4: =IF($K4=0,"",_xlfn.RANK.EQ($K4,$K$2:$K$11,0)+COUNTIF($K$2:K4,$K4)-1) -> 4
A5: ="Adventures in the Forgotten Realms" -> Adventures in the Forgotten Realms | B5: =SUMIFS(Colección!$L$2:$L$10001,Colección!$G$2:$G$10001,$A5,Colección!$M$2:$M$10001,"Compra") -> 74.958987 | C5: =SUMIFS(Colección!$K$2:$K$10001,Colección!$G$2:$G$10001,$A5,Colección!$M$2:$M$10001,"Compra") -> 35 | D5: =IF($B5=0,"",_xlfn.RANK.EQ($B5,$B$2:$B$321,0)+COUNTIF($B$2:B5,$B5)-1) -> 111 | F5: ="100 KMC Perfect Sized Sleeves" -> 100 KMC Perfect Sized Sleeves | G5: =SUMIFS(Colección!$L$2:$L$10001,Colección!$F$2:$F$10001,$F5,Colección!$M$2:$M$10001,"Compra") -> 65.014889 | H5: =IF($G5=0,"",_xlfn.RANK.EQ($G5,$G$2:$G$2353,0)+COUNTIF($G$2:G5,$G5)-1) -> 128 | J5: ="Chino-T" -> Chino-T | K5: =SUMIFS(Colección!$K$2:$K$10001,Colección!$I$2:$I$10001,$J5,Colección!$M$2:$M$10001,"Compra") -> 6 | L5: =IF($K5=0,"",_xlfn.RANK.EQ($K5,$K$2:$K$11,0)+COUNTIF($K$2:K5,$K5)-1) -> 6
A6: ="Adventures in the Forgotten Realms: Extras" -> Adventures in the Forgotten Realms: Extras | B6: =SUMIFS(Colección!$L$2:$L$10001,Colección!$G$2:$G$10001,$A6,Colección!$M$2:$M$10001,"Compra") -> 21.442508 | C6: =SUMIFS(Colección!$K$2:$K$10001,Colección!$G$2:$G$10001,$A6,Colección!$M$2:$M$10001,"Compra") -> 4 | D6: =IF($B6=0,"",_xlfn.RANK.EQ($B6,$B$2:$B$321,0)+COUNTIF($B$2:B6,$B6)-1) -> 202 | F6: ="100 Ultra Pro PLATINUM Nine Pocket Pages" -> 100 Ultra Pro PLATINUM Nine Pocket Pages | G6: =SUMIFS(Colección!$L$2:$L$10001,Colección!$F$2:$F$10001,$F6,Colección!$M$2:$M$10001,"Compra") -> 22.57773 | H6: =IF($G6=0,"",_xlfn.RANK.EQ($G6,$G$2:$G$2353,0)+COUNTIF($G$2:G6,$G6)-1) -> 347 | J6: ="Español" -> Español | K6: =SUMIFS(Colección!$K$2:$K$10001,Colección!$I$2:$I$10001,$J6,Colección!$M$2:$M$10001,"Compra") -> 451 | L6: =IF($K6=0,"",_xlfn.RANK.EQ($K6,$K$2:$K$11,0)+COUNTIF($K$2:K6,$K6)-1) -> 3
A7: ="Adventures in the Forgotten Realms: Promos" -> Adventures in the Forgotten Realms: Promos | B7: =SUMIFS(Colección!$L$2:$L$10001,Colección!$G$2:$G$10001,$A7,Colección!$M$2:$M$10001,"Compra") -> 1.6484393 | C7: =SUMIFS(Colección!$K$2:$K$10001,Colección!$G$2:$G$10001,$A7,Colección!$M$2:$M$10001,"Compra") -> 1 | D7: =IF($B7=0,"",_xlfn.RANK.EQ($B7,$B$2:$B$321,0)+COUNTIF($B$2:B7,$B7)-1) -> 292 | F7: ="Abandon" -> Abandon | G7: =SUMIFS(Colección!$L$2:$L$10001,Colección!$F$2:$F$10001,$F7,Colección!$M$2:$M$10001,"Compra") -> 9.2493671 | H7: =IF($G7=0,"",_xlfn.RANK.EQ($G7,$G$2:$G$2353,0)+COUNTIF($G$2:G7,$G7)-1) -> 691 | J7: ="Francés" -> Francés | K7: =SUMIFS(Colección!$K$2:$K$10001,Colección!$I$2:$I$10001,$J7,Colección!$M$2:$M$10001,"Compra") -> 4 | L7: =IF($K7=0,"",_xlfn.RANK.EQ($K7,$K$2:$K$11,0)+COUNTIF($K$2:K7,$K7)-1) -> 8
A8: ="Aether Revolt" -> Aether Revolt | B8: =SUMIFS(Colección!$L$2:$L$10001,Colección!$G$2:$G$10001,$A8,Colección!$M$2:$M$10001,"Compra") -> 201.79916 | C8: =SUMIFS(Colección!$K$2:$K$10001,Colección!$G$2:$G$10001,$A8,Colección!$M$2:$M$10001,"Compra") -> 24 | D8: =IF($B8=0,"",_xlfn.RANK.EQ($B8,$B$2:$B$321,0)+COUNTIF($B$2:B8,$B8)-1) -> 48 | F8: ="Abandon Attachments" -> Abandon Attachments | G8: =SUMIFS(Colección!$L$2:$L$10001,Colección!$F$2:$F$10001,$F8,Colección!$M$2:$M$10001,"Compra") -> 1.1789474 | H8: =IF($G8=0,"",_xlfn.RANK.EQ($G8,$G$2:$G$2353,0)+COUNTIF($G$2:G8,$G8)-1) -> 1569 | J8: ="Inglés" -> Inglés | K8: =SUMIFS(Colección!$K$2:$K$10001,Colección!$I$2:$I$10001,$J8,Colección!$M$2:$M$10001,"Compra") -> 5499 | L8: =IF($K8=0,"",_xlfn.RANK.EQ($K8,$K$2:$K$11,0)+COUNTIF($K$2:K8,$K8)-1) -> 1
A9: ="Aetherdrift" -> Aetherdrift | B9: =SUMIFS(Colección!$L$2:$L$10001,Colección!$G$2:$G$10001,$A9,Colección!$M$2:$M$10001,"Compra") -> 94.200366 | C9: =SUMIFS(Colección!$K$2:$K$10001,Colección!$G$2:$G$10001,$A9,Colección!$M$2:$M$10001,"Compra") -> 66 | D9: =IF($B9=0,"",_xlfn.RANK.EQ($B9,$B$2:$B$321,0)+COUNTIF($B$2:B9,$B9)-1) -> 86 | F9: ="Abandoned Hall" -> Abandoned Hall | G9: =SUMIFS(Colección!$L$2:$L$10001,Colección!$F$2:$F$10001,$F9,Colección!$M$2:$M$10001,"Compra") -> 0.64365654 | H9: =IF($G9=0,"",_xlfn.RANK.EQ($G9,$G$2:$G$2353,0)+COUNTIF($G$2:G9,$G9)-1) -> 1793 | J9: ="Italiano" -> Italiano | K9: =SUMIFS(Colección!$K$2:$K$10001,Colección!$I$2:$I$10001,$J9,Colección!$M$2:$M$10001,"Compra") -> 8 | L9: =IF($K9=0,"",_xlfn.RANK.EQ($K9,$K$2:$K$11,0)+COUNTIF($K$2:K9,$K9)-1) -> 5
A10: ="Aetherdrift: Extras" -> Aetherdrift: Extras | B10: =SUMIFS(Colección!$L$2:$L$10001,Colección!$G$2:$G$10001,$A10,Colección!$M$2:$M$10001,"Compra") -> 363.38989 | C10: =SUMIFS(Colección!$K$2:$K$10001,Colección!$G$2:$G$10001,$A10,Colección!$M$2:$M$10001,"Compra") -> 40 | D10: =IF($B10=0,"",_xlfn.RANK.EQ($B10,$B$2:$B$321,0)+COUNTIF($B$2:B10,$B10)-1) -> 22 | F10: ="Abhorrent Oculus" -> Abhorrent Oculus | G10: =SUMIFS(Colección!$L$2:$L$10001,Colección!$F$2:$F$10001,$F10,Colección!$M$2:$M$10001,"Compra") -> 65.07 | H10: =IF($G10=0,"",_xlfn.RANK.EQ($G10,$G$2:$G$2353,0)+COUNTIF($G$2:G10,$G10)-1) -> 126 | J10: ="Japonés" -> Japonés | K10: =SUMIFS(Colección!$K$2:$K$10001,Colección!$I$2:$I$10001,$J10,Colección!$M$2:$M$10001,"Compra") -> 1098 | L10: =IF($K10=0,"",_xlfn.RANK.EQ($K10,$K$2:$K$11,0)+COUNTIF($K$2:K10,$K10)-1) -> 2
A11: ="Alara Reborn" -> Alara Reborn | B11: =SUMIFS(Colección!$L$2:$L$10001,Colección!$G$2:$G$10001,$A11,Colección!$M$2:$M$10001,"Compra") -> 27.5 | C11: =SUMIFS(Colección!$K$2:$K$10001,Colección!$G$2:$G$10001,$A11,Colección!$M$2:$M$10001,"Compra") -> 9 | D11: =IF($B11=0,"",_xlfn.RANK.EQ($B11,$B$2:$B$321,0)+COUNTIF($B$2:B11,$B11)-1) -> 181 | F11: ="Abrupt Decay" -> Abrupt Decay | G11: =SUMIFS(Colección!$L$2:$L$10001,Colección!$F$2:$F$10001,$F11,Colección!$M$2:$M$10001,"Compra") -> 12.707967 | H11: =IF($G11=0,"",_xlfn.RANK.EQ($G11,$G$2:$G$2353,0)+COUNTIF($G$2:G11,$G11)-1) -> 559 | J11: ="Ruso" -> Ruso | K11: =SUMIFS(Colección!$K$2:$K$10001,Colección!$I$2:$I$10001,$J11,Colección!$M$2:$M$10001,"Compra") -> 1 | L11: =IF($K11=0,"",_xlfn.RANK.EQ($K11,$K$2:$K$11,0)+COUNTIF($K$2:K11,$K11)-1) -> 10
A12: ="Alliances" -> Alliances | B12: =SUMIFS(Colección!$L$2:$L$10001,Colección!$G$2:$G$10001,$A12,Colección!$M$2:$M$10001,"Compra") -> 220.32818 | C12: =SUMIFS(Colección!$K$2:$K$10001,Colección!$G$2:$G$10001,$A12,Colección!$M$2:$M$10001,"Compra") -> 6 | D12: =IF($B12=0,"",_xlfn.RANK.EQ($B12,$B$2:$B$321,0)+COUNTIF($B$2:B12,$B12)-1) -> 44 | F12: ="Absorb" -> Absorb | G12: =SUMIFS(Colección!$L$2:$L$10001,Colección!$F$2:$F$10001,$F12,Colección!$M$2:$M$10001,"Compra") -> 1.5463706 | H12: =IF($G12=0,"",_xlfn.RANK.EQ($G12,$G$2:$G$2353,0)+COUNTIF($G$2:G12,$G12)-1) -> 1477
A13: ="Amber" -> Amber | B13: =SUMIFS(Colección!$L$2:$L$10001,Colección!$G$2:$G$10001,$A13,Colección!$M$2:$M$10001,"Compra") -> 7.2648649 | C13: =SUMIFS(Colección!$K$2:$K$10001,Colección!$G$2:$G$10001,$A13,Colección!$M$2:$M$10001,"Compra") -> 1 | D13: =IF($B13=0,"",_xlfn.RANK.EQ($B13,$B$2:$B$321,0)+COUNTIF($B$2:B13,$B13)-1) -> 247 | F13: ="Abstergo Entertainment (V.1)" -> Abstergo Entertainment (V.1) | G13: =SUMIFS(Colección!$L$2:$L$10001,Colección!$F$2:$F$10001,$F13,Colección!$M$2:$M$10001,"Compra") -> 1.6299891 | H13: =IF($G13=0,"",_xlfn.RANK.EQ($G13,$G$2:$G$2353,0)+COUNTIF($G$2:G13,$G13)-1) -> 1455
A14: ="Amethyst" -> Amethyst | B14: =SUMIFS(Colección!$L$2:$L$10001,Colección!$G$2:$G$10001,$A14,Colección!$M$2:$M$10001,"Compra") -> 7.7512531 | C14: =SUMIFS(Colección!$K$2:$K$10001,Colección!$G$2:$G$10001,$A14,Colección!$M$2:$M$10001,"Compra") -> 1 | D14: =IF($B14=0,"",_xlfn.RANK.EQ($B14,$B$2:$B$321,0)+COUNTIF($B$2:B14,$B14)-1) -> 244 | F14: ="Abundant Growth" -> Abundant Growth | G14: =SUMIFS(Colección!$L$2:$L$10001,Colección!$F$2:$F$10001,$F14,Colección!$M$2:$M$10001,"Compra") -> 5.729429 | H14: =IF($G14=0,"",_xlfn.RANK.EQ($G14,$G$2:$G$2353,0)+COUNTIF($G$2:G14,$G14)-1) -> 910
A15: ="Amonkhet" -> Amonkhet | B15: =SUMIFS(Colección!$L$2:$L$10001,Colección!$G$2:$G$10001,$A15,Colección!$M$2:$M$10001,"Compra") -> 22.213681 | C15: =SUMIFS(Colección!$K$2:$K$10001,Colección!$G$2:$G$10001,$A15,Colección!$M$2:$M$10001,"Compra") -> 26 | D15: =IF($B15=0,"",_xlfn.RANK.EQ($B15,$B$2:$B$321,0)+COUNTIF($B$2:B15,$B15)-1) -> 199 | F15: ="Abundant Growth (V.2)" -> Abundant Growth (V.2) | G15: =SUMIFS(Colección!$L$2:$L$10001,Colección!$F$2:$F$10001,$F15,Colección!$M$2:$M$10001,"Compra") -> 1.8881226 | H15: =IF($G15=0,"",_xlfn.RANK.EQ($G15,$G$2:$G$2353,0)+COUNTIF($G$2:G15,$G15)-1) -> 1388
A16: ="Apocalypse" -> Apocalypse | B16: =SUMIFS(Colección!$L$2:$L$10001,Colección!$G$2:$G$10001,$A16,Colección!$M$2:$M$10001,"Compra") -> 190.08716 | C16: =SUMIFS(Colección!$K$2:$K$10001,Colección!$G$2:$G$10001,$A16,Colección!$M$2:$M$10001,"Compra") -> 34 | D16: =IF($B16=0,"",_xlfn.RANK.EQ($B16,$B$2:$B$321,0)+COUNTIF($B$2:B16,$B16)-1) -> 50 | F16: ="Abundant Harvest" -> Abundant Harvest | G16: =SUMIFS(Colección!$L$2:$L$10001,Colección!$F$2:$F$10001,$F16,Colección!$M$2:$M$10001,"Compra") -> 0.45013193 | H16: =IF($G16=0,"",_xlfn.RANK.EQ($G16,$G$2:$G$2353,0)+COUNTIF($G$2:G16,$G16)-1) -> 1915
A17: ="Avacyn Restored" -> Avacyn Restored | B17: =SUMIFS(Colección!$L$2:$L$10001,Colección!$G$2:$G$10001,$A17,Colección!$M$2:$M$10001,"Compra") -> 155.46771 | C17: =SUMIFS(Colección!$K$2:$K$10001,Colección!$G$2:$G$10001,$A17,Colección!$M$2:$M$10001,"Compra") -> 16 | D17: =IF($B17=0,"",_xlfn.RANK.EQ($B17,$B$2:$B$321,0)+COUNTIF($B$2:B17,$B17)-1) -> 63 | F17: ="Academy Manufactor [Playset]" -> Academy Manufactor [Playset] | G17: =SUMIFS(Colección!$L$2:$L$10001,Colección!$F$2:$F$10001,$F17,Colección!$M$2:$M$10001,"Compra") -> 12.18 | H17: =IF($G17=0,"",_xlfn.RANK.EQ($G17,$G$2:$G$2353,0)+COUNTIF($G$2:G17,$G17)-1) -> 572
A18: ="Avatar: The Last Airbender" -> Avatar: The Last Airbender | B18: =SUMIFS(Colección!$L$2:$L$10001,Colección!$G$2:$G$10001,$A18,Colección!$M$2:$M$10001,"Compra") -> 0.28942308 | C18: =SUMIFS(Colección!$K$2:$K$10001,Colección!$G$2:$G$10001,$A18,Colección!$M$2:$M$10001,"Compra") -> 1 | D18: =IF($B18=0,"",_xlfn.RANK.EQ($B18,$B$2:$B$321,0)+COUNTIF($B$2:B18,$B18)-1) -> 310 | F18: ="Acceptable Losses" -> Acceptable Losses | G18: =SUMIFS(Colección!$L$2:$L$10001,Colección!$F$2:$F$10001,$F18,Colección!$M$2:$M$10001,"Compra") -> 3.6077508 | H18: =IF($G18=0,"",_xlfn.RANK.EQ($G18,$G$2:$G$2353,0)+COUNTIF($G$2:G18,$G18)-1) -> 1103
A19: ="Awakening of the New Era" -> Awakening of the New Era | B19: =SUMIFS(Colección!$L$2:$L$10001,Colección!$G$2:$G$10001,$A19,Colección!$M$2:$M$10001,"Compra") -> 97.457608 | C19: =SUMIFS(Colección!$K$2:$K$10001,Colección!$G$2:$G$10001,$A19,Colección!$M$2:$M$10001,"Compra") -> 120 | D19: =IF($B19=0,"",_xlfn.RANK.EQ($B19,$B$2:$B$321,0)+COUNTIF($B$2:B19,$B19)-1) -> 84 | F19: ="Accumulate Wisdom" -> Accumulate Wisdom | G19: =SUMIFS(Colección!$L$2:$L$10001,Colección!$F$2:$F$10001,$F19,Colección!$M$2:$M$10001,"Compra") -> 4.4210526 | H19: =IF($G19=0,"",_xlfn.RANK.EQ($G19,$G$2:$G$2353,0)+COUNTIF($G$2:G19,$G19)-1) -> 1007
A20: ="Battle for Zendikar" -> Battle for Zendikar | B20: =SUMIFS(Colección!$L$2:$L$10001,Colección!$G$2:$G$10001,$A20,Colección!$M$2:$M$10001,"Compra") -> 89.314353 | C20: =SUMIFS(Colección!$K$2:$K$10001,Colección!$G$2:$G$10001,$A20,Colección!$M$2:$M$10001,"Compra") -> 18 | D20: =IF($B20=0,"",_xlfn.RANK.EQ($B20,$B$2:$B$321,0)+COUNTIF($B$2:B20,$B20)-1) -> 93 | F20: ="Accumulated Knowledge" -> Accumulated Knowledge | G20: =SUMIFS(Colección!$L$2:$L$10001,Colección!$F$2:$F$10001,$F20,Colección!$M$2:$M$10001,"Compra") -> 7.5 | H20: =IF($G20=0,"",_xlfn.RANK.EQ($G20,$G$2:$G$2353,0)+COUNTIF($G$2:G20,$G20)-1) -> 774
A21: ="Betrayers of Kamigawa" -> Betrayers of Kamigawa | B21: =SUMIFS(Colección!$L$2:$L$10001,Colección!$G$2:$G$10001,$A21,Colección!$M$2:$M$10001,"Compra") -> 78.78963 | C21: =SUMIFS(Colección!$K$2:$K$10001,Colección!$G$2:$G$10001,$A21,Colección!$M$2:$M$10001,"Compra") -> 13 | D21: =IF($B21=0,"",_xlfn.RANK.EQ($B21,$B$2:$B$321,0)+COUNTIF($B$2:B21,$B21)-1) -> 105 | F21: ="Accursed Marauder (V.1)" -> Accursed Marauder (V.1) | G21: =SUMIFS(Colección!$L$2:$L$10001,Colección!$F$2:$F$10001,$F21,Colección!$M$2:$M$10001,"Compra") -> 1.8419022 | H21: =IF($G21=0,"",_xlfn.RANK.EQ($G21,$G$2:$G$2353,0)+COUNTIF($G$2:G21,$G21)-1) -> 1392
A22: ="Black" -> Black | B22: =SUMIFS(Colección!$L$2:$L$10001,Colección!$G$2:$G$10001,$A22,Colección!$M$2:$M$10001,"Compra") -> 15.892449 | C22: =SUMIFS(Colección!$K$2:$K$10001,Colección!$G$2:$G$10001,$A22,Colección!$M$2:$M$10001,"Compra") -> 2 | D22: =IF($B22=0,"",_xlfn.RANK.EQ($B22,$B$2:$B$321,0)+COUNTIF($B$2:B22,$B22)-1) -> 218 | F22: ="Aclazotz, Deepest Betrayal // Temple of the Dead" -> Aclazotz, Deepest Betrayal // Temple of the Dead | G22: =SUMIFS(Colección!$L$2:$L$10001,Colección!$F$2:$F$10001,$F22,Colección!$M$2:$M$10001,"Compra") -> 3.74 | H22: =IF($G22=0,"",_xlfn.RANK.EQ($G22,$G$2:$G$2353,0)+COUNTIF($G$2:G22,$G22)-1) -> 1088
A23: ="Bloomburrow" -> Bloomburrow | B23: =SUMIFS(Colección!$L$2:$L$10001,Colección!$G$2:$G$10001,$A23,Colección!$M$2:$M$10001,"Compra") -> 229.5508 | C23: =SUMIFS(Colección!$K$2:$K$10001,Colección!$G$2:$G$10001,$A23,Colección!$M$2:$M$10001,"Compra") -> 73 | D23: =IF($B23=0,"",_xlfn.RANK.EQ($B23,$B$2:$B$321,0)+COUNTIF($B$2:B23,$B23)-1) -> 42 | F23: ="Adaptatron" -> Adaptatron | G23: =SUMIFS(Colección!$L$2:$L$10001,Colección!$F$2:$F$10001,$F23,Colección!$M$2:$M$10001,"Compra") -> 5.8102456 | H23: =IF($G23=0,"",_xlfn.RANK.EQ($G23,$G$2:$G$2353,0)+COUNTIF($G$2:G23,$G23)-1) -> 901
A24: ="Bloomburrow: Extras" -> Bloomburrow: Extras | B24: =SUMIFS(Colección!$L$2:$L$10001,Colección!$G$2:$G$10001,$A24,Colección!$M$2:$M$10001,"Compra") -> 158.111 | C24: =SUMIFS(Colección!$K$2:$K$10001,Colección!$G$2:$G$10001,$A24,Colección!$M$2:$M$10001,"Compra") -> 25 | D24: =IF($B24=0,"",_xlfn.RANK.EQ($B24,$B$2:$B$321,0)+COUNTIF($B$2:B24,$B24)-1) -> 61 | F24: ="Adarkar Wastes" -> Adarkar Wastes | G24: =SUMIFS(Colección!$L$2:$L$10001,Colección!$F$2:$F$10001,$F24,Colección!$M$2:$M$10001,"Compra") -> 28.654545 | H24: =IF($G24=0,"",_xlfn.RANK.EQ($G24,$G$2:$G$2353,0)+COUNTIF($G$2:G24,$G24)-1) -> 286
A25: ="Bloomburrow: Tokens" -> Bloomburrow: Tokens | B25: =SUMIFS(Colección!$L$2:$L$10001,Colección!$G$2:$G$10001,$A25,Colección!$M$2:$M$10001,"Compra") -> 2.4070833 | C25: =SUMIFS(Colección!$K$2:$K$10001,Colección!$G$2:$G$10001,$A25,Colección!$M$2:$M$10001,"Compra") -> 4 | D25: =IF($B25=0,"",_xlfn.RANK.EQ($B25,$B$2:$B$321,0)+COUNTIF($B$2:B25,$B25)-1) -> 279 | F25: ="Adio (OP03-002)" -> Adio (OP03-002) | G25: =SUMIFS(Colección!$L$2:$L$10001,Colección!$F$2:$F$10001,$F25,Colección!$M$2:$M$10001,"Compra") -> 0.2855814 | H25: =IF($G25=0,"",_xlfn.RANK.EQ($G25,$G$2:$G$2353,0)+COUNTIF($G$2:G25,$G25)-1) -> 2006
A26: ="Buy a Box Promos" -> Buy a Box Promos | B26: =SUMIFS(Colección!$L$2:$L$10001,Colección!$G$2:$G$10001,$A26,Colección!$M$2:$M$10001,"Compra") -> 30.549471 | C26: =SUMIFS(Colección!$K$2:$K$10001,Colección!$G$2:$G$10001,$A26,Colección!$M$2:$M$10001,"Compra") -> 7 | D26: =IF($B26=0,"",_xlfn.RANK.EQ($B26,$B$2:$B$321,0)+COUNTIF($B$2:B26,$B26)-1) -> 174 | F26: ="Aether Hub" -> Aether Hub | G26: =SUMIFS(Colección!$L$2:$L$10001,Colección!$F$2:$F$10001,$F26,Colección!$M$2:$M$10001,"Compra") -> 3.316609 | H26: =IF($G26=0,"",_xlfn.RANK.EQ($G26,$G$2:$G$2353,0)+COUNTIF($G$2:G26,$G26)-1) -> 1147
A27: ="Cats & Cantrips Tokens" -> Cats & Cantrips Tokens | B27: =SUMIFS(Colección!$L$2:$L$10001,Colección!$G$2:$G$10001,$A27,Colección!$M$2:$M$10001,"Compra") -> 42.32 | C27: =SUMIFS(Colección!$K$2:$K$10001,Colección!$G$2:$G$10001,$A27,Colección!$M$2:$M$10001,"Compra") -> 24 | D27: =IF($B27=0,"",_xlfn.RANK.EQ($B27,$B$2:$B$321,0)+COUNTIF($B$2:B27,$B27)-1) -> 153 | F27: ="Aether Spellbomb" -> Aether Spellbomb | G27: =SUMIFS(Colección!$L$2:$L$10001,Colección!$F$2:$F$10001,$F27,Colección!$M$2:$M$10001,"Compra") -> 0.53610973 | H27: =IF($G27=0,"",_xlfn.RANK.EQ($G27,$G$2:$G$2353,0)+COUNTIF($G$2:G27,$G27)-1) -> 1864
A28: ="Champions of Kamigawa" -> Champions of Kamigawa | B28: =SUMIFS(Colección!$L$2:$L$10001,Colección!$G$2:$G$10001,$A28,Colección!$M$2:$M$10001,"Compra") -> 59.392632 | C28: =SUMIFS(Colección!$K$2:$K$10001,Colección!$G$2:$G$10001,$A28,Colección!$M$2:$M$10001,"Compra") -> 17 | D28: =IF($B28=0,"",_xlfn.RANK.EQ($B28,$B$2:$B$321,0)+COUNTIF($B$2:B28,$B28)-1) -> 131 | F28: ="Aether Vial (V.1)" -> Aether Vial (V.1) | G28: =SUMIFS(Colección!$L$2:$L$10001,Colección!$F$2:$F$10001,$F28,Colección!$M$2:$M$10001,"Compra") -> 45.8 | H28: =IF($G28=0,"",_xlfn.RANK.EQ($G28,$G$2:$G$2353,0)+COUNTIF($G$2:G28,$G28)-1) -> 188
A29: ="Chronicles: Japanese" -> Chronicles: Japanese | B29: =SUMIFS(Colección!$L$2:$L$10001,Colección!$G$2:$G$10001,$A29,Colección!$M$2:$M$10001,"Compra") -> 78.12 | C29: =SUMIFS(Colección!$K$2:$K$10001,Colección!$G$2:$G$10001,$A29,Colección!$M$2:$M$10001,"Compra") -> 12 | D29: =IF($B29=0,"",_xlfn.RANK.EQ($B29,$B$2:$B$321,0)+COUNTIF($B$2:B29,$B29)-1) -> 106 | F29: ="Aether Vial [Playset]" -> Aether Vial [Playset] | G29: =SUMIFS(Colección!$L$2:$L$10001,Colección!$F$2:$F$10001,$F29,Colección!$M$2:$M$10001,"Compra") -> 51.28 | H29: =IF($G29=0,"",_xlfn.RANK.EQ($G29,$G$2:$G$2353,0)+COUNTIF($G$2:G29,$G29)-1) -> 169
A30: ="Clear" -> Clear | B30: =SUMIFS(Colección!$L$2:$L$10001,Colección!$G$2:$G$10001,$A30,Colección!$M$2:$M$10001,"Compra") -> 41.448288 | C30: =SUMIFS(Colección!$K$2:$K$10001,Colección!$G$2:$G$10001,$A30,Colección!$M$2:$M$10001,"Compra") -> 5 | D30: =IF($B30=0,"",_xlfn.RANK.EQ($B30,$B$2:$B$321,0)+COUNTIF($B$2:B30,$B30)-1) -> 156 | F30: ="Aftermath Analyst" -> Aftermath Analyst | G30: =SUMIFS(Colección!$L$2:$L$10001,Colección!$F$2:$F$10001,$F30,Colección!$M$2:$M$10001,"Compra") -> 3.9272727 | H30: =IF($G30=0,"",_xlfn.RANK.EQ($G30,$G$2:$G$2353,0)+COUNTIF($G$2:G30,$G30)-1) -> 1069
A31: ="Commander 2013" -> Commander 2013 | B31: =SUMIFS(Colección!$L$2:$L$10001,Colección!$G$2:$G$10001,$A31,Colección!$M$2:$M$10001,"Compra") -> 2.7746232 | C31: =SUMIFS(Colección!$K$2:$K$10001,Colección!$G$2:$G$10001,$A31,Colección!$M$2:$M$10001,"Compra") -> 11 | D31: =IF($B31=0,"",_xlfn.RANK.EQ($B31,$B$2:$B$321,0)+COUNTIF($B$2:B31,$B31)-1) -> 278 | F31: ="Agatha's Soul Cauldron" -> Agatha's Soul Cauldron | G31: =SUMIFS(Colección!$L$2:$L$10001,Colección!$F$2:$F$10001,$F31,Colección!$M$2:$M$10001,"Compra") -> 266.25 | H31: =IF($G31=0,"",_xlfn.RANK.EQ($G31,$G$2:$G$2353,0)+COUNTIF($G$2:G31,$G31)-1) -> 12
A32: ="Commander 2014" -> Commander 2014 | B32: =SUMIFS(Colección!$L$2:$L$10001,Colección!$G$2:$G$10001,$A32,Colección!$M$2:$M$10001,"Compra") -> 2.2122022 | C32: =SUMIFS(Colección!$K$2:$K$10001,Colección!$G$2:$G$10001,$A32,Colección!$M$2:$M$10001,"Compra") -> 4 | D32: =IF($B32=0,"",_xlfn.RANK.EQ($B32,$B$2:$B$321,0)+COUNTIF($B$2:B32,$B32)-1) -> 282 | F32: ="Agony Warp" -> Agony Warp | G32: =SUMIFS(Colección!$L$2:$L$10001,Colección!$F$2:$F$10001,$F32,Colección!$M$2:$M$10001,"Compra") -> 0.27529412 | H32: =IF($G32=0,"",_xlfn.RANK.EQ($G32,$G$2:$G$2353,0)+COUNTIF($G$2:G32,$G32)-1) -> 2026
A33: ="Commander 2016" -> Commander 2016 | B33: =SUMIFS(Colección!$L$2:$L$10001,Colección!$G$2:$G$10001,$A33,Colección!$M$2:$M$10001,"Compra") -> 2.1057062 | C33: =SUMIFS(Colección!$K$2:$K$10001,Colección!$G$2:$G$10001,$A33,Colección!$M$2:$M$10001,"Compra") -> 2 | D33: =IF($B33=0,"",_xlfn.RANK.EQ($B33,$B$2:$B$321,0)+COUNTIF($B$2:B33,$B33)-1) -> 286 | F33: ="Air Door (OP03-094)" -> Air Door (OP03-094) | G33: =SUMIFS(Colección!$L$2:$L$10001,Colección!$F$2:$F$10001,$F33,Colección!$M$2:$M$10001,"Compra") -> 0.22608527 | H33: =IF($G33=0,"",_xlfn.RANK.EQ($G33,$G$2:$G$2353,0)+COUNTIF($G$2:G33,$G33)-1) -> 2055
A34: ="Commander 2018" -> Commander 2018 | B34: =SUMIFS(Colección!$L$2:$L$10001,Colección!$G$2:$G$10001,$A34,Colección!$M$2:$M$10001,"Compra") -> 6.8859982 | C34: =SUMIFS(Colección!$K$2:$K$10001,Colección!$G$2:$G$10001,$A34,Colección!$M$2:$M$10001,"Compra") -> 10 | D34: =IF($B34=0,"",_xlfn.RANK.EQ($B34,$B$2:$B$321,0)+COUNTIF($B$2:B34,$B34)-1) -> 250 | F34: ="Ajani Vengeant" -> Ajani Vengeant | G34: =SUMIFS(Colección!$L$2:$L$10001,Colección!$F$2:$F$10001,$F34,Colección!$M$2:$M$10001,"Compra") -> 4.321679 | H34: =IF($G34=0,"",_xlfn.RANK.EQ($G34,$G$2:$G$2353,0)+COUNTIF($G$2:G34,$G34)-1) -> 1031
A35: ="Commander 2019" -> Commander 2019 | B35: =SUMIFS(Colección!$L$2:$L$10001,Colección!$G$2:$G$10001,$A35,Colección!$M$2:$M$10001,"Compra") -> 3.3197026 | C35: =SUMIFS(Colección!$K$2:$K$10001,Colección!$G$2:$G$10001,$A35,Colección!$M$2:$M$10001,"Compra") -> 9 | D35: =IF($B35=0,"",_xlfn.RANK.EQ($B35,$B$2:$B$321,0)+COUNTIF($B$2:B35,$B35)-1) -> 274 | F35: ="Ajani, Nacatl Pariah // Ajani, Nacatl Avenger" -> Ajani, Nacatl Pariah // Ajani, Nacatl Avenger | G35: =SUMIFS(Colección!$L$2:$L$10001,Colección!$F$2:$F$10001,$F35,Colección!$M$2:$M$10001,"Compra") -> 79.27 | H35: =IF($G35=0,"",_xlfn.RANK.EQ($G35,$G$2:$G$2353,0)+COUNTIF($G$2:G35,$G35)-1) -> 101
A36: ="Commander Anthology" -> Commander Anthology | B36: =SUMIFS(Colección!$L$2:$L$10001,Colección!$G$2:$G$10001,$A36,Colección!$M$2:$M$10001,"Compra") -> 0.42496248 | C36: =SUMIFS(Colección!$K$2:$K$10001,Colección!$G$2:$G$10001,$A36,Colección!$M$2:$M$10001,"Compra") -> 4 | D36: =IF($B36=0,"",_xlfn.RANK.EQ($B36,$B$2:$B$321,0)+COUNTIF($B$2:B36,$B36)-1) -> 309 | F36: ="Ajani, Nacatl Pariah // Ajani, Nacatl Avenger (V.1)" -> Ajani, Nacatl Pariah // Ajani, Nacatl Avenger (V.1) | G36: =SUMIFS(Colección!$L$2:$L$10001,Colección!$F$2:$F$10001,$F36,Colección!$M$2:$M$10001,"Compra") -> 93.117211 | H36: =IF($G36=0,"",_xlfn.RANK.EQ($G36,$G$2:$G$2353,0)+COUNTIF($G$2:G36,$G36)-1) -> 83
A37: ="Commander Anthology II" -> Commander Anthology II | B37: =SUMIFS(Colección!$L$2:$L$10001,Colección!$G$2:$G$10001,$A37,Colección!$M$2:$M$10001,"Compra") -> 4.3929603 | C37: =SUMIFS(Colección!$K$2:$K$10001,Colección!$G$2:$G$10001,$A37,Colección!$M$2:$M$10001,"Compra") -> 2 | D37: =IF($B37=0,"",_xlfn.RANK.EQ($B37,$B$2:$B$321,0)+COUNTIF($B$2:B37,$B37)-1) -> 268 | F37: ="Ajani, the Greathearted" -> Ajani, the Greathearted | G37: =SUMIFS(Colección!$L$2:$L$10001,Colección!$F$2:$F$10001,$F37,Colección!$M$2:$M$10001,"Compra") -> 0.54545455 | H37: =IF($G37=0,"",_xlfn.RANK.EQ($G37,$G$2:$G$2353,0)+COUNTIF($G$2:G37,$G37)-1) -> 1857
A38: ="Commander Collectio" -> Commander Collectio | B38: =SUMIFS(Colección!$L$2:$L$10001,Colección!$G$2:$G$10001,$A38,Colección!$M$2:$M$10001,"Compra") -> 0.83820896 | C38: =SUMIFS(Colección!$K$2:$K$10001,Colección!$G$2:$G$10001,$A38,Colección!$M$2:$M$10001,"Compra") -> 2 | D38: =IF($B38=0,"",_xlfn.RANK.EQ($B38,$B$2:$B$321,0)+COUNTIF($B$2:B38,$B38)-1) -> 302 | F38: ="Akroma's Vengeance" -> Akroma's Vengeance | G38: =SUMIFS(Colección!$L$2:$L$10001,Colección!$F$2:$F$10001,$F38,Colección!$M$2:$M$10001,"Compra") -> 1.3092625 | H38: =IF($G38=0,"",_xlfn.RANK.EQ($G38,$G$2:$G$2353,0)+COUNTIF($G$2:G38,$G38)-1) -> 1541
A39: ="Commander Legends" -> Commander Legends | B39: =SUMIFS(Colección!$L$2:$L$10001,Colección!$G$2:$G$10001,$A39,Colección!$M$2:$M$10001,"Compra") -> 10.920437 | C39: =SUMIFS(Colección!$K$2:$K$10001,Colección!$G$2:$G$10001,$A39,Colección!$M$2:$M$10001,"Compra") -> 10 | D39: =IF($B39=0,"",_xlfn.RANK.EQ($B39,$B$2:$B$321,0)+COUNTIF($B$2:B39,$B39)-1) -> 236 | F39: ="Akroma, Angel of Wrath" -> Akroma, Angel of Wrath | G39: =SUMIFS(Colección!$L$2:$L$10001,Colección!$F$2:$F$10001,$F39,Colección!$M$2:$M$10001,"Compra") -> 8.7915169 | H39: =IF($G39=0,"",_xlfn.RANK.EQ($G39,$G$2:$G$2353,0)+COUNTIF($G$2:G39,$G39)-1) -> 714
A40: ="Commander Legends: Battle for Baldur's Gate" -> Commander Legends: Battle for Baldur's Gate | B40: =SUMIFS(Colección!$L$2:$L$10001,Colección!$G$2:$G$10001,$A40,Colección!$M$2:$M$10001,"Compra") -> 1.5781946 | C40: =SUMIFS(Colección!$K$2:$K$10001,Colección!$G$2:$G$10001,$A40,Colección!$M$2:$M$10001,"Compra") -> 4 | D40: =IF($B40=0,"",_xlfn.RANK.EQ($B40,$B$2:$B$321,0)+COUNTIF($B$2:B40,$B40)-1) -> 294 | F40: ="All Is Dust" -> All Is Dust | G40: =SUMIFS(Colección!$L$2:$L$10001,Colección!$F$2:$F$10001,$F40,Colección!$M$2:$M$10001,"Compra") -> 22.07 | H40: =IF($G40=0,"",_xlfn.RANK.EQ($G40,$G$2:$G$2353,0)+COUNTIF($G$2:G40,$G40)-1) -> 353
A41: ="Commander Legends: Battle for Baldur's Gate: Extras" -> Commander Legends: Battle for Baldur's Gate: Extras | B41: =SUMIFS(Colección!$L$2:$L$10001,Colección!$G$2:$G$10001,$A41,Colección!$M$2:$M$10001,"Compra") -> 15.579125 | C41: =SUMIFS(Colección!$K$2:$K$10001,Colección!$G$2:$G$10001,$A41,Colección!$M$2:$M$10001,"Compra") -> 17 | D41: =IF($B41=0,"",_xlfn.RANK.EQ($B41,$B$2:$B$321,0)+COUNTIF($B$2:B41,$B41)-1) -> 219 | F41: ="Alpine Moon" -> Alpine Moon | G41: =SUMIFS(Colección!$L$2:$L$10001,Colección!$F$2:$F$10001,$F41,Colección!$M$2:$M$10001,"Compra") -> 7.8954394 | H41: =IF($G41=0,"",_xlfn.RANK.EQ($G41,$G$2:$G$2353,0)+COUNTIF($G$2:G41,$G41)-1) -> 755
A42: ="Commander Legends: Extras" -> Commander Legends: Extras | B42: =SUMIFS(Colección!$L$2:$L$10001,Colección!$G$2:$G$10001,$A42,Colección!$M$2:$M$10001,"Compra") -> 19.51324 | C42: =SUMIFS(Colección!$K$2:$K$10001,Colección!$G$2:$G$10001,$A42,Colección!$M$2:$M$10001,"Compra") -> 12 | D42: =IF($B42=0,"",_xlfn.RANK.EQ($B42,$B$2:$B$321,0)+COUNTIF($B$2:B42,$B42)-1) -> 207 | F42: ="Altanak, the Thrice-Called" -> Altanak, the Thrice-Called | G42: =SUMIFS(Colección!$L$2:$L$10001,Colección!$F$2:$F$10001,$F42,Colección!$M$2:$M$10001,"Compra") -> 0.49384615 | H42: =IF($G42=0,"",_xlfn.RANK.EQ($G42,$G$2:$G$2353,0)+COUNTIF($G$2:G42,$G42)-1) -> 1885
A43: ="Commander Masters" -> Commander Masters | B43: =SUMIFS(Colección!$L$2:$L$10001,Colección!$G$2:$G$10001,$A43,Colección!$M$2:$M$10001,"Compra") -> 26.172152 | C43: =SUMIFS(Colección!$K$2:$K$10001,Colección!$G$2:$G$10001,$A43,Colección!$M$2:$M$10001,"Compra") -> 8 | D43: =IF($B43=0,"",_xlfn.RANK.EQ($B43,$B$2:$B$321,0)+COUNTIF($B$2:B43,$B43)-1) -> 192 | F43: ="Alvida (OP03-023)" -> Alvida (OP03-023) | G43: =SUMIFS(Colección!$L$2:$L$10001,Colección!$F$2:$F$10001,$F43,Colección!$M$2:$M$10001,"Compra") -> 0.16658915 | H43: =IF($G43=0,"",_xlfn.RANK.EQ($G43,$G$2:$G$2353,0)+COUNTIF($G$2:G43,$G43)-1) -> 2099
A44: ="Commander Masters: Extras" -> Commander Masters: Extras | B44: =SUMIFS(Colección!$L$2:$L$10001,Colección!$G$2:$G$10001,$A44,Colección!$M$2:$M$10001,"Compra") -> 20.742888 | C44: =SUMIFS(Colección!$K$2:$K$10001,Colección!$G$2:$G$10001,$A44,Colección!$M$2:$M$10001,"Compra") -> 8 | D44: =IF($B44=0,"",_xlfn.RANK.EQ($B44,$B$2:$B$321,0)+COUNTIF($B$2:B44,$B44)-1) -> 204 | F44: ="Amalia Benavides Aguirre" -> Amalia Benavides Aguirre | G44: =SUMIFS(Colección!$L$2:$L$10001,Colección!$F$2:$F$10001,$F44,Colección!$M$2:$M$10001,"Compra") -> 6.02 | H44: =IF($G44=0,"",_xlfn.RANK.EQ($G44,$G$2:$G$2353,0)+COUNTIF($G$2:G44,$G44)-1) -> 887
A45: ="Commander: Adventures in the Forgotten Realms" -> Commander: Adventures in the Forgotten Realms | B45: =SUMIFS(Colección!$L$2:$L$10001,Colección!$G$2:$G$10001,$A45,Colección!$M$2:$M$10001,"Compra") -> 41.355545 | C45: =SUMIFS(Colección!$K$2:$K$10001,Colección!$G$2:$G$10001,$A45,Colección!$M$2:$M$10001,"Compra") -> 16 | D45: =IF($B45=0,"",_xlfn.RANK.EQ($B45,$B$2:$B$321,0)+COUNTIF($B$2:B45,$B45)-1) -> 157 | F45: ="Amazon (OP05-099)" -> Amazon (OP05-099) | G45: =SUMIFS(Colección!$L$2:$L$10001,Colección!$F$2:$F$10001,$F45,Colección!$M$2:$M$10001,"Compra") -> 0.081185113 | H45: =IF($G45=0,"",_xlfn.RANK.EQ($G45,$G$2:$G$2353,0)+COUNTIF($G$2:G45,$G45)-1) -> 2222
A46: ="Commander: Dominaria United" -> Commander: Dominaria United | B46: =SUMIFS(Colección!$L$2:$L$10001,Colección!$G$2:$G$10001,$A46,Colección!$M$2:$M$10001,"Compra") -> 16.163222 | C46: =SUMIFS(Colección!$K$2:$K$10001,Colección!$G$2:$G$10001,$A46,Colección!$M$2:$M$10001,"Compra") -> 13 | D46: =IF($B46=0,"",_xlfn.RANK.EQ($B46,$B$2:$B$321,0)+COUNTIF($B$2:B46,$B46)-1) -> 217 | F46: ="Ambrosia Whiteheart" -> Ambrosia Whiteheart | G46: =SUMIFS(Colección!$L$2:$L$10001,Colección!$F$2:$F$10001,$F46,Colección!$M$2:$M$10001,"Compra") -> 1.0307692 | H46: =IF($G46=0,"",_xlfn.RANK.EQ($G46,$G$2:$G$2353,0)+COUNTIF($G$2:G46,$G46)-1) -> 1647
A47: ="Commander: Duskmourn: House of Horror: Extras" -> Commander: Duskmourn: House of Horror: Extras | B47: =SUMIFS(Colección!$L$2:$L$10001,Colección!$G$2:$G$10001,$A47,Colección!$M$2:$M$10001,"Compra") -> 41.880325 | C47: =SUMIFS(Colección!$K$2:$K$10001,Colección!$G$2:$G$10001,$A47,Colección!$M$2:$M$10001,"Compra") -> 4 | D47: =IF($B47=0,"",_xlfn.RANK.EQ($B47,$B$2:$B$321,0)+COUNTIF($B$2:B47,$B47)-1) -> 154 | F47: ="Amped Raptor" -> Amped Raptor | G47: =SUMIFS(Colección!$L$2:$L$10001,Colección!$F$2:$F$10001,$F47,Colección!$M$2:$M$10001,"Compra") -> 7.854 | H47: =IF($G47=0,"",_xlfn.RANK.EQ($G47,$G$2:$G$2353,0)+COUNTIF($G$2:G47,$G47)-1) -> 758
A48: ="Commander: Ikoria" -> Commander: Ikoria | B48: =SUMIFS(Colección!$L$2:$L$10001,Colección!$G$2:$G$10001,$A48,Colección!$M$2:$M$10001,"Compra") -> 3.8668723 | C48: =SUMIFS(Colección!$K$2:$K$10001,Colección!$G$2:$G$10001,$A48,Colección!$M$2:$M$10001,"Compra") -> 7 | D48: =IF($B48=0,"",_xlfn.RANK.EQ($B48,$B$2:$B$321,0)+COUNTIF($B$2:B48,$B48)-1) -> 272 | F48: ="Amulet of Vigor" -> Amulet of Vigor | G48: =SUMIFS(Colección!$L$2:$L$10001,Colección!$F$2:$F$10001,$F48,Colección!$M$2:$M$10001,"Compra") -> 152.69 | H48: =IF($G48=0,"",_xlfn.RANK.EQ($G48,$G$2:$G$2353,0)+COUNTIF($G$2:G48,$G48)-1) -> 33
A49: ="Commander: Innistrad: Crimson Vow" -> Commander: Innistrad: Crimson Vow | B49: =SUMIFS(Colección!$L$2:$L$10001,Colección!$G$2:$G$10001,$A49,Colección!$M$2:$M$10001,"Compra") -> 0.21197183 | C49: =SUMIFS(Colección!$K$2:$K$10001,Colección!$G$2:$G$10001,$A49,Colección!$M$2:$M$10001,"Compra") -> 1 | D49: =IF($B49=0,"",_xlfn.RANK.EQ($B49,$B$2:$B$321,0)+COUNTIF($B$2:B49,$B49)-1) -> 314 | F49: ="Analyze the Pollen" -> Analyze the Pollen | G49: =SUMIFS(Colección!$L$2:$L$10001,Colección!$F$2:$F$10001,$F49,Colección!$M$2:$M$10001,"Compra") -> 2.4974227 | H49: =IF($G49=0,"",_xlfn.RANK.EQ($G49,$G$2:$G$2353,0)+COUNTIF($G$2:G49,$G49)-1) -> 1259
A50: ="Commander: Kaldheim" -> Commander: Kaldheim | B50: =SUMIFS(Colección!$L$2:$L$10001,Colección!$G$2:$G$10001,$A50,Colección!$M$2:$M$10001,"Compra") -> 4.1546165 | C50: =SUMIFS(Colección!$K$2:$K$10001,Colección!$G$2:$G$10001,$A50,Colección!$M$2:$M$10001,"Compra") -> 2 | D50: =IF($B50=0,"",_xlfn.RANK.EQ($B50,$B$2:$B$321,0)+COUNTIF($B$2:B50,$B50)-1) -> 270 | F50: ="Ancestral Anger" -> Ancestral Anger | G50: =SUMIFS(Colección!$L$2:$L$10001,Colección!$F$2:$F$10001,$F50,Colección!$M$2:$M$10001,"Compra") -> 0.64325134 | H50: =IF($G50=0,"",_xlfn.RANK.EQ($G50,$G$2:$G$2353,0)+COUNTIF($G$2:G50,$G50)-1) -> 1794
A51: ="Commander: Kamigawa: Neon Dynasty" -> Commander: Kamigawa: Neon Dynasty | B51: =SUMIFS(Colección!$L$2:$L$10001,Colección!$G$2:$G$10001,$A51,Colección!$M$2:$M$10001,"Compra") -> 1.0661064 | C51: =SUMIFS(Colección!$K$2:$K$10001,Colección!$G$2:$G$10001,$A51,Colección!$M$2:$M$10001,"Compra") -> 1 | D51: =IF($B51=0,"",_xlfn.RANK.EQ($B51,$B$2:$B$321,0)+COUNTIF($B$2:B51,$B51)-1) -> 300 | F51: ="Ancient Cornucopia (V.1)" -> Ancient Cornucopia (V.1) | G51: =SUMIFS(Colección!$L$2:$L$10001,Colección!$F$2:$F$10001,$F51,Colección!$M$2:$M$10001,"Compra") -> 5.2087339 | H51: =IF($G51=0,"",_xlfn.RANK.EQ($G51,$G$2:$G$2353,0)+COUNTIF($G$2:G51,$G51)-1) -> 957
A52: ="Commander: Modern Horizons 3" -> Commander: Modern Horizons 3 | B52: =SUMIFS(Colección!$L$2:$L$10001,Colección!$G$2:$G$10001,$A52,Colección!$M$2:$M$10001,"Compra") -> 25.24 | C52: =SUMIFS(Colección!$K$2:$K$10001,Colección!$G$2:$G$10001,$A52,Colección!$M$2:$M$10001,"Compra") -> 5 | D52: =IF($B52=0,"",_xlfn.RANK.EQ($B52,$B$2:$B$321,0)+COUNTIF($B$2:B52,$B52)-1) -> 193 | F52: ="Ancient Den" -> Ancient Den | G52: =SUMIFS(Colección!$L$2:$L$10001,Colección!$F$2:$F$10001,$F52,Colección!$M$2:$M$10001,"Compra") -> 8.2909091 | H52: =IF($G52=0,"",_xlfn.RANK.EQ($G52,$G$2:$G$2353,0)+COUNTIF($G$2:G52,$G52)-1) -> 735
A53: ="Commander: Modern Horizons 3: Extras" -> Commander: Modern Horizons 3: Extras | B53: =SUMIFS(Colección!$L$2:$L$10001,Colección!$G$2:$G$10001,$A53,Colección!$M$2:$M$10001,"Compra") -> 77.22 | C53: =SUMIFS(Colección!$K$2:$K$10001,Colección!$G$2:$G$10001,$A53,Colección!$M$2:$M$10001,"Compra") -> 7 | D53: =IF($B53=0,"",_xlfn.RANK.EQ($B53,$B$2:$B$321,0)+COUNTIF($B$2:B53,$B53)-1) -> 108 | F53: ="Ancient Grudge" -> Ancient Grudge | G53: =SUMIFS(Colección!$L$2:$L$10001,Colección!$F$2:$F$10001,$F53,Colección!$M$2:$M$10001,"Compra") -> 0.66455266 | H53: =IF($G53=0,"",_xlfn.RANK.EQ($G53,$G$2:$G$2353,0)+COUNTIF($G$2:G53,$G53)-1) -> 1778
A54: ="Commander: Outlaws of Thunder Junction" -> Commander: Outlaws of Thunder Junction | B54: =SUMIFS(Colección!$L$2:$L$10001,Colección!$G$2:$G$10001,$A54,Colección!$M$2:$M$10001,"Compra") -> 1.0014654 | C54: =SUMIFS(Colección!$K$2:$K$10001,Colección!$G$2:$G$10001,$A54,Colección!$M$2:$M$10001,"Compra") -> 1 | D54: =IF($B54=0,"",_xlfn.RANK.EQ($B54,$B$2:$B$321,0)+COUNTIF($B$2:B54,$B54)-1) -> 301 | F54: ="Ancient Stirrings" -> Ancient Stirrings | G54: =SUMIFS(Colección!$L$2:$L$10001,Colección!$F$2:$F$10001,$F54,Colección!$M$2:$M$10001,"Compra") -> 11.733995 | H54: =IF($G54=0,"",_xlfn.RANK.EQ($G54,$G$2:$G$2353,0)+COUNTIF($G$2:G54,$G54)-1) -> 592
A55: ="Commander: Streets of New Capenna" -> Commander: Streets of New Capenna | B55: =SUMIFS(Colección!$L$2:$L$10001,Colección!$G$2:$G$10001,$A55,Colección!$M$2:$M$10001,"Compra") -> 1.2069321 | C55: =SUMIFS(Colección!$K$2:$K$10001,Colección!$G$2:$G$10001,$A55,Colección!$M$2:$M$10001,"Compra") -> 5 | D55: =IF($B55=0,"",_xlfn.RANK.EQ($B55,$B$2:$B$321,0)+COUNTIF($B$2:B55,$B55)-1) -> 298 | F55: ="Andúril, Flame of the West" -> Andúril, Flame of the West | G55: =SUMIFS(Colección!$L$2:$L$10001,Colección!$F$2:$F$10001,$F55,Colección!$M$2:$M$10001,"Compra") -> 7.3300599 | H55: =IF($G55=0,"",_xlfn.RANK.EQ($G55,$G$2:$G$2353,0)+COUNTIF($G$2:G55,$G55)-1) -> 789
A56: ="Commander: Strixhaven" -> Commander: Strixhaven | B56: =SUMIFS(Colección!$L$2:$L$10001,Colección!$G$2:$G$10001,$A56,Colección!$M$2:$M$10001,"Compra") -> 0.57131801 | C56: =SUMIFS(Colección!$K$2:$K$10001,Colección!$G$2:$G$10001,$A56,Colección!$M$2:$M$10001,"Compra") -> 5 | D56: =IF($B56=0,"",_xlfn.RANK.EQ($B56,$B$2:$B$321,0)+COUNTIF($B$2:B56,$B56)-1) -> 304 | F56: ="Angel of the Ruins" -> Angel of the Ruins | G56: =SUMIFS(Colección!$L$2:$L$10001,Colección!$F$2:$F$10001,$F56,Colección!$M$2:$M$10001,"Compra") -> 0.32826087 | H56: =IF($G56=0,"",_xlfn.RANK.EQ($G56,$G$2:$G$2353,0)+COUNTIF($G$2:G56,$G56)-1) -> 1990
A57: ="Commander: The Brothers' War" -> Commander: The Brothers' War | B57: =SUMIFS(Colección!$L$2:$L$10001,Colección!$G$2:$G$10001,$A57,Colección!$M$2:$M$10001,"Compra") -> 196.0104 | C57: =SUMIFS(Colección!$K$2:$K$10001,Colección!$G$2:$G$10001,$A57,Colección!$M$2:$M$10001,"Compra") -> 68 | D57: =IF($B57=0,"",_xlfn.RANK.EQ($B57,$B$2:$B$321,0)+COUNTIF($B$2:B57,$B57)-1) -> 49 | F57: ="Angel Token (White 4/4)" -> Angel Token (White 4/4) | G57: =SUMIFS(Colección!$L$2:$L$10001,Colección!$F$2:$F$10001,$F57,Colección!$M$2:$M$10001,"Compra") -> 0.48785175 | H57: =IF($G57=0,"",_xlfn.RANK.EQ($G57,$G$2:$G$2353,0)+COUNTIF($G$2:G57,$G57)-1) -> 1887
A58: ="Commander: The Lord of the Rings:" -> Commander: The Lord of the Rings: | B58: =SUMIFS(Colección!$L$2:$L$10001,Colección!$G$2:$G$10001,$A58,Colección!$M$2:$M$10001,"Compra") -> 0.27529412 | C58: =SUMIFS(Colección!$K$2:$K$10001,Colección!$G$2:$G$10001,$A58,Colección!$M$2:$M$10001,"Compra") -> 1 | D58: =IF($B58=0,"",_xlfn.RANK.EQ($B58,$B$2:$B$321,0)+COUNTIF($B$2:B58,$B58)-1) -> 312 | F58: ="Anger of the Gods" -> Anger of the Gods | G58: =SUMIFS(Colección!$L$2:$L$10001,Colección!$F$2:$F$10001,$F58,Colección!$M$2:$M$10001,"Compra") -> 2.33 | H58: =IF($G58=0,"",_xlfn.RANK.EQ($G58,$G$2:$G$2353,0)+COUNTIF($G$2:G58,$G58)-1) -> 1281
A59: ="Commander: The Lord of the Rings: Tales of Middle-" -> Commander: The Lord of the Rings: Tales of Middle- | B59: =SUMIFS(Colección!$L$2:$L$10001,Colección!$G$2:$G$10001,$A59,Colección!$M$2:$M$10001,"Compra") -> 6.7832192 | C59: =SUMIFS(Colección!$K$2:$K$10001,Colección!$G$2:$G$10001,$A59,Colección!$M$2:$M$10001,"Compra") -> 4 | D59: =IF($B59=0,"",_xlfn.RANK.EQ($B59,$B$2:$B$321,0)+COUNTIF($B$2:B59,$B59)-1) -> 251 | F59: ="Angler Beast" -> Angler Beast | G59: =SUMIFS(Colección!$L$2:$L$10001,Colección!$F$2:$F$10001,$F59,Colección!$M$2:$M$10001,"Compra") -> 2.125914 | H59: =IF($G59=0,"",_xlfn.RANK.EQ($G59,$G$2:$G$2353,0)+COUNTIF($G$2:G59,$G59)-1) -> 1337
A60: ="Commander: The Lost Caverns of Ixalan" -> Commander: The Lost Caverns of Ixalan | B60: =SUMIFS(Colección!$L$2:$L$10001,Colección!$G$2:$G$10001,$A60,Colección!$M$2:$M$10001,"Compra") -> 27.302185 | C60: =SUMIFS(Colección!$K$2:$K$10001,Colección!$G$2:$G$10001,$A60,Colección!$M$2:$M$10001,"Compra") -> 15 | D60: =IF($B60=0,"",_xlfn.RANK.EQ($B60,$B$2:$B$321,0)+COUNTIF($B$2:B60,$B60)-1) -> 183 | F60: ="Angrath, Captain of Chaos" -> Angrath, Captain of Chaos | G60: =SUMIFS(Colección!$L$2:$L$10001,Colección!$F$2:$F$10001,$F60,Colección!$M$2:$M$10001,"Compra") -> 0.16363636 | H60: =IF($G60=0,"",_xlfn.RANK.EQ($G60,$G$2:$G$2353,0)+COUNTIF($G$2:G60,$G60)-1) -> 2101
A61: ="Commander: The Lost Caverns of Ixalan: Ex" -> Commander: The Lost Caverns of Ixalan: Ex | B61: =SUMIFS(Colección!$L$2:$L$10001,Colección!$G$2:$G$10001,$A61,Colección!$M$2:$M$10001,"Compra") -> 51.109135 | C61: =SUMIFS(Colección!$K$2:$K$10001,Colección!$G$2:$G$10001,$A61,Colección!$M$2:$M$10001,"Compra") -> 4 | D61: =IF($B61=0,"",_xlfn.RANK.EQ($B61,$B$2:$B$321,0)+COUNTIF($B$2:B61,$B61)-1) -> 142 | F61: ="Annul" -> Annul | G61: =SUMIFS(Colección!$L$2:$L$10001,Colección!$F$2:$F$10001,$F61,Colección!$M$2:$M$10001,"Compra") -> 11.831736 | H61: =IF($G61=0,"",_xlfn.RANK.EQ($G61,$G$2:$G$2353,0)+COUNTIF($G$2:G61,$G61)-1) -> 589
A62: ="Conflux" -> Conflux | B62: =SUMIFS(Colección!$L$2:$L$10001,Colección!$G$2:$G$10001,$A62,Colección!$M$2:$M$10001,"Compra") -> 46.062905 | C62: =SUMIFS(Colección!$K$2:$K$10001,Colección!$G$2:$G$10001,$A62,Colección!$M$2:$M$10001,"Compra") -> 5 | D62: =IF($B62=0,"",_xlfn.RANK.EQ($B62,$B$2:$B$321,0)+COUNTIF($B$2:B62,$B62)-1) -> 148 | F62: ="Anointed Peacekeeper" -> Anointed Peacekeeper | G62: =SUMIFS(Colección!$L$2:$L$10001,Colección!$F$2:$F$10001,$F62,Colección!$M$2:$M$10001,"Compra") -> 4.2325853 | H62: =IF($G62=0,"",_xlfn.RANK.EQ($G62,$G$2:$G$2353,0)+COUNTIF($G$2:G62,$G62)-1) -> 1041
A63: ="Core 2019" -> Core 2019 | B63: =SUMIFS(Colección!$L$2:$L$10001,Colección!$G$2:$G$10001,$A63,Colección!$M$2:$M$10001,"Compra") -> 24.085439 | C63: =SUMIFS(Colección!$K$2:$K$10001,Colección!$G$2:$G$10001,$A63,Colección!$M$2:$M$10001,"Compra") -> 10 | D63: =IF($B63=0,"",_xlfn.RANK.EQ($B63,$B$2:$B$321,0)+COUNTIF($B$2:B63,$B63)-1) -> 194 | F63: ="Apis (OP04-041)" -> Apis (OP04-041) | G63: =SUMIFS(Colección!$L$2:$L$10001,Colección!$F$2:$F$10001,$F63,Colección!$M$2:$M$10001,"Compra") -> 0.061898734 | H63: =IF($G63=0,"",_xlfn.RANK.EQ($G63,$G$2:$G$2353,0)+COUNTIF($G$2:G63,$G63)-1) -> 2256
A64: ="Core 2020" -> Core 2020 | B64: =SUMIFS(Colección!$L$2:$L$10001,Colección!$G$2:$G$10001,$A64,Colección!$M$2:$M$10001,"Compra") -> 26.50394 | C64: =SUMIFS(Colección!$K$2:$K$10001,Colección!$G$2:$G$10001,$A64,Colección!$M$2:$M$10001,"Compra") -> 18 | D64: =IF($B64=0,"",_xlfn.RANK.EQ($B64,$B$2:$B$321,0)+COUNTIF($B$2:B64,$B64)-1) -> 189 | F64: ="Apostle's Blessing" -> Apostle's Blessing | G64: =SUMIFS(Colección!$L$2:$L$10001,Colección!$F$2:$F$10001,$F64,Colección!$M$2:$M$10001,"Compra") -> 1.6081283 | H64: =IF($G64=0,"",_xlfn.RANK.EQ($G64,$G$2:$G$2353,0)+COUNTIF($G$2:G64,$G64)-1) -> 1460
A65: ="Core 2020: Extras" -> Core 2020: Extras | B65: =SUMIFS(Colección!$L$2:$L$10001,Colección!$G$2:$G$10001,$A65,Colección!$M$2:$M$10001,"Compra") -> 5.5884653 | C65: =SUMIFS(Colección!$K$2:$K$10001,Colección!$G$2:$G$10001,$A65,Colección!$M$2:$M$10001,"Compra") -> 4 | D65: =IF($B65=0,"",_xlfn.RANK.EQ($B65,$B$2:$B$321,0)+COUNTIF($B$2:B65,$B65)-1) -> 261 | F65: ="Apostle's Blessing [Playset]" -> Apostle's Blessing [Playset] | G65: =SUMIFS(Colección!$L$2:$L$10001,Colección!$F$2:$F$10001,$F65,Colección!$M$2:$M$10001,"Compra") -> 1.3923077 | H65: =IF($G65=0,"",_xlfn.RANK.EQ($G65,$G$2:$G$2353,0)+COUNTIF($G$2:G65,$G65)-1) -> 1512
A66: ="Core 2021" -> Core 2021 | B66: =SUMIFS(Colección!$L$2:$L$10001,Colección!$G$2:$G$10001,$A66,Colección!$M$2:$M$10001,"Compra") -> 10.302653 | C66: =SUMIFS(Colección!$K$2:$K$10001,Colección!$G$2:$G$10001,$A66,Colección!$M$2:$M$10001,"Compra") -> 30 | D66: =IF($B66=0,"",_xlfn.RANK.EQ($B66,$B$2:$B$321,0)+COUNTIF($B$2:B66,$B66)-1) -> 238 | F66: ="Aquamoeba" -> Aquamoeba | G66: =SUMIFS(Colección!$L$2:$L$10001,Colección!$F$2:$F$10001,$F66,Colección!$M$2:$M$10001,"Compra") -> 7.6341368 | H66: =IF($G66=0,"",_xlfn.RANK.EQ($G66,$G$2:$G$2353,0)+COUNTIF($G$2:G66,$G66)-1) -> 767
A67: ="Core 2021: Extras" -> Core 2021: Extras | B67: =SUMIFS(Colección!$L$2:$L$10001,Colección!$G$2:$G$10001,$A67,Colección!$M$2:$M$10001,"Compra") -> 41.487733 | C67: =SUMIFS(Colección!$K$2:$K$10001,Colección!$G$2:$G$10001,$A67,Colección!$M$2:$M$10001,"Compra") -> 1 | D67: =IF($B67=0,"",_xlfn.RANK.EQ($B67,$B$2:$B$321,0)+COUNTIF($B$2:B67,$B67)-1) -> 155 | F67: ="Arabella, Abandoned Doll" -> Arabella, Abandoned Doll | G67: =SUMIFS(Colección!$L$2:$L$10001,Colección!$F$2:$F$10001,$F67,Colección!$M$2:$M$10001,"Compra") -> 1.35 | H67: =IF($G67=0,"",_xlfn.RANK.EQ($G67,$G$2:$G$2353,0)+COUNTIF($G$2:G67,$G67)-1) -> 1519
A68: ="Core 2021: Promos" -> Core 2021: Promos | B68: =SUMIFS(Colección!$L$2:$L$10001,Colección!$G$2:$G$10001,$A68,Colección!$M$2:$M$10001,"Compra") -> 0.56666667 | C68: =SUMIFS(Colección!$K$2:$K$10001,Colección!$G$2:$G$10001,$A68,Colección!$M$2:$M$10001,"Compra") -> 1 | D68: =IF($B68=0,"",_xlfn.RANK.EQ($B68,$B$2:$B$321,0)+COUNTIF($B$2:B68,$B68)-1) -> 305 | F68: ="Aragorn, Company Leader" -> Aragorn, Company Leader | G68: =SUMIFS(Colección!$L$2:$L$10001,Colección!$F$2:$F$10001,$F68,Colección!$M$2:$M$10001,"Compra") -> 0.20136612 | H68: =IF($G68=0,"",_xlfn.RANK.EQ($G68,$G$2:$G$2353,0)+COUNTIF($G$2:G68,$G68)-1) -> 2092
A69: ="Dark Ascension" -> Dark Ascension | B69: =SUMIFS(Colección!$L$2:$L$10001,Colección!$G$2:$G$10001,$A69,Colección!$M$2:$M$10001,"Compra") -> 52.816226 | C69: =SUMIFS(Colección!$K$2:$K$10001,Colección!$G$2:$G$10001,$A69,Colección!$M$2:$M$10001,"Compra") -> 23 | D69: =IF($B69=0,"",_xlfn.RANK.EQ($B69,$B$2:$B$321,0)+COUNTIF($B$2:B69,$B69)-1) -> 138 | F69: ="Aragorn, Company Leader (V.1)" -> Aragorn, Company Leader (V.1) | G69: =SUMIFS(Colección!$L$2:$L$10001,Colección!$F$2:$F$10001,$F69,Colección!$M$2:$M$10001,"Compra") -> 0.51079812 | H69: =IF($G69=0,"",_xlfn.RANK.EQ($G69,$G$2:$G$2353,0)+COUNTIF($G$2:G69,$G69)-1) -> 1878
A70: ="Darksteel" -> Darksteel | B70: =SUMIFS(Colección!$L$2:$L$10001,Colección!$G$2:$G$10001,$A70,Colección!$M$2:$M$10001,"Compra") -> 98.886259 | C70: =SUMIFS(Colección!$K$2:$K$10001,Colección!$G$2:$G$10001,$A70,Colección!$M$2:$M$10001,"Compra") -> 14 | D70: =IF($B70=0,"",_xlfn.RANK.EQ($B70,$B$2:$B$321,0)+COUNTIF($B$2:B70,$B70)-1) -> 83 | F70: ="Aragorn, Company Leader (V.2)" -> Aragorn, Company Leader (V.2) | G70: =SUMIFS(Colección!$L$2:$L$10001,Colección!$F$2:$F$10001,$F70,Colección!$M$2:$M$10001,"Compra") -> 0.53697632 | H70: =IF($G70=0,"",_xlfn.RANK.EQ($G70,$G$2:$G$2353,0)+COUNTIF($G$2:G70,$G70)-1) -> 1863
A71: ="DCI Promos" -> DCI Promos | B71: =SUMIFS(Colección!$L$2:$L$10001,Colección!$G$2:$G$10001,$A71,Colección!$M$2:$M$10001,"Compra") -> 67.988611 | C71: =SUMIFS(Colección!$K$2:$K$10001,Colección!$G$2:$G$10001,$A71,Colección!$M$2:$M$10001,"Compra") -> 23 | D71: =IF($B71=0,"",_xlfn.RANK.EQ($B71,$B$2:$B$321,0)+COUNTIF($B$2:B71,$B71)-1) -> 118 | F71: ="Aragorn, the Uniter" -> Aragorn, the Uniter | G71: =SUMIFS(Colección!$L$2:$L$10001,Colección!$F$2:$F$10001,$F71,Colección!$M$2:$M$10001,"Compra") -> 5.821875 | H71: =IF($G71=0,"",_xlfn.RANK.EQ($G71,$G$2:$G$2353,0)+COUNTIF($G$2:G71,$G71)-1) -> 900
A72: ="Dissension" -> Dissension | B72: =SUMIFS(Colección!$L$2:$L$10001,Colección!$G$2:$G$10001,$A72,Colección!$M$2:$M$10001,"Compra") -> 36.533704 | C72: =SUMIFS(Colección!$K$2:$K$10001,Colección!$G$2:$G$10001,$A72,Colección!$M$2:$M$10001,"Compra") -> 7 | D72: =IF($B72=0,"",_xlfn.RANK.EQ($B72,$B$2:$B$321,0)+COUNTIF($B$2:B72,$B72)-1) -> 164 | F72: ="Aragorn, the Uniter (V.1)" -> Aragorn, the Uniter (V.1) | G72: =SUMIFS(Colección!$L$2:$L$10001,Colección!$F$2:$F$10001,$F72,Colección!$M$2:$M$10001,"Compra") -> 7.9817949 | H72: =IF($G72=0,"",_xlfn.RANK.EQ($G72,$G$2:$G$2353,0)+COUNTIF($G$2:G72,$G72)-1) -> 752
A73: ="Dominaria" -> Dominaria | B73: =SUMIFS(Colección!$L$2:$L$10001,Colección!$G$2:$G$10001,$A73,Colección!$M$2:$M$10001,"Compra") -> 141.55724 | C73: =SUMIFS(Colección!$K$2:$K$10001,Colección!$G$2:$G$10001,$A73,Colección!$M$2:$M$10001,"Compra") -> 25 | D73: =IF($B73=0,"",_xlfn.RANK.EQ($B73,$B$2:$B$321,0)+COUNTIF($B$2:B73,$B73)-1) -> 69 | F73: ="Aragorn, the Uniter (V.2)" -> Aragorn, the Uniter (V.2) | G73: =SUMIFS(Colección!$L$2:$L$10001,Colección!$F$2:$F$10001,$F73,Colección!$M$2:$M$10001,"Compra") -> 17.3131 | H73: =IF($G73=0,"",_xlfn.RANK.EQ($G73,$G$2:$G$2353,0)+COUNTIF($G$2:G73,$G73)-1) -> 446
A74: ="Dominaria Remastered" -> Dominaria Remastered | B74: =SUMIFS(Colección!$L$2:$L$10001,Colección!$G$2:$G$10001,$A74,Colección!$M$2:$M$10001,"Compra") -> 13.161084 | C74: =SUMIFS(Colección!$K$2:$K$10001,Colección!$G$2:$G$10001,$A74,Colección!$M$2:$M$10001,"Compra") -> 30 | D74: =IF($B74=0,"",_xlfn.RANK.EQ($B74,$B$2:$B$321,0)+COUNTIF($B$2:B74,$B74)-1) -> 227 | F74: ="Arboreal Grazer" -> Arboreal Grazer | G74: =SUMIFS(Colección!$L$2:$L$10001,Colección!$F$2:$F$10001,$F74,Colección!$M$2:$M$10001,"Compra") -> 4.1662454 | H74: =IF($G74=0,"",_xlfn.RANK.EQ($G74,$G$2:$G$2353,0)+COUNTIF($G$2:G74,$G74)-1) -> 1051
A75: ="Dominaria Remastered: Extras" -> Dominaria Remastered: Extras | B75: =SUMIFS(Colección!$L$2:$L$10001,Colección!$G$2:$G$10001,$A75,Colección!$M$2:$M$10001,"Compra") -> 59.577544 | C75: =SUMIFS(Colección!$K$2:$K$10001,Colección!$G$2:$G$10001,$A75,Colección!$M$2:$M$10001,"Compra") -> 23 | D75: =IF($B75=0,"",_xlfn.RANK.EQ($B75,$B$2:$B$321,0)+COUNTIF($B$2:B75,$B75)-1) -> 130 | F75: ="Arcane Box Set" -> Arcane Box Set | G75: =SUMIFS(Colección!$L$2:$L$10001,Colección!$F$2:$F$10001,$F75,Colección!$M$2:$M$10001,"Compra") -> 237.57917 | H75: =IF($G75=0,"",_xlfn.RANK.EQ($G75,$G$2:$G$2353,0)+COUNTIF($G$2:G75,$G75)-1) -> 14
A76: ="Dominaria United" -> Dominaria United | B76: =SUMIFS(Colección!$L$2:$L$10001,Colección!$G$2:$G$10001,$A76,Colección!$M$2:$M$10001,"Compra") -> 274.51143 | C76: =SUMIFS(Colección!$K$2:$K$10001,Colección!$G$2:$G$10001,$A76,Colección!$M$2:$M$10001,"Compra") -> 104 | D76: =IF($B76=0,"",_xlfn.RANK.EQ($B76,$B$2:$B$321,0)+COUNTIF($B$2:B76,$B76)-1) -> 31 | F76: ="Arcbound Ravager" -> Arcbound Ravager | G76: =SUMIFS(Colección!$L$2:$L$10001,Colección!$F$2:$F$10001,$F76,Colección!$M$2:$M$10001,"Compra") -> 41.18 | H76: =IF($G76=0,"",_xlfn.RANK.EQ($G76,$G$2:$G$2353,0)+COUNTIF($G$2:G76,$G76)-1) -> 208
A77: ="Dominaria United: Extras" -> Dominaria United: Extras | B77: =SUMIFS(Colección!$L$2:$L$10001,Colección!$G$2:$G$10001,$A77,Colección!$M$2:$M$10001,"Compra") -> 76.442791 | C77: =SUMIFS(Colección!$K$2:$K$10001,Colección!$G$2:$G$10001,$A77,Colección!$M$2:$M$10001,"Compra") -> 39 | D77: =IF($B77=0,"",_xlfn.RANK.EQ($B77,$B$2:$B$321,0)+COUNTIF($B$2:B77,$B77)-1) -> 109 | F77: ="Archaeomancer" -> Archaeomancer | G77: =SUMIFS(Colección!$L$2:$L$10001,Colección!$F$2:$F$10001,$F77,Colección!$M$2:$M$10001,"Compra") -> 2.53 | H77: =IF($G77=0,"",_xlfn.RANK.EQ($G77,$G$2:$G$2353,0)+COUNTIF($G$2:G77,$G77)-1) -> 1249
A78: ="Dominaria United: Promos" -> Dominaria United: Promos | B78: =SUMIFS(Colección!$L$2:$L$10001,Colección!$G$2:$G$10001,$A78,Colección!$M$2:$M$10001,"Compra") -> 35.18 | C78: =SUMIFS(Colección!$K$2:$K$10001,Colección!$G$2:$G$10001,$A78,Colección!$M$2:$M$10001,"Compra") -> 2 | D78: =IF($B78=0,"",_xlfn.RANK.EQ($B78,$B$2:$B$321,0)+COUNTIF($B$2:B78,$B78)-1) -> 166 | F78: ="Archangel of Wrath" -> Archangel of Wrath | G78: =SUMIFS(Colección!$L$2:$L$10001,Colección!$F$2:$F$10001,$F78,Colección!$M$2:$M$10001,"Compra") -> 2.9720383 | H78: =IF($G78=0,"",_xlfn.RANK.EQ($G78,$G$2:$G$2353,0)+COUNTIF($G$2:G78,$G78)-1) -> 1198
A79: ="Double Masters" -> Double Masters | B79: =SUMIFS(Colección!$L$2:$L$10001,Colección!$G$2:$G$10001,$A79,Colección!$M$2:$M$10001,"Compra") -> 108.45982 | C79: =SUMIFS(Colección!$K$2:$K$10001,Colección!$G$2:$G$10001,$A79,Colección!$M$2:$M$10001,"Compra") -> 60 | D79: =IF($B79=0,"",_xlfn.RANK.EQ($B79,$B$2:$B$321,0)+COUNTIF($B$2:B79,$B79)-1) -> 73 | F79: ="Archmage's Charm" -> Archmage's Charm | G79: =SUMIFS(Colección!$L$2:$L$10001,Colección!$F$2:$F$10001,$F79,Colección!$M$2:$M$10001,"Compra") -> 57.278571 | H79: =IF($G79=0,"",_xlfn.RANK.EQ($G79,$G$2:$G$2353,0)+COUNTIF($G$2:G79,$G79)-1) -> 150
A80: ="Double Masters 2022" -> Double Masters 2022 | B80: =SUMIFS(Colección!$L$2:$L$10001,Colección!$G$2:$G$10001,$A80,Colección!$M$2:$M$10001,"Compra") -> 50.172886 | C80: =SUMIFS(Colección!$K$2:$K$10001,Colección!$G$2:$G$10001,$A80,Colección!$M$2:$M$10001,"Compra") -> 81 | D80: =IF($B80=0,"",_xlfn.RANK.EQ($B80,$B$2:$B$321,0)+COUNTIF($B$2:B80,$B80)-1) -> 144 | F80: ="Archon of Cruelty [Playset]" -> Archon of Cruelty [Playset] | G80: =SUMIFS(Colección!$L$2:$L$10001,Colección!$F$2:$F$10001,$F80,Colección!$M$2:$M$10001,"Compra") -> 52.904939 | H80: =IF($G80=0,"",_xlfn.RANK.EQ($G80,$G$2:$G$2353,0)+COUNTIF($G$2:G80,$G80)-1) -> 166
A81: ="Double Masters 2022: Extras" -> Double Masters 2022: Extras | B81: =SUMIFS(Colección!$L$2:$L$10001,Colección!$G$2:$G$10001,$A81,Colección!$M$2:$M$10001,"Compra") -> 459.8881 | C81: =SUMIFS(Colección!$K$2:$K$10001,Colección!$G$2:$G$10001,$A81,Colección!$M$2:$M$10001,"Compra") -> 66 | D81: =IF($B81=0,"",_xlfn.RANK.EQ($B81,$B$2:$B$321,0)+COUNTIF($B$2:B81,$B81)-1) -> 17 | F81: ="Archon of Emeria [Playset]" -> Archon of Emeria [Playset] | G81: =SUMIFS(Colección!$L$2:$L$10001,Colección!$F$2:$F$10001,$F81,Colección!$M$2:$M$10001,"Compra") -> 12.615652 | H81: =IF($G81=0,"",_xlfn.RANK.EQ($G81,$G$2:$G$2353,0)+COUNTIF($G$2:G81,$G81)-1) -> 562
A82: ="Double Masters: Extras" -> Double Masters: Extras | B82: =SUMIFS(Colección!$L$2:$L$10001,Colección!$G$2:$G$10001,$A82,Colección!$M$2:$M$10001,"Compra") -> 35.359166 | C82: =SUMIFS(Colección!$K$2:$K$10001,Colección!$G$2:$G$10001,$A82,Colección!$M$2:$M$10001,"Compra") -> 11 | D82: =IF($B82=0,"",_xlfn.RANK.EQ($B82,$B$2:$B$321,0)+COUNTIF($B$2:B82,$B82)-1) -> 165 | F82: ="Arclight Phoenix (V.1)" -> Arclight Phoenix (V.1) | G82: =SUMIFS(Colección!$L$2:$L$10001,Colección!$F$2:$F$10001,$F82,Colección!$M$2:$M$10001,"Compra") -> 33.47 | H82: =IF($G82=0,"",_xlfn.RANK.EQ($G82,$G$2:$G$2353,0)+COUNTIF($G$2:G82,$G82)-1) -> 254
A83: ="Dragon's Maze" -> Dragon's Maze | B83: =SUMIFS(Colección!$L$2:$L$10001,Colección!$G$2:$G$10001,$A83,Colección!$M$2:$M$10001,"Compra") -> 12.030223 | C83: =SUMIFS(Colección!$K$2:$K$10001,Colección!$G$2:$G$10001,$A83,Colección!$M$2:$M$10001,"Compra") -> 7 | D83: =IF($B83=0,"",_xlfn.RANK.EQ($B83,$B$2:$B$321,0)+COUNTIF($B$2:B83,$B83)-1) -> 231 | F83: ="Ardent Plea" -> Ardent Plea | G83: =SUMIFS(Colección!$L$2:$L$10001,Colección!$F$2:$F$10001,$F83,Colección!$M$2:$M$10001,"Compra") -> 21.94 | H83: =IF($G83=0,"",_xlfn.RANK.EQ($G83,$G$2:$G$2353,0)+COUNTIF($G$2:G83,$G83)-1) -> 357
A84: ="Dragons of Tarkir" -> Dragons of Tarkir | B84: =SUMIFS(Colección!$L$2:$L$10001,Colección!$G$2:$G$10001,$A84,Colección!$M$2:$M$10001,"Compra") -> 12.947351 | C84: =SUMIFS(Colección!$K$2:$K$10001,Colección!$G$2:$G$10001,$A84,Colección!$M$2:$M$10001,"Compra") -> 5 | D84: =IF($B84=0,"",_xlfn.RANK.EQ($B84,$B$2:$B$321,0)+COUNTIF($B$2:B84,$B84)-1) -> 229 | F84: ="Arena of Glory" -> Arena of Glory | G84: =SUMIFS(Colección!$L$2:$L$10001,Colección!$F$2:$F$10001,$F84,Colección!$M$2:$M$10001,"Compra") -> 25.31191 | H84: =IF($G84=0,"",_xlfn.RANK.EQ($G84,$G$2:$G$2353,0)+COUNTIF($G$2:G84,$G84)-1) -> 307
A85: ="Duel Decks: Ajani vs. Nicol Bolas" -> Duel Decks: Ajani vs. Nicol Bolas | B85: =SUMIFS(Colección!$L$2:$L$10001,Colección!$G$2:$G$10001,$A85,Colección!$M$2:$M$10001,"Compra") -> 4.321679 | C85: =SUMIFS(Colección!$K$2:$K$10001,Colección!$G$2:$G$10001,$A85,Colección!$M$2:$M$10001,"Compra") -> 1 | D85: =IF($B85=0,"",_xlfn.RANK.EQ($B85,$B$2:$B$321,0)+COUNTIF($B$2:B85,$B85)-1) -> 269 | F85: ="Aria of Flame" -> Aria of Flame | G85: =SUMIFS(Colección!$L$2:$L$10001,Colección!$F$2:$F$10001,$F85,Colección!$M$2:$M$10001,"Compra") -> 2.2280396 | H85: =IF($G85=0,"",_xlfn.RANK.EQ($G85,$G$2:$G$2353,0)+COUNTIF($G$2:G85,$G85)-1) -> 1304
A86: ="Duel Decks: Anthology" -> Duel Decks: Anthology | B86: =SUMIFS(Colección!$L$2:$L$10001,Colección!$G$2:$G$10001,$A86,Colección!$M$2:$M$10001,"Compra") -> 1.645757 | C86: =SUMIFS(Colección!$K$2:$K$10001,Colección!$G$2:$G$10001,$A86,Colección!$M$2:$M$10001,"Compra") -> 1 | D86: =IF($B86=0,"",_xlfn.RANK.EQ($B86,$B$2:$B$321,0)+COUNTIF($B$2:B86,$B86)-1) -> 293 | F86: ="Arid Mesa" -> Arid Mesa | G86: =SUMIFS(Colección!$L$2:$L$10001,Colección!$F$2:$F$10001,$F86,Colección!$M$2:$M$10001,"Compra") -> 67.601526 | H86: =IF($G86=0,"",_xlfn.RANK.EQ($G86,$G$2:$G$2353,0)+COUNTIF($G$2:G86,$G86)-1) -> 120
A87: ="Duel Decks: Elves vs. Inventors" -> Duel Decks: Elves vs. Inventors | B87: =SUMIFS(Colección!$L$2:$L$10001,Colección!$G$2:$G$10001,$A87,Colección!$M$2:$M$10001,"Compra") -> 2.0985995 | C87: =SUMIFS(Colección!$K$2:$K$10001,Colección!$G$2:$G$10001,$A87,Colección!$M$2:$M$10001,"Compra") -> 6 | D87: =IF($B87=0,"",_xlfn.RANK.EQ($B87,$B$2:$B$321,0)+COUNTIF($B$2:B87,$B87)-1) -> 287 | F87: ="Arid Mesa (V.1)" -> Arid Mesa (V.1) | G87: =SUMIFS(Colección!$L$2:$L$10001,Colección!$F$2:$F$10001,$F87,Colección!$M$2:$M$10001,"Compra") -> 97.43 | H87: =IF($G87=0,"",_xlfn.RANK.EQ($G87,$G$2:$G$2353,0)+COUNTIF($G$2:G87,$G87)-1) -> 78
A88: ="Duel Decks: Merfolk vs. Goblins" -> Duel Decks: Merfolk vs. Goblins | B88: =SUMIFS(Colección!$L$2:$L$10001,Colección!$G$2:$G$10001,$A88,Colección!$M$2:$M$10001,"Compra") -> 4.4695513 | C88: =SUMIFS(Colección!$K$2:$K$10001,Colección!$G$2:$G$10001,$A88,Colección!$M$2:$M$10001,"Compra") -> 4 | D88: =IF($B88=0,"",_xlfn.RANK.EQ($B88,$B$2:$B$321,0)+COUNTIF($B$2:B88,$B88)-1) -> 267 | F88: ="Arise!" -> Arise! | G88: =SUMIFS(Colección!$L$2:$L$10001,Colección!$F$2:$F$10001,$F88,Colección!$M$2:$M$10001,"Compra") -> 74.153567 | H88: =IF($G88=0,"",_xlfn.RANK.EQ($G88,$G$2:$G$2353,0)+COUNTIF($G$2:G88,$G88)-1) -> 107
A89: ="Duel Decks: Nissa vs. Ob Nixilis" -> Duel Decks: Nissa vs. Ob Nixilis | B89: =SUMIFS(Colección!$L$2:$L$10001,Colección!$G$2:$G$10001,$A89,Colección!$M$2:$M$10001,"Compra") -> 0.20955224 | C89: =SUMIFS(Colección!$K$2:$K$10001,Colección!$G$2:$G$10001,$A89,Colección!$M$2:$M$10001,"Compra") -> 3 | D89: =IF($B89=0,"",_xlfn.RANK.EQ($B89,$B$2:$B$321,0)+COUNTIF($B$2:B89,$B89)-1) -> 315 | F89: ="Arlinn, Voice of the Pack" -> Arlinn, Voice of the Pack | G89: =SUMIFS(Colección!$L$2:$L$10001,Colección!$F$2:$F$10001,$F89,Colección!$M$2:$M$10001,"Compra") -> 0.16363636 | H89: =IF($G89=0,"",_xlfn.RANK.EQ($G89,$G$2:$G$2353,0)+COUNTIF($G$2:G89,$G89)-1) -> 2102
A90: ="Duskmourn: House of Horror" -> Duskmourn: House of Horror | B90: =SUMIFS(Colección!$L$2:$L$10001,Colección!$G$2:$G$10001,$A90,Colección!$M$2:$M$10001,"Compra") -> 297.93952 | C90: =SUMIFS(Colección!$K$2:$K$10001,Colección!$G$2:$G$10001,$A90,Colección!$M$2:$M$10001,"Compra") -> 118 | D90: =IF($B90=0,"",_xlfn.RANK.EQ($B90,$B$2:$B$321,0)+COUNTIF($B$2:B90,$B90)-1) -> 29 | F90: ="Arlong (OP03-022) (V.1)" -> Arlong (OP03-022) (V.1) | G90: =SUMIFS(Colección!$L$2:$L$10001,Colección!$F$2:$F$10001,$F90,Colección!$M$2:$M$10001,"Compra") -> 0.40457364 | H90: =IF($G90=0,"",_xlfn.RANK.EQ($G90,$G$2:$G$2353,0)+COUNTIF($G$2:G90,$G90)-1) -> 1947
A91: ="Duskmourn: House of Horror: Extras" -> Duskmourn: House of Horror: Extras | B91: =SUMIFS(Colección!$L$2:$L$10001,Colección!$G$2:$G$10001,$A91,Colección!$M$2:$M$10001,"Compra") -> 409.04853 | C91: =SUMIFS(Colección!$K$2:$K$10001,Colección!$G$2:$G$10001,$A91,Colección!$M$2:$M$10001,"Compra") -> 30 | D91: =IF($B91=0,"",_xlfn.RANK.EQ($B91,$B$2:$B$321,0)+COUNTIF($B$2:B91,$B91)-1) -> 20 | F91: ="Arms of Hadar" -> Arms of Hadar | G91: =SUMIFS(Colección!$L$2:$L$10001,Colección!$F$2:$F$10001,$F91,Colección!$M$2:$M$10001,"Compra") -> 1.0276063 | H91: =IF($G91=0,"",_xlfn.RANK.EQ($G91,$G$2:$G$2353,0)+COUNTIF($G$2:G91,$G91)-1) -> 1649
A92: ="Duskmourn: House of Horror: Tokens" -> Duskmourn: House of Horror: Tokens | B92: =SUMIFS(Colección!$L$2:$L$10001,Colección!$G$2:$G$10001,$A92,Colección!$M$2:$M$10001,"Compra") -> 14.186531 | C92: =SUMIFS(Colección!$K$2:$K$10001,Colección!$G$2:$G$10001,$A92,Colección!$M$2:$M$10001,"Compra") -> 10 | D92: =IF($B92=0,"",_xlfn.RANK.EQ($B92,$B$2:$B$321,0)+COUNTIF($B$2:B92,$B92)-1) -> 226 | F92: ="Arrogant Wurm" -> Arrogant Wurm | G92: =SUMIFS(Colección!$L$2:$L$10001,Colección!$F$2:$F$10001,$F92,Colección!$M$2:$M$10001,"Compra") -> 16.68422 | H92: =IF($G92=0,"",_xlfn.RANK.EQ($G92,$G$2:$G$2353,0)+COUNTIF($G$2:G92,$G92)-1) -> 462
A93: ="Edge of Eternities" -> Edge of Eternities | B93: =SUMIFS(Colección!$L$2:$L$10001,Colección!$G$2:$G$10001,$A93,Colección!$M$2:$M$10001,"Compra") -> 252.46326 | C93: =SUMIFS(Colección!$K$2:$K$10001,Colección!$G$2:$G$10001,$A93,Colección!$M$2:$M$10001,"Compra") -> 36 | D93: =IF($B93=0,"",_xlfn.RANK.EQ($B93,$B$2:$B$321,0)+COUNTIF($B$2:B93,$B93)-1) -> 35 | F93: ="Art Series: Plains (V.1)" -> Art Series: Plains (V.1) | G93: =SUMIFS(Colección!$L$2:$L$10001,Colección!$F$2:$F$10001,$F93,Colección!$M$2:$M$10001,"Compra") -> 0.12640449 | H93: =IF($G93=0,"",_xlfn.RANK.EQ($G93,$G$2:$G$2353,0)+COUNTIF($G$2:G93,$G93)-1) -> 2149
A94: ="Edge of Eternities: Extras" -> Edge of Eternities: Extras | B94: =SUMIFS(Colección!$L$2:$L$10001,Colección!$G$2:$G$10001,$A94,Colección!$M$2:$M$10001,"Compra") -> 105.13 | C94: =SUMIFS(Colección!$K$2:$K$10001,Colección!$G$2:$G$10001,$A94,Colección!$M$2:$M$10001,"Compra") -> 13 | D94: =IF($B94=0,"",_xlfn.RANK.EQ($B94,$B$2:$B$321,0)+COUNTIF($B$2:B94,$B94)-1) -> 76 | F94: ="Artist's Talent" -> Artist's Talent | G94: =SUMIFS(Colección!$L$2:$L$10001,Colección!$F$2:$F$10001,$F94,Colección!$M$2:$M$10001,"Compra") -> 31.73 | H94: =IF($G94=0,"",_xlfn.RANK.EQ($G94,$G$2:$G$2353,0)+COUNTIF($G$2:G94,$G94)-1) -> 268
A95: ="Eldritch Moon" -> Eldritch Moon | B95: =SUMIFS(Colección!$L$2:$L$10001,Colección!$G$2:$G$10001,$A95,Colección!$M$2:$M$10001,"Compra") -> 79.047326 | C95: =SUMIFS(Colección!$K$2:$K$10001,Colección!$G$2:$G$10001,$A95,Colección!$M$2:$M$10001,"Compra") -> 3 | D95: =IF($B95=0,"",_xlfn.RANK.EQ($B95,$B$2:$B$321,0)+COUNTIF($B$2:B95,$B95)-1) -> 104 | F95: ="Arwen, Mortal Queen" -> Arwen, Mortal Queen | G95: =SUMIFS(Colección!$L$2:$L$10001,Colección!$F$2:$F$10001,$F95,Colección!$M$2:$M$10001,"Compra") -> 3.2774867 | H95: =IF($G95=0,"",_xlfn.RANK.EQ($G95,$G$2:$G$2353,0)+COUNTIF($G$2:G95,$G95)-1) -> 1154
A96: ="Enchanting Tales" -> Enchanting Tales | B96: =SUMIFS(Colección!$L$2:$L$10001,Colección!$G$2:$G$10001,$A96,Colección!$M$2:$M$10001,"Compra") -> 11.348818 | C96: =SUMIFS(Colección!$K$2:$K$10001,Colección!$G$2:$G$10001,$A96,Colección!$M$2:$M$10001,"Compra") -> 4 | D96: =IF($B96=0,"",_xlfn.RANK.EQ($B96,$B$2:$B$321,0)+COUNTIF($B$2:B96,$B96)-1) -> 233 | F96: ="Ascendant Packleader" -> Ascendant Packleader | G96: =SUMIFS(Colección!$L$2:$L$10001,Colección!$F$2:$F$10001,$F96,Colección!$M$2:$M$10001,"Compra") -> 6.6812104 | H96: =IF($G96=0,"",_xlfn.RANK.EQ($G96,$G$2:$G$2353,0)+COUNTIF($G$2:G96,$G96)-1) -> 830
A97: ="Eternal Masters" -> Eternal Masters | B97: =SUMIFS(Colección!$L$2:$L$10001,Colección!$G$2:$G$10001,$A97,Colección!$M$2:$M$10001,"Compra") -> 42.421682 | C97: =SUMIFS(Colección!$K$2:$K$10001,Colección!$G$2:$G$10001,$A97,Colección!$M$2:$M$10001,"Compra") -> 1 | D97: =IF($B97=0,"",_xlfn.RANK.EQ($B97,$B$2:$B$321,0)+COUNTIF($B$2:B97,$B97)-1) -> 152 | F97: ="Ashe, Focused" -> Ashe, Focused | G97: =SUMIFS(Colección!$L$2:$L$10001,Colección!$F$2:$F$10001,$F97,Colección!$M$2:$M$10001,"Compra") -> 1.3322449 | H97: =IF($G97=0,"",_xlfn.RANK.EQ($G97,$G$2:$G$2353,0)+COUNTIF($G$2:G97,$G97)-1) -> 1531
A98: ="Eventide" -> Eventide | B98: =SUMIFS(Colección!$L$2:$L$10001,Colección!$G$2:$G$10001,$A98,Colección!$M$2:$M$10001,"Compra") -> 5.7678974 | C98: =SUMIFS(Colección!$K$2:$K$10001,Colección!$G$2:$G$10001,$A98,Colección!$M$2:$M$10001,"Compra") -> 1 | D98: =IF($B98=0,"",_xlfn.RANK.EQ($B98,$B$2:$B$321,0)+COUNTIF($B$2:B98,$B98)-1) -> 260 | F98: ="Ashiok, Dream Render" -> Ashiok, Dream Render | G98: =SUMIFS(Colección!$L$2:$L$10001,Colección!$F$2:$F$10001,$F98,Colección!$M$2:$M$10001,"Compra") -> 5.1770068 | H98: =IF($G98=0,"",_xlfn.RANK.EQ($G98,$G$2:$G$2353,0)+COUNTIF($G$2:G98,$G98)-1) -> 961
A99: ="Exodus" -> Exodus | B99: =SUMIFS(Colección!$L$2:$L$10001,Colección!$G$2:$G$10001,$A99,Colección!$M$2:$M$10001,"Compra") -> 1327.3305 | C99: =SUMIFS(Colección!$K$2:$K$10001,Colección!$G$2:$G$10001,$A99,Colección!$M$2:$M$10001,"Compra") -> 9 | D99: =IF($B99=0,"",_xlfn.RANK.EQ($B99,$B$2:$B$321,0)+COUNTIF($B$2:B99,$B99)-1) -> 4 | F99: ="Asmoranomardicadaistinaculdacar" -> Asmoranomardicadaistinaculdacar | G99: =SUMIFS(Colección!$L$2:$L$10001,Colección!$F$2:$F$10001,$F99,Colección!$M$2:$M$10001,"Compra") -> 1.3291053 | H99: =IF($G99=0,"",_xlfn.RANK.EQ($G99,$G$2:$G$2353,0)+COUNTIF($G$2:G99,$G99)-1) -> 1535
A100: ="Fate Reforged" -> Fate Reforged | B100: =SUMIFS(Colección!$L$2:$L$10001,Colección!$G$2:$G$10001,$A100,Colección!$M$2:$M$10001,"Compra") -> 2.1150196 | C100: =SUMIFS(Colección!$K$2:$K$10001,Colección!$G$2:$G$10001,$A100,Colección!$M$2:$M$10001,"Compra") -> 7 | D100: =IF($B100=0,"",_xlfn.RANK.EQ($B100,$B$2:$B$321,0)+COUNTIF($B$2:B100,$B100)-1) -> 285 | F100: ="Assassin Token (B 1/1 Menace) // Phobos Token (R 3/2)" -> Assassin Token (B 1/1 Menace) // Phobos Token (R 3/2) | G100: =SUMIFS(Colección!$L$2:$L$10001,Colección!$F$2:$F$10001,$F100,Colección!$M$2:$M$10001,"Compra") -> 0.27607843 | H100: =IF($G100=0,"",_xlfn.RANK.EQ($G100,$G$2:$G$2353,0)+COUNTIF($G$2:G100,$G100)-1) -> 2022
...

Sheet Resumen actualización
A1: Resumen de actualizacion: Cancelados marcados y Graficos con formulas
A3: Lineas Coleccion antes de separar | B3: 3562
A4: Lineas Compra/Venta originales separadas | B4: 292
A5: Lineas Coleccion finales | B5: 3854
A6: Lineas Compra finales | B6: 3285
A7: Lineas Venta finales | B7: 569
A8: Lineas Compra/Venta restantes | B8: 0
A10: Ventas Compra/Venta mapeadas a pedido CardMarket | B10: 255
A11: Ventas Compra/Venta sin pedido identificado | B11: 37
A12: Ajuste neto aplicado en Precio de venta por matching mbox | B12: -0.55
A14: Gasto compra total final | B14: 38396.52
A15: Importe venta total final | B15: 7217.91
A16: Lineas finales en Pedidos CardMarket | B16: 1739
A18: Regla nueva | B18: Compra y Venta ya no comparten fila: Total queda como importe de la operacion y Precio de venta solo se rellena en ventas.
A19: Trazabilidad | B19: Ver hoja Desglose Compra Venta para el origen de cada split Compra/Venta.
A21: Detalle matching Compra/Venta
A22: CardMarket corregido desde precio unitario | B22: 1
A23: CardMarket corregido desde precio unitario (candidato ambiguo resuelto) | B23: 1
A24: CardMarket exacto | B24: 250
A25: CardMarket exacto (candidato ambiguo resuelto) | B25: 3
A26: Sintético sin pedido identificado | B26: 37
A28: Pedidos con comentario Cancelado marcados como Cancelado | B28: 158
A29: Pedidos cuyo Tipo Operación ha cambiado a Cancelado | B29: 158
A30: Lineas Coleccion marcadas como Cancelado | B30: 124
A31: Lineas Coleccion cuyo Tipo Operación ha cambiado a Cancelado | B31: 124
A32: Formulas KPI implementadas | B32: Graficos!H1:H6
A33: Formula gasto mensual | B33: Graficos!A5
A34: Formula resumen TCG | B34: Graficos!J5
A35: Formula resumen Compra/Venta/Cancelado | B35: Graficos!J19
A36: Formula rankings | B36: Graficos!J35, Graficos!A56, Graficos!A78
A37: Nota | B37: Las formulas dinamicas se recalculan al abrir el archivo en Excel.

Sheet Mapeo Hareruya
A1: Codigo Hareruya | B1: Edicion normalizada | C1: Lineas activas | D1: Codigo fuente | E1: Fuente / nota
A2: 2X2-BF | B2: Double Masters 2022: Extras | C2: 8 | D2: 2x2 | E2: https://scryfall.com/sets/2x2
A3: 2XM | B3: Double Masters | C3: 1 | D3: 2xm | E3: https://scryfall.com/sets/2xm
A4: 2XM-BF | B4: Double Masters: Extras | C4: 1 | D4: 2xm | E4: https://scryfall.com/sets/2xm
A5: 4EDBB | B5: Fourth Edition: Black Bordered | C5: 12 | D5: 4bb | E5: https://scryfall.com/sets/4bb
A6: 5ED | B6: Fifth Edition | C6: 2 | D6: 5ed | E6: https://scryfall.com/sets/5ed
A7: ALL | B7: Alliances | C7: 1 | D7: all | E7: https://scryfall.com/sets/all
A8: APC | B8: Apocalypse | C8: 6 | D8: apc | E8: https://scryfall.com/sets/apc
A9: BRC-BF | B9: Commander: The Brothers' War | C9: 3 | D9: brc | E9: https://scryfall.com/sets/brc
A10: BRR | B10: Retro Frame Artifacts | C10: 1 | D10: brr | E10: https://scryfall.com/sets/brr
A11: DFT | B11: Aetherdrift | C11: 3 | D11: dft | E11: https://scryfall.com/sets/dft
A12: DFT-BF | B12: Aetherdrift: Extras | C12: 1 | D12: dft | E12: https://scryfall.com/sets/dft
A13: DMU | B13: Dominaria United | C13: 2 | D13: dmu | E13: https://scryfall.com/sets/dmu
... A52: ZNE | B52: Zendikar Rising: Expeditions | C52: 2 | D52: zne | E52: https://scryfall.com/sets/zne
A53: 流星マーク | B53: Promos | C53: 3 | E53: Marca promocional Hareruya; normalizada como Promos
A54: Accesorios | B54: Accesorios | C54: 15 | E54: Lineas Hareruya sin codigo de expansion

Sheet Pedidos WhatsApp
A1: Order Number | B1: Mes | C1: Año | D1: Date | E1: Seller / Buyer | F1: Card Name | G1: Edition | H1: Playset | I1: Language | J1: Unit Price | K1: Quantity | L1: Total | M1: Tipo Operación | N1: Precio de venta | O1: TCG | P1: Notas
A2: WA-20240501-01 | B2: Mayo | C2: 2024 | D2: 45413 | E2: Juan Premodern | F2: Wasteland | G2: Torment | H2: Si | I2: Japonés | J2: 145 | K2: 1 | L2: 145 | M2: Compra | O2: Magic The Gathering | P2: Importado desde Pedidos WhatsApp
A3: WA-20240501-02 | B3: Mayo | C3: 2024 | D3: 45413 | E3: Nicolas Premodern | F3: Mental Note | G3: Sin edición especificada | H3: Si | I3: Japonés | J3: 23 | K3: 1 | L3: 23 | M3: Compra | O3: Magic The Gathering | P3: Importado desde Pedidos WhatsApp
A4: WA-20240501-03 | B4: Mayo | C4: 2024 | D4: 45413 | E4: Pascual Premodern | F4: Intuition | G4: Tempest | H4: No | I4: Japonés | J4: 100 | K4: 1 | L4: 100 | M4: Compra | O4: Magic The Gathering | P4: Importado desde Pedidos WhatsApp
A5: WA-20240501-03 | B5: Mayo | C5: 2024 | D5: 45413 | E5: Pascual Premodern | F5: Stifle | G5: Scourge | H5: Si | I5: Japonés | J5: 150 | K5: 1 | L5: 150 | M5: Compra | O5: Magic The Gathering | P5: Importado desde Pedidos WhatsApp
A6: WA-20240501-03 | B6: Mayo | C6: 2024 | D6: 45413 | E6: Pascual Premodern | F6: Chill | G6: Tempest | H6: Si | I6: Japonés | J6: 5 | K6: 1 | L6: 5 | M6: Compra | O6: Magic The Gathering | P6: Importado desde Pedidos WhatsApp
A7: WA-20240501-03 | B7: Mayo | C7: 2024 | D7: 45413 | E7: Pascual Premodern | F7: Deep Analysis | G7: Torment | H7: No | I7: Japonés | J7: 3.3 | K7: 3 | L7: 9.9 | M7: Compra | O7: Magic The Gathering | P7: Importado desde Pedidos WhatsApp
A8: WA-20241001-01 | B8: Octubre | C8: 2024 | D8: 45566 | E8: 34633956985 | F8: Ocelot Pride | G8: Modern Horizons 3 | H8: Si | I8: Inglés | J8: 35.8175 | K8: 4 | L8: 143.27 | M8: Venta | N8: 143.27 | O8: Magic The Gathering | P8: Importado desde Pedidos WhatsApp
A9: WA-20241001-02 | B9: Octubre | C9: 2024 | D9: 45566 | E9: David Premodern | F9: Fire/Ice | G9: Apocalypse | H9: Si | I9: Japonés | J9: 12 | K9: 1 | L9: 12 | M9: Compra | O9: Magic The Gathering | P9: Importado desde Pedidos WhatsApp
A10: WA-20250101-01 | B10: Enero | C10: 2025 | D10: 45658 | E10: Ivan Arjona | F10: The Meathook Massacre (V.1) | G10: Innistrad Remastered: Extras | H10: No | I10: Inglés | J10: 22 | K10: 1 | L10: 22 | M10: Compra | O10: Magic The Gathering | P10: Importado desde Pedidos WhatsApp
A11: WA-20250307-01 | B11: Marzo | C11: 2025 | D11: 45723 | E11: Andrés Ramón | F11: Dark Ritual | G11: Fourth Edition: Black Bordered | H11: No | I11: Japonés | J11: 8 | K11: 4 | L11: 32 | M11: Compra | O11: Magic The Gathering | P11: Importado desde Pedidos WhatsApp
A12: WA-20250307-02 | B12: Marzo | C12: 2025 | D12: 45723 | E12: DanielJV | F12: Caretaker's Talent | G12: Bloomburrow | H12: No | I12: Inglés | J12: 13.99 | K12: 4 | L12: 55.96 | M12: Compra | O12: Magic The Gathering | P12: Importado desde Pedidos WhatsApp
A13: WA-20250307-02 | B13: Marzo | C13: 2025 | D13: 45723 | E13: DanielJV | F13: Mirrex | G13: Phyrexia: All Will Be One | H13: No | I13: Japonés | J13: 5.49 | K13: 3 | L13: 16.47 | M13: Compra | O13: Magic The Gathering | P13: Importado desde Pedidos WhatsApp
A14: WA-20250307-02 | B14: Marzo | C14: 2025 | D14: 45723 | E14: DanielJV | F14: Boon-Bringer Valkyrie | G14: March of the Machine | H14: No | I14: Inglés | J14: 0.99 | K14: 2 | L14: 1.98 | M14: Compra | O14: Magic The Gathering | P14: Importado desde Pedidos WhatsApp
A15: WA-20250307-03 | B15: Marzo | C15: 2025 | D15: 45723 | E15: punipwni | F15: Wrath of God | G15: Fourth Edition: Black Bordered | H15: No | I15: Japonés | J15: 39 | K15: 2 | L15: 78 | M15: Compra | O15: Magic The Gathering | P15: Importado desde Pedidos WhatsApp
A16: WA-20250307-03 | B16: Marzo | C16: 2025 | D16: 45723 | E16: punipwni | F16: Hypnotic Specter | G16: Fourth Edition: Black Bordered | H16: No | I16: Japonés | J16: 24 | K16: 4 | L16: 96 | M16: Compra | O16: Magic The Gathering | P16: Importado desde Pedidos WhatsApp
A17: WA-20250307-03 | B17: Marzo | C17: 2025 | D17: 45723 | E17: punipwni | F17: Skeletal Scrying | G17: Odyssey | H17: No | I17: Japonés | J17: 10 | K17: 4 | L17: 40 | M17: Compra | O17: Magic The Gathering | P17: Importado desde Pedidos WhatsApp
A18: WA-20250307-03 | B18: Marzo | C18: 2025 | D18: 45723 | E18: punipwni | F18: Dust Bowl | G18: Mercadian Masques | H18: No | I18: Japonés | J18: 14 | K18: 1 | L18: 14 | M18: Compra | O18: Magic The Gathering | P18: Importado desde Pedidos WhatsApp
A19: WA-20250307-03 | B19: Marzo | C19: 2025 | D19: 45723 | E19: punipwni | F19: Nantuko Shade | G19: Torment | H19: No | I19: Japonés | J19: 6.75 | K19: 4 | L19: 27 | M19: Compra | O19: Magic The Gathering | P19: Importado desde Pedidos WhatsApp
A20: WA-20250307-03 | B20: Marzo | C20: 2025 | D20: 45723 | E20: punipwni | F20: Disenchant | G20: Fourth Edition: Black Bordered | H20: No | I20: Japonés | J20: 4 | K20: 4 | L20: 16 | M20: Compra | O20: Magic The Gathering | P20: Importado desde Pedidos WhatsApp
... A35: WA-20250430-01 | B35: Abril | C35: 2025 | D35: 45777 | E35: Japón | F35: Recurring Nightmare | G35: Exodus | H35: No | I35: Japonés | J35: 30 | K35: 1 | L35: 30 | M35: Compra | O35: Magic The Gathering | P35: Importado desde Pedidos WhatsApp
A36: WA-20250611-01 | B36: Junio | C36: 2025 | D36: 45819 | E36: 34676414055 | F36: Yavimaya Elder | G36: Urza's Destiny | H36: Si | I36: Japonés | J36: 1 | K36: 4 | L36: 4 | M36: Venta | N36: 4 | O36: Magic The Gathering | P36: Importado desde Pedidos WhatsApp
A37: WA-20250611-01 | B37: Junio | C37: 2025 | D37: 45819 | E37: 34676414055 | F37: Phyrexian Rager | G37: Apocalypse | H37: Si | I37: Japonés | J37: 1.5 | K37: 4 | L37: 6 | M37: Venta | N37: 6 | O37: Magic The Gathering | P37: Importado desde Pedidos WhatsApp
A38: WA-20250611-02 | B38: Junio | C38: 2025 | D38: 45819 | E38: 34683281207 | F38: Squee, Goblin Nabob | G38: Mercadian Masques | H38: No | I38: Japonés | J38: 15 | K38: 1 | L38: 15 | M38: Venta | N38: 15 | O38: Magic The Gathering | P38: Importado desde Pedidos WhatsApp
A39: WA-20250708-01 | B39: Julio | C39: 2025 | D39: 45846 | E39: 34653388331 | F39: Opt | G39: Invasion | H39: No | I39: Japonés | J39: 1 | K39: 1 | L39: 1 | M39: Venta | N39: 1 | O39: Magic The Gathering | P39: Importado desde Pedidos WhatsApp
A40: WA-20250708-01 | B40: Julio | C40: 2025 | D40: 45846 | E40: 34653388331 | F40: Opt | G40: Invasion | H40: No | I40: Chino | J40: 0.5 | K40: 3 | L40: 1.5 | M40: Venta | N40: 1.5 | O40: Magic The Gathering | P40: Importado desde Pedidos WhatsApp
A41: WA-20250708-01 | B41: Julio | C41: 2025 | D41: 45846 | E41: 34653388331 | F41: Haunting Echoes | G41: Odyssey | H41: No | I41: Japonés | J41: 8 | K41: 2 | L41: 16 | M41: Venta | N41: 16 | O41: Magic The Gathering | P41: Importado desde Pedidos WhatsApp
A42: WA-20250708-01 | B42: Julio | C42: 2025 | D42: 45846 | E42: 34653388331 | F42: Ravenous Baloth | G42: Onslaught | H42: No | I42: Japonés | J42: 17 | K42: 4 | L42: 68 | M42: Venta | N42: 68 | O42: Magic The Gathering | P42: Importado desde Pedidos WhatsApp
A43: WA-20250708-01 | B43: Julio | C43: 2025 | D43: 45846 | E43: 34653388331 | F43: Living Wish | G43: Judgment | H43: No | I43: Japonés | J43: 4.5 | K43: 4 | L43: 18 | M43: Venta | N43: 18 | O43: Magic The Gathering | P43: Importado desde Pedidos WhatsApp
A44: WA-20250708-01 | B44: Julio | C44: 2025 | D44: 45846 | E44: 34653388331 | F44: Spiritmonger | G44: Apocalypse | H44: No | I44: Japonés | J44: 3 | K44: 1 | L44: 3 | M44: Venta | N44: 3 | O44: Magic The Gathering | P44: Importado desde Pedidos WhatsApp
A45: WA-20250708-01 | B45: Julio | C45: 2025 | D45: 45846 | E45: 34653388331 | F45: Cursed Totem | G45: Mirage | H45: No | I45: Japonés | J45: 20 | K45: 1 | L45: 20 | M45: Venta | N45: 20 | O45: Magic The Gathering | P45: Importado desde Pedidos WhatsApp
A46: WA-20250708-02 | B46: Julio | C46: 2025 | D46: 45846 | E46: David Rivero | F46: Vivi Ornitier (V.1) | G46: FINAL FANTASY: Extras | H46: No | I46: Inglés | J46: 85 | K46: 1 | L46: 85 | M46: Compra | O46: Magic The Gathering | P46: Importado desde Pedidos WhatsApp
A47: WA-20251201-01 | B47: Diciembre | C47: 2025 | D47: 45992 | E47: 34640601276 | F47: Goblin Sharpshooter | G47: Onslaught | H47: No | I47: Japonés | J47: 25 | K47: 1 | L47: 25 | M47: Venta | N47: 25 | O47: Magic The Gathering | P47: Importado desde Pedidos WhatsApp
A48: WA-20251203-01 | B48: Diciembre | C48: 2025 | D48: 45994 | E48: 34644320420 | F48: Cosmogrand Zenith | G48: Edge of Eternities | H48: Si | I48: Inglés | J48: 11.25 | K48: 4 | L48: 45 | M48: Venta | N48: 45 | O48: Magic The Gathering | P48: Importado desde Pedidos WhatsApp
A49: WA-20251203-02 | B49: Diciembre | C49: 2025 | D49: 45994 | E49: 34688908486 | F49: Simic Growth Chamber | G49: Sin edición especificada | H49: Si | I49: Japonés | J49: 2.75 | K49: 4 | L49: 11 | M49: Venta | N49: 11 | O49: Magic The Gathering | P49: Importado desde Pedidos WhatsApp
A50: WA-20251203-03 | B50: Diciembre | C50: 2025 | D50: 45994 | E50: Aner | F50: Underground Sea | G50: Revised | H50: No | I50: Inglés | J50: 600 | K50: 1 | L50: 600 | M50: Compra | O50: Magic The Gathering | P50: Importado desde Pedidos WhatsApp
A51: WA-20251220-01 | B51: Diciembre | C51: 2025 | D51: 46011 | E51: 34628270693 | F51: City of Traitors | G51: Exodus | H51: No | I51: Japonés | J51: 310 | K51: 1 | L51: 310 | M51: Compra | O51: Magic The Gathering | P51: Importado desde Pedidos WhatsApp
A52: WA-20260101-01 | B52: Enero | C52: 2026 | D52: 46023 | E52: Bronhy | F52: Serra's Sanctum | G52: Urza's Saga | H52: No | I52: Japonés | J52: 350 | K52: 2 | L52: 700 | M52: Compra | O52: Magic The Gathering | P52: Importado desde Pedidos WhatsApp
A53: WA-20260101-02 | B53: Enero | C53: 2026 | D53: 46023 | E53: Liddia7 | F53: Accumulated Knowledge | G53: Nemesis | H53: No | I53: Japonés | J53: 2.5 | K53: 3 | L53: 7.5 | M53: Compra | O53: Magic The Gathering | P53: Importado desde Pedidos WhatsApp
A54: WA-20260101-02 | B54: Enero | C54: 2026 | D54: 46023 | E54: Liddia7 | F54: Tranquil Domain | G54: Mirage | H54: No | I54: Japonés | J54: 6 | K54: 4 | L54: 24 | M54: Compra | O54: Magic The Gathering | P54: Importado desde Pedidos WhatsApp
A55: WA-20260101-03 | B55: Enero | C55: 2026 | D55: 46023 | E55: Willybizarre | F55: Serra's Sanctum | G55: Urza's Saga | H55: No | I55: Japonés | J55: 330 | K55: 1 | L55: 330 | M55: Compra | O55: Magic The Gathering | P55: Importado desde Pedidos WhatsApp

Sheet Desglose Compra Venta
A1: Fila original Coleccion | B1: Pedido compra | C1: Pedido venta | D1: Estado matching | E1: Card Name | F1: Edition | G1: Language | H1: Qty compra original | I1: Total compra original | J1: Precio venta anterior | K1: Precio venta separado | L1: Comprador venta | M1: Fecha venta | N1: Qty venta | O1: Unit venta | P1: TCG
A2: 274 | B2: 1262888434 | C2: 1239427732 | D2: CardMarket exacto | E2: Haliya, Guided by Light | F2: Edge of Eternities: Extras | G2: Inglés | H2: 4 | I2: 24.05 | J2: 19.33 | K2: 19.33 | L2: Vladitsv | M2: 13.11.2025 | N2: 4 | O2: 4.8325 | P2: Magic The Gathering
A3: 309 | B3: 1255553836 | C3: 1223440654 | D3: CardMarket exacto (candidato ambiguo resuelto) | E3: Stoneforge Mystic | F3: Worldwake | G3: Inglés | H3: 2 | I3: 33.43 | J3: 15.23 | K3: 15.23 | L3: FalcorMelkor | M3: 07.08.2025 | N3: 1 | O3: 15.23 | P3: Magic The Gathering
A4: 313 | B4: 1254712460 | C4: 1276244057 | D4: CardMarket exacto | E4: Sunderflock | F4: Lorwyn Eclipsed: Extras | G4: Inglés | H4: 2 | I4: 7.45 | J4: 11.95 | K4: 11.95 | L4: Beliase | M4: 26.05.2026 | N4: 3 | O4: 3.983333 | P4: Magic The Gathering
A5: 366 | B5: 1250180858 | C5: 1118014908 | D5: CardMarket exacto | E5: Cyclonic Rift | F5: Return to Ravnica | G5: Inglés | H5: 1 | I5: 25.45 | J5: 32.75 | K5: 32.75 | L5: roggearne | M5: 05.07.2023 | N5: 1 | O5: 32.75 | P5: Magic The Gathering
A6: 462 | B6: 1241623919 | C6: 1241597708 | D6: CardMarket exacto | E6: Birthing Ritual | F6: Modern Horizons 3: Extras | G6: Inglés | H6: 1 | I6: 9.32 | J6: 8.03 | K6: 8.03 | L6: Lyrae | M6: 01.12.2025 | N6: 1 | O6: 8.03 | P6: Magic The Gathering
A7: 476 | B7: 1240432988 | C7: 1244111848 | D7: CardMarket exacto | E7: Serum Visions | F7: Fifth Dawn | G7: Inglés | H7: 2 | I7: 2.23 | J7: 0.79555556 | K7: 0.79555556 | L7: robleno | M7: 09.12.2025 | N7: 2 | O7: 0.397778 | P7: Magic The Gathering
A8: 495 | B8: 1239758352 | C8: 1223745664 | D8: CardMarket exacto | E8: Stoneforge Mystic | F8: Worldwake | G8: Inglés | H8: 2 | I8: 21.33 | J8: 15.23 | K8: 15.23 | L8: Riverup | M8: 22.08.2025 | N8: 1 | O8: 15.23 | P8: Magic The Gathering
A9: 546 | B9: 1234769837 | C9: 1234193549 | D9: CardMarket exacto | E9: Amulet of Vigor | F9: Worldwake | G9: Inglés | H9: 2 | I9: 55.93 | J9: 23.28 | K9: 23.28 | L9: erreme2121 | M9: 14.10.2025 | N9: 1 | O9: 23.28 | P9: Magic The Gathering
A10: 552 | B10: 1232885725 | C10: 1234987459 | D10: CardMarket exacto | E10: Amulet of Vigor | F10: Worldwake | G10: Inglés | H10: 1 | I10: 26.29 | J10: 24.28 | K10: 24.28 | L10: Ancor96 | M10: 24.10.2025 | N10: 1 | O10: 24.28 | P10: Magic The Gathering
A11: 557 | B11: 1231010967 | C11: 1274354305 | D11: CardMarket exacto | E11: Goblin Warchief | F11: Scourge | G11: Japonés | H11: 1 | I11: 3.83 | J11: 1.95 | K11: 1.95 | L11: AATHOV | M11: 27.05.2026 | N11: 1 | O11: 1.95 | P11: Magic The Gathering
A12: 559 | B12: 1230639811 | C12: 1238778886 | D12: CardMarket exacto | E12: Azure Beastbinder | F12: Bloomburrow: Extras | G12: Inglés | H12: 1 | I12: 2.33 | J12: 22.35 | K12: 22.35 | L12: Kurgankurgan | M12: 14.11.2025 | N12: 2 | O12: 11.175 | P12: Magic The Gathering
A13: 580 | B13: 1228559054 | C13: 1243793386 | D13: CardMarket exacto | E13: Mistvault Bridge | F13: Commander: The Brothers' War | G13: Inglés | H13: 4 | I13: 3.5701445 | J13: 3.33 | K13: 3.33 | L13: Rul83 | M13: 09.12.2025 | N13: 4 | O13: 0.8325 | P13: Magic The Gathering
... A17: 643 | B17: 1220383457 | C17: 1194307080 | D17: CardMarket exacto | E17: Agatha's Soul Cauldron | F17: Wilds of Eldraine | G17: Inglés | H17: 1 | I17: 39.93 | J17: 42.55 | K17: 42.55 | L17: DarkJaBBa | M17: 11.02.2025 | N17: 1 | O17: 42.55 | P17: Magic The Gathering
A18: 657 | B18: 1219222787 | C18: CVSALE-1219222787-01 | D18: Sintético sin pedido identificado | E18: Marang River Regent // Coil and Catch | F18: Tarkir: Dragonstorm | G18: Inglés | H18: 4 | I18: 16.815169 | J18: 8.9172464 | K18: 8.9172464 | L18: No identificado | M18: 04.07.2025 | N18: 4 | O18: 2.229312 | P18: Magic The Gathering
A19: 660 | B19: 1219053120 | C19: 1255482037 | D19: CardMarket exacto | E19: Monument to Endurance | F19: Aetherdrift: Extras | G19: Inglés | H19: 4 | I19: 31.93 | J19: 62.23 | K19: 62.23 | L19: Kenoven | M19: 09.02.2026 | N19: 4 | O19: 15.5575 | P19: Magic The Gathering
A20: 661 | B20: 1219048667 | C20: 1249777080 | D20: CardMarket exacto | E20: Ral, Crackling Wit (V.1) | F20: Bloomburrow: Extras | G20: Japonés | H20: 2 | I20: 18.31 | J20: 18 | K20: 18 | L20: davtaz | M20: 23.01.2026 | N20: 1 | O20: 18 | P20: Magic The Gathering
A21: 665 | B21: 1219042917 | C21: 1246809442 | D21: CardMarket exacto | E21: Riverpyre Verge | F21: Aetherdrift: Extras | G21: Inglés | H21: 4 | I21: 44.04786 | J21: 87.4 | K21: 87.4 | L21: Racato | M21: 29.12.2025 | N21: 4 | O21: 21.85 | P21: Magic The Gathering
A22: 670 | B22: 1218844710 | C22: 1242211482 | D22: CardMarket exacto | E22: Preacher of the Schism | F22: The Lost Caverns of Ixalan | G22: Inglés | H22: 3 | I22: 11.685105 | J22: 4.4 | K22: 4.4 | L22: Gerardo80 | M22: 11.12.2025 | N22: 1 | O22: 4.4 | P22: Magic The Gathering
A23: 679 | B23: 1218815145 | C23: 1258407112 | D23: CardMarket exacto | E23: Voldaren Thrillseeker | F23: March of the Machine | G23: Inglés | H23: 1 | I23: 0.5 | J23: 0.80942623 | K23: 0.80942623 | L23: Metropolis-Center | M23: 03.03.2026 | N23: 3 | O23: 0.269809 | P23: Magic The Gathering
A24: 722 | B24: 1214667069 | C24: 1157804109 | D24: CardMarket exacto | E24: Galvanic Blast | F24: Scars of Mirrodin | G24: Japonés | H24: 4 | I24: 16.553266 | J24: 5.12 | K24: 5.12 | L24: MrColos | M24: 27.05.2024 | N24: 2 | O24: 2.56 | P24: Magic The Gathering
A25: 725 | B25: 1214178445 | C25: 1171549482 | D25: CardMarket exacto (candidato ambiguo resuelto) | E25: Walking Ballista | F25: Aether Revolt | G25: Inglés | H25: 3 | I25: 38.985091 | J25: 12.17 | K25: 12.17 | L25: esboards1 | M25: 03.09.2024 | N25: 1 | O25: 12.17 | P25: Magic The Gathering
A26: 734 | B26: 1213602383 | C26: 1250212850 | D26: CardMarket exacto | E26: Nevermore | F26: Innistrad | G26: Inglés | H26: 3 | I26: 1.25 | J26: 1.6647727 | K26: 1.6647727 | L26: Yajaidi | M26: 20.01.2026 | N26: 3 | O26: 0.554924 | P26: Magic The Gathering
A27: 737 | B27: 1213602303 | C27: 1192929609 | D27: CardMarket exacto | E27: On Thin Ice | F27: Modern Horizons | G27: Inglés | H27: 4 | I27: 6.13 | J27: 7.2428571 | K27: 7.2428571 | L27: bonic | M27: 22.02.2025 | N27: 3 | O27: 2.414286 | P27: Magic The Gathering
A28: 748 | B28: 1211774266 | C28: 1211690069 | D28: CardMarket exacto | E28: The Watcher in the Water | F28: The Lord of the Rings: Tales of Middle-earth | G28: Inglés | H28: 1 | I28: 7.7861213 | J28: 1.0679574 | K28: 1.0679574 | L28: suavejuanma | M28: 21.05.2025 | N28: 1 | O28: 1.067957 | P28: Magic The Gathering
A29: 756 | B29: 1211773018 | C29: 1249717335 | D29: CardMarket exacto | E29: Call of the Ring | F29: The Lord of the Rings: Tales of Middle-earth | G29: Inglés | H29: 1 | I29: 4.3228443 | J29: 3.4 | K29: 3.4 | L29: Sheisenn1809 | M29: 14.01.2026 | N29: 1 | O29: 3.4 | P29: Magic The Gathering
A30: 775 | B30: 1210864766 | C30: 1263299290 | D30: CardMarket exacto | E30: Silverbluff Bridge | F30: Commander: The Brothers' War | G30: Inglés | H30: 4 | I30: 3.1066289 | J30: 9.25 | K30: 9.25 | L30: Riotaire | M30: 31.03.2026 | N30: 4 | O30: 2.3125 | P30: Magic The Gathering
... A36: 1096 | B36: 1198703619 | C36: 1255989435 | D36: CardMarket exacto | E36: Wastewood Verge | F36: Aetherdrift: Extras | G36: Inglés | H36: 1 | I36: 8.33 | J36: 8.4 | K36: 8.4 | L36: kaiserknight19 | M36: 17.02.2026 | N36: 1 | O36: 8.4 | P36: Magic The Gathering
A37: 1116 | B37: 1197466620 | C37: CVSALE-1197466620-01 | D37: Sintético sin pedido identificado | E37: Elas il-Kor, Sadistic Pilgrim (V.1) | F37: Dominaria United: Extras | G37: Inglés | H37: 4 | I37: 1.4582857 | J37: 1.1221907 | K37: 1.1221907 | L37: No identificado | M37: 18.02.2025 | N37: 4 | O37: 0.280548 | P37: Magic The Gathering
A38: 1130 | B38: 1195814832 | C38: 1159274341 | D38: CardMarket exacto | E38: Memnite | F38: Scars of Mirrodin | G38: Inglés | H38: 4 | I38: 9.29 | J38: 3.72 | K38: 3.72 | L38: LucasHobbes | M38: 03.06.2024 | N38: 1 | O38: 3.72 | P38: Magic The Gathering
A39: 1145 | B39: 1194915006 | C39: 1131574286 | D39: CardMarket exacto | E39: Agatha's Soul Cauldron | F39: Wilds of Eldraine | G39: Inglés | H39: 1 | I39: 35.93 | J39: 42.2 | K39: 42.2 | L39: dmnferreira | M39: 30.10.2023 | N39: 1 | O39: 42.2 | P39: Magic The Gathering
A40: 1168 | B40: 1192922149 | C40: 1202034396 | D40: CardMarket exacto | E40: Aven Interrupter | F40: Outlaws of Thunder Junction | G40: Inglés | H40: 1 | I40: 3.83 | J40: 7.32 | K40: 7.32 | L40: PlaneswalkersTeam | M40: 02.04.2025 | N40: 1 | O40: 7.32 | P40: Magic The Gathering
A41: 1200 | B41: 1190728790 | C41: 1241565486 | D41: CardMarket exacto | E41: Smuggler's Surprise | F41: Outlaws of Thunder Junction | G41: Inglés | H41: 1 | I41: 2.5898589 | J41: 22.25 | K41: 22.25 | L41: Kevin9990 | M41: 24.11.2025 | N41: 4 | O41: 5.5625 | P41: Magic The Gathering
A42: 1202 | B42: 1190728790 | C42: 1241668804 | D42: CardMarket exacto | E42: Outcaster Trailblazer | F42: Outlaws of Thunder Junction | G42: Inglés | H42: 4 | I42: 6.0229277 | J42: 4.3855346 | K42: 4.3855346 | L42: toycastle-D | M42: 24.11.2025 | N42: 4 | O42: 1.096384 | P42: Magic The Gathering
A43: 1205 | B43: 1190720765 | C43: 1252378732 | D43: CardMarket exacto | E43: Enduring Courage (V.1) | F43: Duskmourn: House of Horror: Extras | G43: Inglés | H43: 2 | I43: 4.3559342 | J43: 3.7647059 | K43: 3.7647059 | L43: Squirle | M43: 28.01.2026 | N43: 2 | O43: 1.882353 | P43: Magic The Gathering
A44: 1210 | B44: 1190070315 | C44: 1249091802 | D44: CardMarket exacto | E44: Lush Portico | F44: Murders at Karlov Manor | G44: Español | H44: 1 | I44: 7.5 | J44: 8.55 | K44: 8.55 | L44: debz701 | M44: 09.02.2026 | N44: 1 | O44: 8.55 | P44: Magic The Gathering
A45: 1232 | B45: 1188486169 | C45: 1188485592 | D45: CardMarket exacto | E45: Flame of Anor | F45: The Lord of the Rings: Tales of Middle-earth | G45: Inglés | H45: 4 | I45: 25.22 | J45: 21.02 | K45: 21.02 | L45: SrGekota | M45: 12.01.2025 | N45: 4 | O45: 5.255 | P45: Magic The Gathering
A46: 1243 | B46: 1188047728 | C46: 1244111848 | D46: CardMarket exacto | E46: Deceiver Exarch | F46: Commander 2013 | G46: Inglés | H46: 3 | I46: 1.5051217 | J46: 1.1933333 | K46: 1.1933333 | L46: robleno | M46: 09.12.2025 | N46: 3 | O46: 0.397778 | P46: Magic The Gathering
A47: 1247 | B47: 1187904430 | C47: CVSALE-1187904430-01 | D47: Sintético sin pedido identificado | E47: Griselbrand | F47: Avacyn Restored | G47: Inglés | H47: 1 | I47: 11.145961 | J47: 16.789236 | K47: 16.789236 | L47: No identificado | M47: 20.12.2024 | N47: 1 | O47: 16.789236 | P47: Magic The Gathering
A48: 1251 | B48: 1187561567 | C48: 1191950168 | D48: CardMarket exacto | E48: Gut Shot | F48: New Phyrexia | G48: Chino-S | H48: 4 | I48: 7.8 | J48: 9.13 | K48: 9.13 | L48: waskache | M48: 27.01.2025 | N48: 4 | O48: 2.2825 | P48: Magic The Gathering
A49: 1261 | B49: 1187231107 | C49: 1241668804 | D49: CardMarket exacto | E49: Ancient Cornucopia (V.1) | F49: The Big Score | G49: Inglés | H49: 1 | I49: 5.2087339 | J49: 1.0963836 | K49: 1.0963836 | L49: toycastle-D | M49: 24.11.2025 | N49: 1 | O49: 1.096384 | P49: Magic The Gathering
A50: 1269 | B50: 1186395377 | C50: 1242056139 | D50: CardMarket exacto | E50: Split Up | F50: Duskmourn: House of Horror | G50: Inglés | H50: 2 | I50: 8.0414634 | J50: 7.23 | K50: 7.23 | L50: Marcelrocle | M50: 27.11.2025 | N50: 2 | O50: 3.615 | P50: Magic The Gathering
A51: 1277 | B51: 1186392450 | C51: 1249045481 | D51: CardMarket exacto | E51: Novice Inspector | F51: Murders at Karlov Manor | G51: Inglés | H51: 4 | I51: 5.8099814 | J51: 5.8583333 | K51: 5.8583333 | L51: SnowyKnight | M51: 14.01.2026 | N51: 4 | O51: 1.464583 | P51: Magic The Gathering
A52: 1286 | B52: 1185932217 | C52: 1245439549 | D52: CardMarket exacto | E52: Lumra, Bellow of the Woods (V.1) | F52: Bloomburrow: Extras | G52: Inglés | H52: 1 | I52: 17.917898 | J52: 42.55 | K52: 42.55 | L52: Enderu01 | M52: 21.12.2025 | N52: 1 | O52: 42.55 | P52: Magic The Gathering
A53: 1301 | B53: 1185052001 | C53: 1240763009 | D53: CardMarket exacto | E53: Thornspire Verge | F53: Duskmourn: House of Horror: Extras | G53: Inglés | H53: 3 | I53: 21.92 | J53: 16.18 | K53: 16.18 | L53: monomoi | M53: 30.11.2025 | N53: 3 | O53: 5.393333 | P53: Magic The Gathering
A54: 1307 | B54: 1184996784 | C54: 1258407112 | D54: CardMarket exacto | E54: Analyze the Pollen | F54: Murders at Karlov Manor: Extras | G54: Inglés | H54: 2 | I54: 2.4974227 | J54: 1.079235 | K54: 1.079235 | L54: Metropolis-Center | M54: 03.03.2026 | N54: 2 | O54: 0.539617 | P54: Magic The Gathering
A55: 1320 | B55: 1183899080 | C55: 1201256238 | D55: CardMarket exacto | E55: Zur, Eternal Schemer (V.1) | F55: Dominaria United: Extras | G55: Inglés | H55: 1 | I55: 10.514943 | J55: 10.4 | K55: 10.4 | L55: Guilem44 | M55: 25.03.2025 | N55: 1 | O55: 10.4 | P55: Magic The Gathering
A56: 1321 | B56: 1183899080 | C56: 1199075481 | D56: CardMarket exacto | E56: Pawpatch Formation | F56: Bloomburrow | G56: Inglés | H56: 4 | I56: 10.514943 | J56: 11.3 | K56: 11.3 | L56: pallekuling | M56: 12.03.2025 | N56: 3 | O56: 3.766667 | P56: Magic The Gathering
A57: 1323 | B57: 1183898242 | C57: CVSALE-1183898242-01 | D57: Sintético sin pedido identificado | E57: Overlord of the Mistmoors | F57: Duskmourn: House of Horror | G57: Inglés | H57: 3 | I57: 24.871267 | J57: 25.92 | K57: 25.92 | L57: No identificado | M57: 23.11.2024 | N57: 3 | O57: 8.64 | P57: Magic The Gathering
A58: 1324 | B58: 1183898242 | C58: CVSALE-1183898242-02 | D58: Sintético sin pedido identificado | E58: Authority of the Consuls | F58: Magic: The Gathering Foundations | G58: Inglés | H58: 3 | I58: 10.167499 | J58: 10.78 | K58: 10.78 | L58: No identificado | M58: 23.11.2024 | N58: 3 | O58: 3.593333 | P58: Magic The Gathering
A59: 1326 | B59: 1183898242 | C59: 1243134485 | D59: CardMarket exacto | E59: Hushwood Verge | F59: Duskmourn: House of Horror: Extras | G59: Inglés | H59: 4 | I59: 20.647845 | J59: 11.23 | K59: 11.23 | L59: danicsb | M59: 01.12.2025 | N59: 2 | O59: 5.615 | P59: Magic The Gathering
A60: 1328 | B60: 1183898242 | C60: 1242930381 | D60: CardMarket exacto | E60: Split Up | F60: Duskmourn: House of Horror | G60: Inglés | H60: 2 | I60: 4.0669997 | J60: 4.426599 | K60: 4.426599 | L60: Metadiscipulo | M60: 02.12.2025 | N60: 2 | O60: 2.213299 | P60: Magic The Gathering
A61: 1330 | B61: 1183898242 | C61: 1194954076 | D61: CardMarket exacto | E61: Overlord of the Floodpits | F61: Duskmourn: House of Horror | G61: Inglés | H61: 3 | I61: 14.703768 | J61: 13.030562 | K61: 13.030562 | L61: Adricarf | M61: 07.02.2025 | N61: 3 | O61: 4.343521 | P61: Magic The Gathering
A62: 1331 | B62: 1183898242 | C62: 1198292265 | D62: CardMarket exacto | E62: Overlord of the Hauntwoods | F62: Duskmourn: House of Horror | G62: Inglés | H62: 4 | I62: 74.874508 | J62: 65.53 | K62: 65.53 | L62: safetronik1985 | M62: 27.02.2025 | N62: 4 | O62: 16.3825 | P62: Magic The Gathering
A63: 1332 | B63: 1183898242 | C63: 1215806617 | D63: CardMarket exacto | E63: Everywhere Token | F63: Duskmourn: House of Horror: Tokens | G63: Inglés | H63: 4 | I63: 12.305281 | J63: 8.3 | K63: 8.3 | L63: shiar | M63: 18.06.2025 | N63: 3 | O63: 2.766667 | P63: Magic The Gathering
A64: 1333 | B64: 1183897966 | C64: 1197512959 | D64: CardMarket exacto | E64: Zur, Eternal Schemer (V.1) | F64: Dominaria United: Extras | G64: Inglés | H64: 3 | I64: 23.47 | J64: 26.3 | K64: 26.3 | L64: EndlessFate | M64: 25.02.2025 | N64: 3 | O64: 8.766667 | P64: Magic The Gathering
A65: 1346 | B65: 1179942773 | C65: 1185865223 | D65: CardMarket exacto | E65: Enduring Innocence | F65: Duskmourn: House of Horror | G65: Inglés | H65: 4 | I65: 33.27 | J65: 35.1 | K65: 35.1 | L65: MTB123 | M65: 17.12.2024 | N65: 4 | O65: 8.775 | P65: Magic The Gathering
A66: 1347 | B66: 1179920868 | C66: 1219880469 | D66: CardMarket exacto | E66: Beza, the Bounding Spring | F66: Bloomburrow: Extras | G66: Inglés | H66: 1 | I66: 17.12 | J66: 39.83 | K66: 39.83 | L66: XAntonioX24 | M66: 15.07.2025 | N66: 2 | O66: 19.915 | P66: Magic The Gathering
A67: 1382 | B67: 1178155822 | C67: 1254900778 | D67: CardMarket exacto | E67: Three Steps Ahead | F67: Outlaws of Thunder Junction | G67: Inglés | H67: 1 | I67: 7.6325926 | J67: 9.4 | K67: 9.4 | L67: Cualquiera | M67: 05.02.2026 | N67: 1 | O67: 9.4 | P67: Magic The Gathering
A68: 1383 | B68: 1178155822 | C68: 1242930381 | D68: CardMarket exacto | E68: Three Steps Ahead | F68: Outlaws of Thunder Junction | G68: Inglés | H68: 1 | I68: 7.0874074 | J68: 6.753401 | K68: 6.753401 | L68: Metadiscipulo | M68: 02.12.2025 | N68: 1 | O68: 6.753401 | P68: Magic The Gathering
A69: 1384 | B69: 1178144974 | C69: 1185364801 | D69: CardMarket exacto | E69: Fountainport | F69: Bloomburrow | G69: Inglés | H69: 4 | I69: 24.82 | J69: 37.27 | K69: 37.27 | L69: teff13 | M69: 05.12.2024 | N69: 4 | O69: 9.3175 | P69: Magic The Gathering
A70: 1402 | B70: 1177000590 | C70: 1211757537 | D70: CardMarket exacto | E70: The Wandering Emperor (V.2) | F70: Kamigawa: Neon Dynasty: Promos | G70: Inglés | H70: 1 | I70: 18.07 | J70: 8.9810638 | K70: 8.9810638 | L70: yosy-gvng | M70: 16.05.2025 | N70: 1 | O70: 8.981064 | P70: Magic The Gathering
... A83: 1519 | B83: 1167529843 | C83: 1248289480 | D83: CardMarket exacto | E83: Unearth | F83: Double Masters 2022 | G83: Inglés | H83: 4 | I83: 0.79896523 | J83: 1.8866667 | K83: 1.8866667 | L83: adriangd | M83: 15.01.2026 | N83: 4 | O83: 0.471667 | P83: Magic The Gathering
A84: 1527 | B84: 1166475023 | C84: CVSALE-1166475023-01 | D84: Sintético sin pedido identificado | E84: Warren Soultrader | F84: Modern Horizons 3 | G84: Inglés | H84: 4 | I84: 19.126154 | J84: 16.56 | K84: 16.56 | L84: No identificado | M84: 21.07.2024 | N84: 4 | O84: 4.14 | P84: Magic The Gathering
A85: 1544 | B85: 1165702710 | C85: 1238166844 | D85: CardMarket exacto | E85: Ob Nixilis, the Adversary | F85: Streets of New Capenna | G85: Inglés | H85: 2 | I85: 16.22 | J85: 3.1532902 | K85: 3.1532902 | L85: Raykerebagon | M85: 06.11.2025 | N85: 1 | O85: 3.15329 | P85: Magic The Gathering
A86: 1587 | B86: 1163389136 | C86: 1167365531 | D86: CardMarket exacto | E86: Wrath of the Skies (V.2) | F86: Modern Horizons 3: Extras | G86: Inglés | H86: 1 | I86: 4.72 | J86: 9.17 | K86: 9.17 | L86: Penesaurio | M86: 08.08.2024 | N86: 1 | O86: 9.17 | P86: Magic The Gathering
A87: 1593 | B87: 1163347613 | C87: 1178747825 | D87: CardMarket exacto | E87: Suncleanser | F87: Core 2019 | G87: Inglés | H87: 4 | I87: 2.62 | J87: 24.970806 | K87: 24.970806 | L87: Mazvigosl | M87: 22.10.2024 | N87: 4 | O87: 6.242702 | P87: Magic The Gathering
A88: 1601 | B88: 1162882331 | C88: 1171287033 | D88: CardMarket exacto | E88: Arena of Glory | F88: Modern Horizons 3 | G88: Inglés | H88: 1 | I88: 2.1682569 | J88: 5.72 | K88: 5.72 | L88: xXxMoRFeOxXx | M88: 30.08.2024 | N88: 1 | O88: 5.72 | P88: Magic The Gathering
A89: 1610 | B89: 1161780833 | C89: 1191509329 | D89: CardMarket exacto | E89: Force of Despair | F89: Modern Horizons | G89: Japonés | H89: 2 | I89: 15.2 | J89: 13.23 | K89: 13.23 | L89: augustojas | M89: 17.01.2025 | N89: 2 | O89: 6.615 | P89: Magic The Gathering
A90: 1611 | B90: 1161770456 | C90: 1179893768 | D90: CardMarket exacto | E90: Ajani, Nacatl Pariah // Ajani, Nacatl Avenger | F90: Modern Horizons 3: Extras | G90: Inglés | H90: 4 | I90: 79.27 | J90: 89.27 | K90: 89.27 | L90: Veilanof | M90: 31.10.2024 | N90: 4 | O90: 22.3175 | P90: Magic The Gathering
A91: 1616 | B91: 1161596697 | C91: 1254403240 | D91: CardMarket exacto | E91: Cloudshift | F91: Avacyn Restored | G91: Español | H91: 1 | I91: 0.33964286 | J91: 1.0777778 | K91: 1.0777778 | L91: Fabuloussanta | M91: 21.02.2026 | N91: 1 | O91: 1.077778 | P91: Magic The Gathering
A92: 1626 | B92: 1161346361 | C92: 1165660431 | D92: CardMarket exacto | E92: Phlage, Titan of Fire's Fury | F92: Modern Horizons 3 | G92: Inglés | H92: 2 | I92: 41.47 | J92: 47.42 | K92: 47.42 | L92: Jesval | M92: 19.07.2024 | N92: 1 | O92: 47.42 | P92: Magic The Gathering
A93: 1627 | B93: 1161289000 | C93: 1164742270 | D93: CardMarket exacto | E93: Phlage, Titan of Fire's Fury | F93: Modern Horizons 3 | G93: Inglés | H93: 2 | I93: 37.3 | J93: 155.32 | K93: 155.32 | L93: Knowny | M93: 17.07.2024 | N93: 3 | O93: 51.773333 | P93: Magic The Gathering
A94: 1635 | B94: 1161221042 | C94: 1195175019 | D94: CardMarket exacto | E94: Thassa's Oracle | F94: Theros Beyond Death | G94: Chino-T | H94: 1 | I94: 12.21 | J94: 15.28 | K94: 15.28 | L94: Liquiidzx | M94: 11.02.2025 | N94: 1 | O94: 15.28 | P94: Magic The Gathering
A95: 1636 | B95: 1161161813 | C95: 1164617239 | D95: CardMarket exacto | E95: Nethergoyf | F95: Modern Horizons 3 | G95: Inglés | H95: 4 | I95: 167.6 | J95: 21.873793 | K95: 21.873793 | L95: Oyea2000Hacha | M95: 13.07.2024 | N95: 1 | O95: 21.873793 | P95: Magic The Gathering
A96: 1637 | B96: 1161161813 | C96: 1178792325 | D96: CardMarket exacto | E96: Psychic Frog | F96: Modern Horizons 3 | G96: Inglés | H96: 4 | I96: 20 | J96: 69.27 | K96: 69.27 | L96: SrBau | M96: 17.10.2024 | N96: 4 | O96: 17.3175 | P96: Magic The Gathering
... A113: 1723 | B113: 1157532571 | C113: 1242651146 | D113: CardMarket exacto | E113: Foil | F113: Prophecy | G113: Japonés | H113: 1 | I113: 3.977095 | J113: 6.28 | K113: 6.28 | L113: joselu350z | M113: 05.12.2025 | N113: 1 | O113: 6.28 | P113: Magic The Gathering
A114: 1741 | B114: 1156805109 | C114: CVSALE-1156805109-01 | D114: Sintético sin pedido identificado | E114: Naturalize | F114: Onslaught | G114: Inglés | H114: 3 | I114: 5.283964 | J114: 7.3484838 | K114: 7.3484838 | L114: No identificado | M114: 10.05.2024 | N114: 3 | O114: 2.449495 | P114: Magic The Gathering
A115: 1765 | B115: 1155735787 | C115: 1161471470 | D115: CardMarket exacto | E115: Daze | F115: Nemesis | G115: Inglés | H115: 1 | I115: 2.6877884 | J115: 2.4028912 | K115: 2.4028912 | L115: Cachopito | M115: 19.06.2024 | N115: 1 | O115: 2.402891 | P115: Magic The Gathering
A116: 1769 | B116: 1155733905 | C116: 1161381058 | D116: CardMarket exacto | E116: Chill | F116: Tempest | G116: Español | H116: 2 | I116: 2.2218182 | J116: 3.12 | K116: 3.12 | L116: eduardomtg | M116: 19.06.2024 | N116: 2 | O116: 1.56 | P116: Magic The Gathering
A117: 1798 | B117: 1154966443 | C117: 1245445493 | D117: CardMarket exacto | E117: Yasharn, Implacable Earth | F117: Zendikar Rising | G117: Inglés | H117: 2 | I117: 1 | J117: 0.36259191 | K117: 0.36259191 | L117: KingKenji | M117: 19.12.2025 | N117: 1 | O117: 0.362592 | P117: Magic The Gathering
A118: 1816 | B118: 1153278715 | C118: 1232760932 | D118: CardMarket exacto | E118: Amulet of Vigor | F118: Worldwake | G118: Español | H118: 3 | I118: 52.039385 | J118: 23.28 | K118: 23.28 | L118: alextormento | M118: 02.10.2025 | N118: 1 | O118: 23.28 | P118: Magic The Gathering
A119: 1828 | B119: 1152048190 | C119: 1238163768 | D119: CardMarket exacto | E119: Prismatic Ending (V.1) | F119: Modern Horizons 2: Extras | G119: Español | H119: 4 | I119: 7.76 | J119: 9.13 | K119: 9.13 | L119: Hacter | M119: 01.11.2025 | N119: 4 | O119: 2.2825 | P119: Magic The Gathering
A120: 1832 | B120: 1151713514 | C120: 1247478896 | D120: CardMarket exacto | E120: Cultivator Colossus (V.2) | F120: Innistrad: Crimson Vow: Promos | G120: Inglés | H120: 1 | I120: 7.22 | J120: 5.28 | K120: 5.28 | L120: Mikota | M120: 14.01.2026 | N120: 1 | O120: 5.28 | P120: Magic The Gathering
A121: 1853 | B121: 1150722256 | C121: 1162835755 | D121: CardMarket exacto | E121: Flooded Strand | F121: Khans of Tarkir | G121: Español | H121: 2 | I121: 42.978178 | J121: 65.27 | K121: 65.27 | L121: Noeperez | M121: 16.07.2024 | N121: 4 | O121: 16.3175 | P121: Magic The Gathering
A122: 1860 | B122: 1150694432 | C122: 1244990507 | D122: CardMarket exacto | E122: Persist | F122: Modern Horizons 2 | G122: Inglés | H122: 1 | I122: 1.9658065 | J122: 12.73976 | K122: 12.73976 | L122: eGodrama | M122: 17.12.2025 | N122: 4 | O122: 3.18494 | P122: Magic The Gathering
A123: 1866 | B123: 1149149024 | C123: 1149346155 | D123: CardMarket exacto | E123: Ardent Plea | F123: Alara Reborn | G123: Español | H123: 2 | I123: 9.8133333 | J123: 10.21 | K123: 10.21 | L123: dannylarousso | M123: 22.03.2024 | N123: 1 | O123: 10.21 | P123: Magic The Gathering
A124: 1887 | B124: 1147180690 | C124: 1247290743 | D124: CardMarket exacto | E124: Sundown Pass | F124: Universes Beyond: Doctor Who | G124: Inglés | H124: 1 | I124: 6.22 | J124: 5.3329843 | K124: 5.3329843 | L124: SantiBosch | M124: 29.12.2025 | N124: 1 | O124: 5.332984 | P124: Magic The Gathering
A125: 1893 | B125: 1147134772 | C125: 1257189486 | D125: CardMarket exacto | E125: Loran's Escape | F125: The Brothers' War | G125: Inglés | H125: 4 | I125: 0.78335152 | J125: 4.6 | K125: 4.6 | L125: mariozeferino | M125: 19.02.2026 | N125: 4 | O125: 1.15 | P125: Magic The Gathering
A126: 1895 | B126: 1147134772 | C126: 1189912274 | D126: CardMarket exacto | E126: Monstrous Rage | F126: Wilds of Eldraine | G126: Inglés | H126: 3 | I126: 1.2095869 | J126: 13.29 | K126: 13.29 | L126: MiquelSenpai | M126: 10.01.2025 | N126: 4 | O126: 3.3225 | P126: Magic The Gathering
... A129: 1931 | B129: 1145607221 | C129: 1252378732 | D129: CardMarket exacto | E129: Stonecoil Serpent | F129: Throne of Eldraine | G129: Inglés | H129: 2 | I129: 3.02 | J129: 0.62745098 | K129: 0.62745098 | L129: Squirle | M129: 28.01.2026 | N129: 1 | O129: 0.627451 | P129: Magic The Gathering
A130: 1934 | B130: 1145214768 | C130: CVSALE-1145214768-01 | D130: Sintético sin pedido identificado | E130: Breeding Pool | F130: Gatecrash | G130: Inglés | H130: 1 | I130: 16.17 | J130: 47.62 | K130: 47.62 | L130: No identificado | M130: 10.02.2024 | N130: 1 | O130: 47.62 | P130: Magic The Gathering
A131: 1958 | B131: 1143910475 | C131: CVSALE-1143910475-01 | D131: Sintético sin pedido identificado | E131: Of One Mind | F131: Ikoria: Lair of Behemoths | G131: Inglés | H131: 4 | I131: 4.3588235 | J131: 3.8216667 | K131: 3.8216667 | L131: No identificado | M131: 31.01.2024 | N131: 4 | O131: 0.955417 | P131: Magic The Gathering
A132: 1984 | B132: 1143280006 | C132: 1249268818 | D132: CardMarket exacto | E132: Magus of the Moon | F132: Time Spiral Remastered | G132: Inglés | H132: 2 | I132: 21.22 | J132: 11.35 | K132: 11.35 | L132: Overrchepa | M132: 09.01.2026 | N132: 2 | O132: 5.675 | P132: Magic The Gathering
A133: 1994 | B133: 1142560986 | C133: 1143358804 | D133: CardMarket exacto | E133: Spirebluff Canal | F133: Kaladesh | G133: Inglés | H133: 1 | I133: 16.735 | J133: 13.21 | K133: 13.21 | L133: Wiyou13 | M133: 01.02.2024 | N133: 1 | O133: 13.21 | P133: Magic The Gathering
A134: 1996 | B134: 1142556696 | C134: CVSALE-1142556696-01 | D134: Sintético sin pedido identificado | E134: Scalding Tarn | F134: Modern Horizons 2 | G134: Inglés | H134: 2 | I134: 48.369278 | J134: 54.42 | K134: 54.42 | L134: No identificado | M134: 20.01.2024 | N134: 2 | O134: 27.21 | P134: Magic The Gathering
A135: 1997 | B135: 1142556696 | C135: 1166492703 | D135: CardMarket exacto | E135: Ledger Shredder | F135: Streets of New Capenna: Extras | G135: Inglés | H135: 3 | I135: 57.300722 | J135: 47.424286 | K135: 47.424286 | L135: hotcoffeegg | M135: 26.07.2024 | N135: 3 | O135: 15.808095 | P135: Magic The Gathering
A136: 2000 | B136: 1141270423 | C136: 1152040638 | D136: CardMarket exacto | E136: Plaza of Heroes | F136: Dominaria United | G136: Inglés | H136: 1 | I136: 7.71 | J136: 7.21 | K136: 7.21 | L136: Prometeu82 | M136: 11.04.2024 | N136: 1 | O136: 7.21 | P136: Magic The Gathering
A137: 2002 | B137: 1141146578 | C137: 1149672466 | D137: CardMarket exacto | E137: Shipwreck Marsh | F137: Innistrad: Midnight Hunt | G137: Inglés | H137: 1 | I137: 3.2532872 | J137: 7.12 | K137: 7.12 | L137: FrachLouz | M137: 26.03.2024 | N137: 2 | O137: 3.56 | P137: Magic The Gathering
A138: 2012 | B138: 1139362216 | C138: CVSALE-1139362216-01 | D138: Sintético sin pedido identificado | E138: Cut Down | F138: Dominaria United | G138: Inglés | H138: 4 | I138: 4.4753012 | J138: 9.34 | K138: 9.34 | L138: No identificado | M138: 24.12.2023 | N138: 4 | O138: 2.335 | P138: Magic The Gathering
...

Sheet Listas de valores
A1: Idioma | B1: Tipo Operación | C1: TCG
A2: Inglés | B2: Compra | C2: Magic The Gathering
A3: Español | B3: Venta | C3: One Piece
A4: Japonés | B4: Cancelado | C4: Riftbound
A5: Alemán | C5: Mixto
A6: Francés
A7: Italiano
A8: Portugués
A9: Ruso
A10: Coreano
A11: Chino
A12: Chino-S
A13: Chino-T
